Workbook
Name __FDS_HYPERLINK_TOGGLE_STATE__: "ON"
Name __FDS_UNIQUE_RANGE_ID_GENERATOR_COUNTER: 28
Name __FDS_USED_FOR_REUSING_RANGE_IDS_RECYCLE: {16,16,16,16,16,16,16,16,16,16,16}
Name __FDS_USED_FOR_REUSING_RANGE_IDS_RECYCLE: {16,16,16,16,16,16,16,16,16,16,16}
Name __FDS_USED_FOR_REUSING_RANGE_IDS_RECYCLE: {16,16,16,16,16,16,16,16,16,16,16}
Name __FDS_USED_FOR_REUSING_RANGE_IDS_RECYCLE: {16,16,16,16,16,16,16,16,16,16,16}
Name __FDS_USED_FOR_REUSING_RANGE_IDS_RECYCLE: {16,16,16,16,16,16,16,16,16,16,16}
Name __FDS_USED_FOR_REUSING_RANGE_IDS_RECYCLE_1: {16,16,16,16,16,16,16,16,16,16,16}
Name _10a2_: {"Client Name or Project Name"}
Name _11a2_: {"Client Name or Project Name"}
Name _12a2_: {"Client Name or Project Name"}
Name _12a2_: {"Client Name or Project Name"}
Name _12a2_: {"Client Name or Project Name"}
Name _12a2_: {"Client Name or Project Name"}
Name _12a2_: {"Client Name or Project Name"}
Name _12a2__1: {"Client Name or Project Name"}
Name _13a2_: {"Client Name or Project Name"}
Name _14a2_: {"Client Name or Project Name"}
Name _14a2_: {"Client Name or Project Name"}
Name _14a2__1: {"Client Name or Project Name"}
Name _1999E: #REF!
Name _1a1_: {"Client Name or Project Name"}
Name _1a1_: {"Client Name or Project Name"}
Name _1a1_: {"Client Name or Project Name"}
Name _1a1_: {"Client Name or Project Name"}
Name _1a1_: {"Client Name or Project Name"}
Name _1a1__1: {"Client Name or Project Name"}
Name _1Q97A: #REF!
Name _1Q98A: #REF!
Name _1Q99A: #REF!
Name _2000E: #REF!
Name _2001E: #REF!
Name _2002E: #REF!
Name _2003E: #REF!
Name _2004E: #REF!
Name _2005E: #REF!
Name _2006E: #REF!
Name _2007E: #REF!
Name _2008E: #REF!
Name _2a1_: {"Client Name or Project Name"}
Name _2a1_: {"Client Name or Project Name"}
Name _2a1_: {"Client Name or Project Name"}
Name _2a1_: {"Client Name or Project Name"}
Name _2a1_: {"Client Name or Project Name"}
Name _2a1__1: {"Client Name or Project Name"}
Name _2a2_: {"Client Name or Project Name"}
Name _2a2_: {"Client Name or Project Name"}
Name _2a2_: {"Client Name or Project Name"}
Name _2a2_: {"Client Name or Project Name"}
Name _2a2__1: {"Client Name or Project Name"}
Name _2Q97A: #REF!
Name _2Q98A: #REF!
Name _2Q99A: #REF!
Name _3a1_: {"Client Name or Project Name"}
Name _3Q97A: #REF!
Name _3Q98A: #REF!
Name _4a1_: {"Client Name or Project Name"}
Name _4a1_: {"Client Name or Project Name"}
Name _4a1_: {"Client Name or Project Name"}
Name _4a1_: {"Client Name or Project Name"}

Sheet Header(C)
C5: 中国建筑国际(03311.HK)
C6: 更新日期： | D6: =TODAY() -> 46120
C11: 陈彦，CFA | F11: 任嘉禹
C12: (00852)94723508 | F12: 18801066373
C13: yan3.chen@cicc.com.cn | F13: jiayu.ren@cicc.com.cn
C15: 资料来源：万得，彭博，中金公司研究部
A17: 法律声明 一般声明 本资料由中国国际金融股份有限公司（已具备中国证监会批复的证券投资咨询业务资格）制作。本资料中的信息均来源于我们认为可靠的已公开资料，但中国国际金融股份有限公司及其关联机构（以下统称“中金公司”）对这些信息的准确性及完整性不作任何保证。本资料中的信息、意见等均仅供投资者参考之用，不构成对买卖任何证券或其他金融工具的出价或征价或提供任何投资决策建议的服务。该等信息、意见并未考虑到获取本资料人员的具体投资目的、财务状况以及特定需求，在任何时候均不构成对任何人的个人推荐或投资操作性建议。投资者应当对本资料中的信息和意见进行独立评估，自主审慎做出决策并自行承担风险。投资者在依据本资料涉及的内容进行任何决策前，应同时考量各自的投资目的、财务状况和特定需求，并就相关决策咨询专业顾问的意见对依据或者使用本资料所造成的一切后果，中金公司及/或其关联人员均不承担任何责任。 本资料所载的意见、评估及预测仅为本资料出具日的观点和判断。该等意见、评估及预测无需通知即可随时更改。在不同时期，中金公司可能会发出与本资料所载意见、评估及预测不一致的研究资料。 本资料署名分析师可能会不时与中金公司的客户、销售交易人员、其他业务人员或在本资料中针对可能对本资料所涉及的标的证券或其他金融工具的市场价格产生短期影响的催化剂或事件进行交易策略的讨论。这种短期影响的分析可能与分析师已发布的关于相关证券或其他金融工具的目标价、评级、估值、预测等观点相反或不一致，相关的交易策略不同于且也不影响分析师关于其所研究标的证券或其他金融工具的基本面评级。 中金公司的销售人员、交易人员以及其他专业人士可能会依据不同假设和标准、采用不同的分析方法而口头或书面发表与本资料意见及建议不一致的市场评论和/或交易观点。中金公司没有将此意见及建议向资料所有接收者进行更新的义务。中金公司的资产管理部门、自营部门以及其他投资业务部门可能独立做出与本资料中的意见不一致的投资决策。 除非另行说明，本资料中所引用的关于业绩的数据代表过往表现。过往的业绩表现亦不应作为日后回报的预示。我们不承诺也不保证，任何所预示的回报会得以实现。分析中所做的预测可能是基于相应的假设。任何假设的变化可能会显著地影响所预测的回报。 本资料提供给某接收人是基于该接收人被认为有能力独立评估投资风险并就投资决策能行使独立判断。投资的独立判断是指，投资决策是投资者自身基于对潜在投资的目标、需求、机会、风险、市场因素及其他投资考虑而独立做出的。 本资料由受香港证券和期货委员会监管的中国国际金融香港证券有限公司（“中金香港”）于香港提供。香港的投资者若有任何关于中金公司研究资料的问题请直接联系中金香港的销售交易代表。 本资料由受新加坡金融管理局监管的中国国际金融（新加坡）有限公司 (“中金新加坡”) 于新加坡向符合新加坡《证券期货法》定义下的认可投资者及/或机构投资者提供。提供本资料于此类投资者, 有关财务顾问将无需根据新加坡之《财务顾问法》第36 条就任何利益及/或其代表就任何证券利益进行披露。有关本资料之任何查询，在新加坡获得本资料的人员可联系中金新加坡销售交易代表。 本资料由受金融服务监管局监管的中国国际金融（英国）有限公司（“中金英国”）于英国提供。本资料有关的投资和服务仅向符合《2000年金融服务和市场法2005年（金融推介）令》第19（5）条、 38条、 47条以及 49条规定的人士提供。本资料并未打算提供给零售客户使用。在其他欧洲经济区国家，本资料向被其本国认定为专业投资者（或相当性质）的人士提供。 本资料将依据其他国家或地区的法律法规和监管要求于该国家或地区提供。 特别声明 在法律许可的情况下，中金公司可能与本资料中提及公司正在建立或争取建立业务关系或服务关系。因此，投资者应当考虑到中金公司及/或其相关人员可能存在影响本资料观点客观性的潜在利益冲突。 与本资料所含具体公司相关的披露信息请访https://research.cicc.com/footer/disclosures，亦可参见近期已发布的关于该等公司的具体研究资料。 中金研究基本评级体系说明： 分析师采用相对评级体系，股票评级分为跑赢行业、中性、跑输行业（定义见下文）。 除了股票评级外，中金公司对覆盖行业的未来市场表现提供行业评级观点，行业评级分为超配、标配、低配（定义见下文）。 我们在此提醒您，中金公司对研究覆盖的股票不提供买入、卖出评级。跑赢行业、跑输行业不等同于买入、卖出。投资者应仔细阅读中金公司研究报告中的所有评级定义。请投资者仔细阅读研究报告全文，以获取比较完整的观点与信息，不应仅仅依靠评级来推断结论。在任何情形下，评级（或研究观点）都不应被视为或作为投资建议。投资者买卖证券或其他金融产品的决定应基于自身实际具体情况（比如当前的持仓结构）及其他需要考虑的因素。 股票评级定义：  跑赢行业（OUTPERFORM）：未来6~12个月，分析师预计个股表现超过同期其所属的中金行业指数；  中性（NEUTRAL）：未来6~12个月，分析师预计个股表现与同期其所属的中金行业指数相比持平；  跑输行业（UNDERPERFORM）：未来6~12个月，分析师预计个股表现不及同期其所属的中金行业指数。 行业评级定义：  超配（OVERWEIGHT）：未来6~12个月，分析师预计某行业会跑赢大盘10%以上；  标配（EQUAL-WEIGHT）：未来6~12个月，分析师预计某行业表现与大盘的关系在-10%与10%之间；  低配（UNDERWEIGHT）：未来6~12个月，分析师预计某行业会跑输大盘10%以上。 研究报告评级分布可从https://research.cicc.com/footer/disclosures 获悉。 本报告的版权仅为中金公司所有，未经书面许可任何机构和个人不得以任何形式转发、翻版、复制、刊登、发表或引用。

Sheet Header(E)
C5: China State Construction Int'l(03311.HK)
C6: update as of | D6: ='Header(C)'!D6 -> 46120
C11: Yan CHEN, CFA | F11: Jiayu REN
C12: (00852)94723508 | F12: 18801066373
C13: yan3.chen@cicc.com.cn | F13: jiayu.ren@cicc.com.cn
C15: Source: Wind, Bloomberg, CICC Research
A17: General Disclosures This document has been produced by China International Capital Corporation Hong Kong Securities Limited (CICCHKS). This document is based on information available to the public that we consider reliable, but CICCHKS and its associated company(ies)(collectively, hereinafter “CICC”) do not represent that it is accurate or complete. The information and opinions contained herein are for investors’ reference only and do not take into account the particular investment objectives, financial situation, or needs of any client, and are not an offer to buy or sell or a solicitation of an offer to buy or sell any securities/financial products or to participate in any particular trading strategy. Under no circumstances shall the information contained herein or the opinions expressed herein constitute a personal recommendation to anyone. Investors should make their own independent evaluation of the information contained in this research document, consider their own individual investment objectives, financial situation and particular needs. CICC does not provide tax, accounting, or legal advice to our clients, and all investors are advised to consult with their tax, accounting, or legal advisers regarding any potential investment. Neither CICC nor its related persons shall be liable in any manner whatsoever for any consequences of any reliance thereon or usage thereof. The performance information (including any expression of opinion or forecast) herein reflect the most up-to-date opinions, speculations and forecasts at the time of the document’s production and publication. Such opinions, speculations and forecasts are subject to change and may be amended without any notification. At different periods, CICC may release documents which are inconsistent with the opinions, speculations and forecasts contained herein. The analysts named in this document may have from time to time discussed with our clients, including CICC salespeople, traders, and other professionals, or may discuss in this document, trading strategies that reference catalysts or events that may have a near-term impact on the market price of the equity securities discussed in this document, which impact may be directionally counter to the analysts' published price target expectations for such stocks. Any such trading strategies are distinct from and do not affect the analysts' fundamental equity rating for such stocks as described herein. CICC’s salespeople, traders, and other professionals may provide oral or written market commentary or trading ideas that may be inconsistent with, and reach different conclusions from, the recommendations and opinions presented in this document. Such ideas or recommendations reflect the different assumptions, views and analytical methods of the persons who prepared them, and CICC is under no obligation to ensure that such other trading ideas or recommendations are brought to the attention of any recipient of this document. CICC’s asset management area, proprietary trading desks and other investing businesses may make investment decisions that are inconsistent with the recommendations or opinions expressed in this document. Unless stated otherwise, any performance data quoted represents past performance. Past performance is not an indicator of future performance. No representation or warranty is made that any returns indicated will be achieved. Certain assumptions may have been made in this analysis which has resulted in any returns detailed herein. Changes to the assumptions may have a material impact on any returns detailed. To the extent this material is provided to any recipient, this material is provided solely on the basis that the recipient has the capability to independently evaluate investment risk and is exercising independent judgment in evaluating investment decisions in that its investment decisions will be based on its own independent assessment of the opportunities and risks presented by a potential investment, market factors and other investment considerations. This document is distributed in Hong Kong by CICCHKS, which is regulated by the Securities and Futures Commission. Queries concerning CICC Research from readers in Hong Kong should be directed to our Hong Kong sales representatives. This document is distributed in Singapore only to accredited investors and/or institutional investors, as defined in the Securities and Futures Act, by China International Capital Corporation (Singapore) Pte. Limited (“CICCSG”), which is regulated by the Monetary Authority of Singapore. By virtue of distribution by CICCSG to these categories of investors in Singapore, disclosure under Section 36 of the Financial Adviser Act (which relates to disclosure of a financial adviser’s interest and/or its representative’s interest in securities) is not required. Recipients of this document in Singapore should contact CICCSG in respect of any matter arising from or in connection with this document. This document is not intended for and should not be distributed or passed on, directly or indirectly, to any other person in the jurisdiction of Singapore. This document is distributed in the United Kingdom by China International Capital Corporation (UK) Limited (“CICCUK”), which is authorized and regulated by the Financial Conduct Authority. The investments and services to which this document relates are only available to persons of a kind described in Article 19 (5), 38, 47 and 49 of the Financial Services and Markets Act 2000 (Financial Promotion) Order 2005. This document is not intended for retail clients. In other EEA countries, the document is issued to persons regarded as professional investors (or equivalent) in their home jurisdiction. This document will be made available in other jurisdictions pursuant to the applicable laws and regulations in those particular jurisdictions. Special Disclosures CICC does and seeks to do business with companies covered in CICC Research. As a result, investors should be aware that CICC and/or its associated persons may have a conflict of interest that could affect the objectivity of this document. Disclosures in relation to the Companies contained this document could be found at https://research.cicc.com/footer/disclosures, or in the published latest company-specific research. Guide to the CICC Fundamental Equity Research Rating System: Our analysts use a stock rating framework in which they rate stocks as OUTPERFORM, NEUTRAL or UNDERPERFORM (see definitions below). In addition to the stock rating, we provide industry views which rate the outlook for the industry coverage universe as OVERWEIGHT, EQUAL-WEIGHT or UNDERWEIGHT (see definitions below). CICC does not assign ratings of BUY, HOLD or SELL to the stocks we cover. OUTPERFORM, NEUTRAL or UNDERPERFORM are not the equivalent of BUY, HOLD or SELL. Investors should carefully read the definitions of all ratings used in CICC Research. In addition, since CICC Research contains more complete information concerning the analyst's views, investors should carefully read CICC Research, in its entirety, and not infer the contents from the rating alone. In any case, ratings (or research) should not be used or relied upon as investment advice. An investor's decision to buy or sell a stock should depend on individual circumstances (such as the investor's existing holdings) and other considerations. Explanation of Stock Ratings:  OUTPERFORM: Our analysts expect the stock’s return to exceed the return of the corresponding CICC sector index over the next 6~12 months;  NEUTRAL: Our analysts expect the stock’s return to be in line with the return of the corresponding CICC sector index over the next 6~12 months;  UNDERPERFORM: Our analysts expect the stock’s return to be below the return of the corresponding CICC sector index over the next 6~12 months. Explanation of Industry Ratings:  OVERWEIGHT: Our analysts expect the sector to outperform the market by 10% or more over the next 6~12 months;  EQUAL-WEIGHT: Our analysts expect the sector to end up between 10% below and 10% above the market over the next 6~12 months;  UNDERWEIGHT: Our analysts expect the sector to fall behind the market by 10% or more over the next 6~12 months. Distribution of ratings is available at https://research.cicc.com/footer/disclosures. Copyright of this document belongs to CICC. Any form of unauthorized distribution, reproduction, publication, release or quotation is prohibited without CICC’s written permission.

Sheet Header(E)-US
C5: China State Construction Int'l(03311.HK)
C6: update as of | D6: ='Header(C)'!D6 -> 46120
C11: Yan CHEN, CFA | F11: Jiayu REN
C12: (00852)94723508 | F12: 18801066373
C13: yan3.chen@cicc.com.cn | F13: jiayu.ren@cicc.com.cn
C15: Source: Wind, Bloomberg, CICC Research
A17: General Disclosures This document has been produced by China International Capital Corporation Hong Kong Securities Limited (CICCHKS). This document is based on information available to the public that we consider reliable, but CICCHKS and its associated company(ies)(collectively, hereinafter “CICC”) do not represent that it is accurate or complete. The information and opinions contained herein are for investors’ reference only and do not take into account the particular investment objectives, financial situation, or needs of any client, and are not an offer to buy or sell or a solicitation of an offer to buy or sell any securities/ financial products or to participate in any particular trading strategy. Under no circumstances shall the information contained herein or the opinions expressed herein constitute a personal recommendation to anyone. Investors should make their own independent evaluation of the information contained in this research document, consider their own individual investment objectives, financial situation and particular needs. CICC does not provide tax, accounting, or legal advice to our clients, and all investors are advised to consult with their tax, accounting, or legal advisers regarding any potential investment. Neither CICC nor its related persons shall be liable in any manner whatsoever for any consequences of any reliance thereon or usage thereof. The performance information (including any expression of opinion or forecast) herein reflect the most up-to-date opinions, speculations and forecasts at the time of the document’s production and publication. Such opinions, speculations and forecasts are subject to change and may be amended without any notification. At different periods, CICC may release documents which are inconsistent with the opinions, speculations and forecasts contained herein. The analysts named in this document may have from time to time discussed with our clients, including CICC salespeople, traders, and other professionals, or may discuss in this document, trading strategies that reference catalysts or events that may have a near-term impact on the market price of the equity securities discussed in this document, which impact may be directionally counter to the analysts' published price target expectations for such stocks. Any such trading strategies are distinct from and do not affect the analysts' fundamental equity rating for such stocks as described herein. CICC’s salespeople, traders, and other professionals may provide oral or written market commentary or trading ideas that may be inconsistent with, and reach different conclusions from, the recommendations and opinions presented in this document. Such ideas or recommendations reflect the different assumptions, views and analytical methods of the persons who prepared them, and CICC is under no obligation to ensure that such other trading ideas or recommendations are brought to the attention of any recipient of this document. CICC’s asset management area, proprietary trading desks and other investing businesses may make investment decisions that are inconsistent with the recommendations or opinions expressed in this document. Unless stated otherwise, any performance data quoted represents past performance. Past performance is not an indicator of future performance. No representation or warranty is made that any returns indicated will be achieved. Certain assumptions may have been made in this analysis which has resulted in any returns detailed herein. Changes to the assumptions may have a material impact on any returns detailed. To the extent this material is provided to any recipient, this material is provided solely on the basis that the recipient has the capability to independently evaluate investment risk and is exercising independent judgment in evaluating investment decisions in that its investment decisions will be based on its own independent assessment of the opportunities and risks presented by a potential investment, market factors and other investment considerations. This document is distributed in Hong Kong by CICCHKS, which is regulated by the Securities and Futures Commission. Queries concerning CICC Research from readers in Hong Kong should be directed to our Hong Kong sales representatives. This document is distributed in Singapore only to accredited investors and/or institutional investors, as defined in the Securities and Futures Act, by China International Capital Corporation (Singapore) Pte. Limited (“CICCSG”), which is regulated by the Monetary Authority of Singapore. By virtue of distribution by CICCSG to these categories of investors in Singapore, disclosure under Section 36 of the Financial Adviser Act (which relates to disclosure of a financial adviser’s interest and/or its representative’s interest in securities) is not required. Recipients of this document in Singapore should contact CICCSG in respect of any matter arising from or in connection with this document. This document is not intended for and should not be distributed or passed on, directly or indirectly, to any other person in the jurisdiction of Singapore. This document is distributed in the United Kingdom by China International Capital Corporation (UK) Limited (“CICCUK”), which is authorized and regulated by the Financial Conduct Authority. The investments and services to which this document relates are only available to persons of a kind described in Article 19 (5), 38, 47 and 49 of the Financial Services and Markets Act 2000 (Financial Promotion) Order 2005. This document is not intended for retail clients. In other EEA countries, the document is issued to persons regarded as professional investors (or equivalent) in their home jurisdiction. This document will be made available in other jurisdictions pursuant to the applicable laws and regulations in those particular jurisdictions. Special Disclosures CICC does and seeks to do business with companies covered in CICC Research. As a result, investors should be aware that CICC and/or its associated persons may have a conflict of interest that could affect the objectivity of this document. Disclosures in relation to the Companies contained this document could be found at https://research.cicc.com/footer/disclosures, or in the published latest company-specific research. Guide to the CICC Fundamental Equity Research Rating System: Our analysts use a stock rating framework in which they rate stocks as OUTPERFORM, NEUTRAL or UNDERPERFORM (see definitions below). In addition to the stock rating, we provide industry views which rate the outlook for the industry coverage universe as OVERWEIGHT, EQUAL-WEIGHT or UNDERWEIGHT (see definitions below). CICC does not assign ratings of BUY, HOLD or SELL to the stocks we cover. OUTPERFORM, NEUTRAL or UNDERPERFORM are not the equivalent of BUY, HOLD or SELL. Investors should carefully read the definitions of all ratings used in CICC Research. In addition, since CICC Research contains more complete information concerning the analyst's views, investors should carefully read CICC Research, in its entirety, and not infer the contents from the rating alone. In any case, ratings (or research) should not be used or relied upon as investment advice. An investor's decision to buy or sell a stock should depend on individual circumstances (such as the investor's existing holdings) and other considerations. Explanation of Stock Ratings:  OUTPERFORM: Our analysts expect the stock’s return to exceed the return of the corresponding CICC sector index over the next 6~12 months;  NEUTRAL: Our analysts expect the stock’s return to be in line with the return of the corresponding CICC sector index over the next 6~12 months;  UNDERPERFORM: Our analysts expect the stock’s return to be below the return of the corresponding CICC sector index over the next 6~12 months. Explanation of Industry Ratings:  OVERWEIGHT: Our analysts expect the sector to outperform the market by 10% or more over the next 6~12 months;  EQUAL-WEIGHT: Our analysts expect the sector to end up between 10% below and 10% above the market over the next 6~12 months;  UNDERWEIGHT: Our analysts expect the sector to fall behind the market by 10% or more over the next 6~12 months. Distribution of ratings is available at https://research.cicc.com/footer/disclosures. Copyright of this document belongs to CICC. Any form of unauthorized distribution, reproduction, publication, release or quotation is prohibited without CICC’s written permission. US Regulatory Disclosures Analyst Certification The analysts who prepared the research document contained herein hereby certify pursuant to Regulation AC of the U.S. Securities and Exchange Commission (the "SEC") that: (i) the views expressed in this research document accurately reflect my personal views about the subject securities and issuers; and (ii) no part of my compensation was, is, or will be, directly or indirectly, related to the specific recommendations or views expressed in this research document. Foreign Broker-Dealer Disclosure This research document was prepared by China International Capital Corporation Limited and China International Capital Corporation Hong Kong Securities Limited (hereinafter "CICC"). CICC is not a registered broker-dealer in the United States and, therefore, is not subject to U.S. rules regarding the preparation of research documents and the independence of research analysts. This research document is provided for distribution to “major U.S. institutional investors” in reliance on the exemption from registration provided by Rule 15a-6 of the U.S. Securities Exchange Act of 1934, as amended (the “Exchange Act”). Any U.S. recipient of this research document wishing to effect any transaction to buy or sell securities or related financial instruments based on the information provided in this research document should do so only through CICC US Securities, Inc. (hereinafter "CICC US"), a registered broker-dealer in the United States. Under no circumstances should any recipient of this research document effect any transaction to buy or sell securities or related financial instruments through CICC. CICC US accepts responsibility for the contents of this research document, subject to the terms set out below, to the extent that it is delivered to a U.S. person other than a major U.S. institutional investor. The analyst whose name appears in this research document is not registered or qualified as a research analyst with the Financial Industry Regulatory Authority (“FINRA”) and may not be an associated person of CICC US and, therefore, may not be subject to applicable restrictions under FINRA Rules on communications with a subject company, public appearances and trading securities held by a research analyst account.

Sheet RAWS
A1: @STOCK_CNAME | B1: 证券简称 | C1: Company Name | D1: China State Construction | BG1: 北京市 | CA1: 推荐 | CB1: FY | CC1: 千万 | CD1: 1995 | CF1: Version2.0 | CG1: 1 | CH1: 上调至 | CI1: Upgrade to | CJ1: 1 | CK1: 推荐 | CL1: BUY
A2: @STOCK_CODE | B2: 证券代码 | C2: Ticker | D2: 3311 | BG2: 上海市 | CA2: 审慎推荐 | CB2: 1Q | CC2: 百万 | CD2: 1996 | CG2: 2 | CH2: 下调至 | CI2: Downgrade to | CJ2: 3 | CK2: 中性 | CL2: HOLD
A3: @INSTTYPE | B3: 模板类型 | C3: Instrument Type | D3: HKINDU | BG3: 广东省 | CA3: 中性 | CB3: 1H | CC3: 万 | CD3: 1997 | CG3: 3 | CH3: 维持 | CI3: Maintain | CJ3: 5 | CK3: 回避 | CL3: SELL
A4: @REC_DIRECTION | B4: 评级方向 | C4: Direction | D4: Maintain | BG4: 天津市 | CA4: 回避 | CB4: 3Q | CC4: 千 | CD4: 1998 | CG4: 4 | CH4: 首次覆盖 | CI4: Initiate with | CJ4: 6 | CK4: 无评级 | CL4: Not rated
A5: @REC | B5: 投资评级 | C5: Recommendation | D5: OUTPERFORM | BG5: 重庆市 | CA5: 长期 | CD5: 1999 | CG5: 5 | CH5: 再次覆盖 | CI5: Resume at
A6: @TARGET | B6: 目标价格 | C6: Share Price Target | D6: 11.63 | BG6: 江苏省 | CA6: 短期 | CD6: 2000
A7: @COMPROFILE_CN | B7: 公司概述 - 中文 | C7: Company Desc - Chinese | D7: 中建国际是中国建筑(601668.SH)旗下子公司，2005年于联交所主板上市。公司经营范围包括房屋工程如公营房屋、私人住宅楼宇、商业、工业、医疗机械、教育文化设施、酒店、公共建设(机场等)；土木工程如土地平整、公路、桥梁、填海、隧道等；以及机电工程等周边业务。目前已打造成港澳、内地及海外(远东环球830.HK)三大区域平台。 | BG7: 浙江省 | CA7: 减持 | CD7: 2001
A8: @COMPROFILE_EN | B8: 公司概述 - 英文 | C8: Company Desc - English | D8: China State Construction International (CSCI), a subsidiary of CSCEC (601668.SH), was listed on the main board of the Hong Kong Stock Exchange in 2005. The company has built three regional business platforms: mainland China, Hong Kong-Macau and overseas. In Hong Kong and Macau, it is one of the largest housing and infrastructure construction contractors, while in mainland China, it focuses on investing in infrastructure and affordable housing (BT). Its overseas platform is operated by Far East (830.HK), an affiliate whose main business is curtain walls. | BG8: 四川省 | CA8: 无评级 | CD8: 2002
A9: @FINA_YEAR | B9: 报表年份 | C9: Reporting Year | K9: 2010 | L9: 2011 | M9: 2012 | N9: 2013 | O9: 2014 | P9: 2015 | Q9: 2016 | R9: 2017 | S9: 2018 | T9: 2019 | U9: 2020 | V9: 2021 | W9: 2022 | X9: 2023 | Y9: 2024 | Z9: 2025 | AA9: 2026 | AB9: 2027 | BG9: 海南省 | CD9: 2003
A10: @FINA_PERIOD | B10: 报表周期 | C10: Reporting Period | K10: FY | L10: FY | M10: FY | N10: FY | O10: FY | P10: FY | Q10: FY | R10: FY | S10: FY | T10: FY | U10: FY | V10: FY | W10: FY | X10: FY | Y10: FY | Z10: FY | AA10: FY | AB10: FY | BG10: 福建省 | CD10: 2004
A11: @ACCOUNTS_STATUS | B11: 报表状态 | C11: Accounts Status | K11: A | L11: A | M11: A | N11: A | O11: A | P11: A | Q11: A | R11: A | S11: A | T11: A | U11: A | V11: A | W11: A | X11: A | Y11: A | Z11: A | AA11: E | AB11: E | BG11: 山东省 | CA11: Buy | CD11: 2005
A12: @MULTIPLIER | B12: 报表单位 | C12: Unit | K12: 百万 | L12: 百万 | M12: 百万 | N12: 百万 | O12: 百万 | P12: 百万 | Q12: 百万 | R12: 百万 | S12: 百万 | T12: 百万 | U12: 百万 | V12: 百万 | W12: 百万 | X12: 百万 | Y12: 百万 | Z12: 百万 | AA12: 百万 | AB12: 百万 | BG12: 江西省 | CA12: Accumulate | CD12: 2006
A13: @CURRENCY_ENAME | B13: 报表货币单位 | C13: Fundamental Currency | K13: RMB | L13: RMB | M13: RMB | N13: RMB | O13: RMB | P13: RMB | Q13: RMB | R13: RMB | S13: RMB | T13: RMB | U13: RMB | V13: RMB | W13: RMB | X13: RMB | Y13: RMB | Z13: RMB | AA13: RMB | AB13: RMB | BG13: 广西省 | CA13: Hold | CD13: 2007
A14: @DATABEGIN | B14: HK | BG14: 安徽省 | CA14: Reduce | CD14: 2008
B15: 损益表 | C15: Income Statement | BG15: 河北省 | CA15: Sell | CD15: 2009
BG16: 河南省 | CA16: Long-term | CD16: 2010
A17: @HKINDU001 | B17: Revenue | C17: Revenue | K17: =PL!H4 -> 11982.871 | L17: =PL!I4 -> 16379.311 | M17: =PL!J4 -> 21910.66 | N17: =PL!K4 -> 27285.62 | O17: =PL!L4 -> 34439.575 | P17: =PL!M4 -> 38001.876 | Q17: =PL!N4 -> 46207.508 | R17: =PL!O4 -> 50152.524 | ... AB17: =PL!Y4 -> 114194.84 | BG17: 湖北省 | CA17: Short-term | CD17: 2011
A18: @HKINDU002 | B18: Cost of goods sold (-) | C18: Cost of goods sold (-) | K18: =-PL!H19 -> -10667.017 | L18: =-PL!I19 -> -14581.127 | M18: =-PL!J19 -> -19192.443 | N18: =-PL!K19 -> -23539.675 | O18: =-PL!L19 -> -29696.483 | P18: =-PL!M19 -> -32888.761 | Q18: =-PL!N19 -> -40224.63 | R18: =-PL!O19 -> -42537.494 | ... AB18: =-PL!Y19 -> -95642.559 | BG18: 湖南省 | CA18: Not Rated | CD18: 2012
A19: @HKINDU028 | B19: Gross profit | C19: Gross profit | K19: =K17+K18 -> 1315.854 | L19: =L17+L18 -> 1798.184 | M19: =M17+M18 -> 2718.217 | N19: =N17+N18 -> 3745.945 | O19: =O17+O18 -> 4743.092 | P19: =P17+P18 -> 5113.115 | Q19: =Q17+Q18 -> 5982.878 | R19: =R17+R18 -> 7615.03 | ... AB19: =AB17+AB18 -> 18552.281 | BG19: 陕西省 | CD19: 2013
A20: @HKINDU026 | B20: Other gains, net | C20: Other gains, net | K20: =PL!H61+PL!H88 -> 188.889 | L20: =PL!I61+PL!I88 -> 422.315 | M20: =PL!J61+PL!J88 -> 371.09 | N20: =PL!K61+PL!K88 -> 436.542 | O20: =PL!L61+PL!L88 -> 475.339 | P20: =PL!M61+PL!M88 -> 1159.441 | Q20: =PL!N61+PL!N88 -> 1260.12 | R20: =PL!O61+PL!O88 -> 747.678 | ... AB20: =PL!Y61+PL!Y88 -> 281.47053 | BG20: 山西省 | CA20: Consolidated | CB20: A | CC20: RMB | CD20: 2014
A21: @HKINDU008 | B21: Total Operating Expenses (-) | C21: Total Operating Expenses (-) | F21: =F22+F23+F24+F2 -> 0 | K21: =-PL!H79 -> -497.888 | L21: =-PL!I79 -> -577.157 | M21: =-PL!J79 -> -740.074 | N21: =-PL!K79 -> -1042.458 | O21: =-PL!L79 -> -1033.14 | P21: =-PL!M79 -> -1007.396 | Q21: =-PL!N79 -> -1106.084 | R21: =-PL!O79 -> -1394.668 | ... AB21: =-PL!Y79 -> -2460.8988 | BG21: 黑龙江省 | CB21: E | CC21: HKD | CD21: 2016
A22: @HKINDU004 | B22: Selling expenses | C22: Selling expenses | K22: =-PL!H81 -> -4.736 | L22: =-PL!I81 -> -15.523 | M22: =-PL!J81 -> -5.505 | N22: =-PL!K81 -> -82.946 | O22: =-PL!L81 -> -133.871 | P22: =-PL!M81 -> 0 | Q22: =-PL!N81 -> 0 | R22: =-PL!O81 -> 0 | ... AB22: =-PL!Y81 -> 0 | BG22: 辽宁省 | CB22: P | CC22: USD | CD22: 2017
A23: @HKINDU005 | B23: General and administrative expenses | C23: General and administrative expenses | K23: =-PL!H83 -> -466.766 | L23: =-PL!I83 -> -538.68 | M23: =-PL!J83 -> -704.139 | N23: =-PL!K83 -> -959.512 | O23: =-PL!L83 -> -899.269 | P23: =-PL!M83 -> 0 | Q23: =-PL!N83 -> 0 | R23: =-PL!O83 -> 0 | ... AB23: =-PL!Y83 -> 0 | BG23: 吉林省 | CC23: SGD | CD23: 2015
A24: @HKINDU006 | B24: R&D expenses | C24: R&D expenses | BG24: 云南省 | CC24: CAD | CD24: 2018
A25: @HKINDU003 | B25: Other Operating Expenses (-) | C25: Other Operating Expenses (-) | K25: =K21-K22-K23 -> -26.386 | L25: =L21-L22-L23 -> -22.954 | M25: =M21-M22-M23 -> -30.43 | N25: =N21-N22-N23 -> 0 | O25: =O21-O22-O23 -> 0 | P25: =P21-P22-P23 -> -1007.396 | Q25: =Q21-Q22-Q23 -> -1106.084 | R25: =R21-R22-R23 -> -1394.668 | ... AB25: =AB21-AB22-AB23 -> -2460.8988 | BG25: 贵州省 | CD25: 2019
A26: @HKINDU027 | B26: Operating profit | C26: Operating profit | K26: =K19+K21+K20 -> 1006.855 | L26: =L19+L21+L20 -> 1643.342 | M26: =M19+M21+M20 -> 2349.233 | N26: =N19+N21+N20 -> 3140.029 | O26: =O19+O21+O20 -> 4185.291 | P26: =P19+P21+P20 -> 5265.16 | Q26: =Q19+Q21+Q20 -> 6136.914 | R26: =R19+R21+R20 -> 6968.04 | ... AB26: =AB19+AB21+AB20 -> 16372.853 | BG26: 甘肃省 | CD26: 2020
A27: @HKINDU007 | B27: Financial costs (-) | C27: Financial costs (-) | K27: =K28-K29 -> -15.552 | L27: =L28-L29 -> -192.69 | M27: =M28-M29 -> -239.375 | N27: =N28-N29 -> -418.44 | O27: =O28-O29 -> -455.829 | P27: =P28-P29 -> -629.105 | Q27: =Q28-Q29 -> -688.159 | R27: =R28-R29 -> -1069.754 | ... AB27: =AB28-AB29 -> -2740.134 | BG27: 内蒙古
A28: @HKINDU010 | B28: Interest Expense (-) | C28: Interest Expense (-) | K28: =-PL!H90 -> -15.552 | L28: =-PL!I90 -> -192.69 | M28: =-PL!J90 -> -239.375 | N28: =-PL!K90 -> -418.44 | O28: =-PL!L90 -> -455.829 | P28: =-PL!M90 -> -629.105 | Q28: =-PL!N90 -> -688.159 | R28: =-PL!O90 -> -1069.754 | ... AB28: =-PL!Y90 -> -2740.134 | BG28: 宁夏
A29: @HKINDU009 | B29: Interest Income (+) | C29: Interest Income (+) | K29: 0 | L29: 0 | M29: 0 | N29: 0 | O29: 0 | P29: 0 | Q29: 0 | R29: 0 | S29: 0 | T29: 0 | U29: 0 | V29: 0 | W29: 0 | X29: 0 | Y29: 0 | Z29: 0 | AA29: 0 | AB29: 0 | BG29: 西藏
A30: @HKINDU012 | B30: Foreign Exchange Gain/Loss (+/-) | C30: Foreign Exchange Gain/Loss (+/-) | K30: 0 | L30: 0 | M30: 0 | N30: 0 | O30: 0 | P30: 0 | Q30: 0 | R30: 0 | S30: 0 | T30: 0 | U30: 0 | V30: 0 | W30: 0 | X30: 0 | Y30: 0 | Z30: 0 | AA30: 0 | AB30: 0 | BG30: 新疆 | CA30: 合并
A31: @HKINDU014 | B31: Net Participation Income/Associates Profits (+/-) | C31: Net Participation Income/Associates Profits (+/-) | K31: =PL!H100 -> 342.164 | L31: =PL!I100 -> 393.649 | M31: =PL!J100 -> 431.539 | N31: =PL!K100 -> 452.169 | O31: =PL!L100 -> 318.132 | P31: =PL!M100 -> 496.19 | Q31: =PL!N100 -> 562.965 | R31: =PL!O100 -> 891.68 | ... AB31: =PL!Y100 -> 922.1426 | BG31: 青海省
A32: @HKINDU013 | B32: Other Income/ Expense (+/-) | C32: Other Income/ Expense (+/-) | K32: =PL!H100 -> 342.164 | L32: =PL!I100 -> 393.649 | M32: =PL!J100 -> 431.539 | N32: =PL!K100 -> 452.169 | O32: =PL!L100 -> 318.132 | P32: =PL!M100 -> 496.19 | Q32: =PL!N100 -> 562.965 | R32: =PL!O100 -> 891.68 | ... AB32: =PL!Y100 -> 922.1426 | BG32: 香港
A33: @HKINDU017 | B33: Profit before taxes | C33: Profit before taxes | K33: =K26+K28+K31 -> 1333.467 | L33: =L26+L28+L31 -> 1844.301 | M33: =M26+M28+M31 -> 2541.397 | N33: =N26+N28+N31 -> 3173.758 | O33: =O26+O28+O31 -> 4047.594 | P33: =P26+P28+P31 -> 5132.245 | Q33: =Q26+Q28+Q31 -> 6011.72 | R33: =R26+R28+R31 -> 6789.966 | ... AB33: =AB26+AB28+AB31 -> 14554.861 | BG33: 澳门
A34: @HKINDU018 | B34: Taxes on Profit (-) | C34: Taxes on Profit (-) | K34: =-PL!H105 -> -213.218 | L34: =-PL!I105 -> -334.122 | M34: =-PL!J105 -> 404.896 | N34: =-PL!K105 -> -503.071 | O34: =-PL!L105 -> -659.716 | P34: =-PL!M105 -> -659.562 | Q34: =-PL!N105 -> -1004.504 | R34: =-PL!O105 -> -1255.662 | ... AB34: =-PL!Y105 -> -3602.509 | BG34: 台湾
A35: @HKINDU019 | B35: Minority Interests (+/-) | C35: Minority Interests (+/-) | K35: =-PL!H109 -> -83.971 | L35: =-PL!I109 -> -2.774 | M35: =-PL!J109 -> -5.042 | N35: =-PL!K109 -> 78.864 | O35: =-PL!L109 -> 69.532 | P35: =-PL!M109 -> 51.443 | Q35: =-PL!N109 -> 122.85 | R35: =-PL!O109 -> -44.213 | ... AB35: =-PL!Y109 -> -228.79432 | BG35: 国外
A36: @HKINDU020 | B36: Preference Dividends (-) | C36: Preference Dividends (-) | BG36: 其他
A37: @HKINDU022 | B37: Net Profit | C37: Net Profit | K37: =PL!H112 -> 1036.278 | L37: =PL!I112 -> 1507.405 | M37: =PL!J112 -> 2941.251 | N37: =PL!K112 -> 2749.551 | O37: =PL!L112 -> 3457.41 | P37: =PL!M112 -> 4524.126 | Q37: =PL!N112 -> 5130.066 | R37: =PL!O112 -> 5490.091 | ... AB37: =PL!Y112 -> 10494.75
A38: @HKINDU023 | B38: Adjustments (Non Recurrent Items) (+/-) | C38: Adjustments (Non Recurrent Items) (+/-)
A39: @HKINDU024 | B39: Recurrent Net Profit | C39: Recurrent Net Profit | K39: =PL!H118 -> 1036.278 | L39: =PL!I118 -> 1507.405 | M39: =PL!J118 -> 2131.459 | N39: =PL!K118 -> 2749.551 | O39: =PL!L118 -> 3457.41 | P39: =PL!M118 -> 4153 | Q39: =PL!N118 -> 4153.546 | R39: =PL!O118 -> 5072.521 | ... AB39: =PL!Y118 -> 10493.75
A40: @HKINDU021 | B40: Dividends | C40: Dividends | K40: =PL!H129 -> 251.561 | L40: =PL!I129 -> 430.382 | M40: =PL!J129 -> 622.1 | N40: =PL!K129 -> 816.636 | O40: =PL!L129 -> 895.251 | P40: =PL!M129 -> 1338 | Q40: =PL!N129 -> 1481 | R40: =PL!O129 -> 1767.2048 | ... AB40: =PL!Y129 -> 3673.1625
B42: 资产负债表 | C42: Balance Sheet
A44: @HKINDU089 | B44: Assets | C44: Assets | K44: =SUM(K46,K49:K55) -> 9762.655 | L44: =SUM(L46,L49:L55) -> 12326.397 | M44: =SUM(M46,M49:M55) -> 16774.905 | N44: =SUM(N46,N49:N55) -> 23397.291 | O44: =SUM(O46,O49:O55) -> 32249.5 | P44: =SUM(P46,P49:P55) -> 40685.634 | Q44: =SUM(Q46,Q49:Q55) -> 46030.725 | R44: =SUM(R46,R49:R55) -> 63040.636 | ... AB44: =SUM(AB46,AB49:AB55) -> 106424.8
A45: @HKINDU050 | B45: Total Non Current Assets | C45: Total Non Current Assets | K45: =BS!H24 -> 9762.655 | L45: =BS!I24 -> 12326.397 | M45: =BS!J24 -> 16774.905 | N45: =BS!K24 -> 23397.291 | O45: =BS!L24 -> 32249.5 | P45: =BS!M24 -> 40685.634 | Q45: =BS!N24 -> 46030.725 | R45: =BS!O24 -> 63040.636 | ... AB45: =BS!Y24 -> 107266.96
A46: @HKINDU051 | B46: Property plant and equipment, net | C46: Property plant and equipment, net | K46: =BS!H4 -> 1454.445 | L46: =BS!I4 -> 1870.033 | M46: =BS!J4 -> 2190.951 | N46: =BS!K4 -> 2672.357 | O46: =BS!L4 -> 2827.3 | P46: =BS!M4 -> 2786.916 | Q46: =BS!N4 -> 2493.761 | R46: =BS!O4 -> 3818.806 | ... AB46: =BS!Y4 -> 8205.1342
A47: @HKINDU090 | B47: Gross Value (+) | C47: Gross Value (+) | K47: =K46+K48 -> 2411.61 | L47: =L46+L48 -> 2933.154 | M47: =M46+M48 -> 3396.529 | N47: =N46+N48 -> 4115.771 | O47: =O46+O48 -> 4518.731 | P47: =P46+P48 -> 4664.986 | Q47: =Q46+Q48 -> 4557.065 | R47: =R46+R48 -> 6227.917 | ... AB47: =AB46+AB48 -> 13630.663
A48: @HKINDU052 | B48: Accumulated Depreciation (-) | C48: Accumulated Depreciation (-) | K48: =CAPEX!H76 -> 957.165 | L48: =CAPEX!I76 -> 1063.121 | M48: =CAPEX!J76 -> 1205.578 | N48: =CAPEX!K76 -> 1443.414 | O48: =CAPEX!L76 -> 1691.431 | P48: =CAPEX!M76 -> 1878.07 | Q48: =CAPEX!N76 -> 2063.304 | R48: =CAPEX!O76 -> 2409.111 | ... AB48: =CAPEX!Y76 -> 5425.5288
A49: @HKINDU053 | B49: Construction in Process | C49: Construction in Process | K49: =BS!H5 -> 42.038 | L49: =BS!I5 -> 41.063 | M49: =BS!J5 -> 40.044 | N49: =BS!K5 -> 39.085 | O49: =BS!L5 -> 38.073 | P49: =BS!M5 -> 3050.468 | Q49: =BS!N5 -> 4249.52 | R49: =BS!O5 -> 4750.265 | ... AB49: =BS!Y5 -> 6736.116
A50: @HKINDU054 | B50: Long-term Investments | C50: Long-term Investments | K50: =BS!H9+BS!H10+BS!H6+BS!H11+BS!H12 -> 3465.923 | L50: =BS!I9+BS!I10+BS!I6+BS!I11+BS!I12 -> 3793.081 | M50: =BS!J9+BS!J10+BS!J6+BS!J11+BS!J12 -> 4437.11 | N50: =BS!K9+BS!K10+BS!K6+BS!K11+BS!K12 -> 4154.9 | O50: =BS!L9+BS!L10+BS!L6+BS!L11+BS!L12 -> 7697.091 | P50: =BS!M9+BS!M10+BS!M6+BS!M11+BS!M12 -> 9335.755 | Q50: =BS!N9+BS!N10+BS!N6+BS!N11+BS!N12 -> 10918.22 | R50: =BS!O9+BS!O10+BS!O6+BS!O11+BS!O12 -> 18566.812 | ... AB50: =BS!Y9+BS!Y10+BS!Y6+BS!Y11+BS!Y12 -> 26046.339
A51: @HKINDU056 | B51: Goodwill, net | C51: Goodwill, net | K51: =BS!H22 -> 0 | L51: =BS!I22 -> 0 | M51: =BS!J22 -> 577.664 | N51: =BS!K22 -> 577.664 | O51: =BS!L22 -> 577.664 | P51: =BS!M22 -> 577.664 | Q51: =BS!N22 -> 577.664 | R51: =BS!O22 -> 577.664 | ... AB51: =BS!Y22 -> 519.9
A52: @HKINDU057 | B52: Other Intangible Asset, net | C52: Other Intangible Asset, net | K52: =BS!H8 -> 172.258 | L52: =BS!I8 -> 180.197 | M52: =BS!J8 -> 182.291 | N52: =BS!K8 -> 280.063 | O52: =BS!L8 -> 273.022 | P52: =BS!M8 -> 269.816 | Q52: =BS!N8 -> 315.097 | R52: =BS!O8 -> 391.306 | ... AB52: =BS!Y8 -> 0
A53: @HKINDU058 | B53: Deferred Tax Asset | C53: Deferred Tax Asset | K53: =BS!H15 -> 0 | L53: =BS!I15 -> 0 | M53: =BS!J15 -> 0 | N53: =BS!K15 -> 151.027 | O53: =BS!L15 -> 187.32 | P53: =BS!M15 -> 280.951 | Q53: =BS!N15 -> 225.006 | R53: =BS!O15 -> 222.58 | ... AB53: =BS!Y15 -> 130.36255
A54: @HKINDU059 | B54: Deferred Charges | C54: Deferred Charges
A55: @HKINDU055 | B55: Other non-current Asset | C55: Other non-current Asset | K55: =BS!H7+BS!H13+BS!H20+BS!H14+BS!H17+BS!H18+BS!H19+BS!H16 -> 4627.991 | L55: =BS!I7+BS!I13+BS!I20+BS!I14+BS!I17+BS!I18+BS!I19+BS!I16 -> 6442.023 | M55: =BS!J7+BS!J13+BS!J20+BS!J14+BS!J17+BS!J18+BS!J19+BS!J16 -> 9346.845 | N55: =BS!K7+BS!K13+BS!K20+BS!K14+BS!K17+BS!K18+BS!K19+BS!K16 -> 15522.195 | O55: =BS!L7+BS!L13+BS!L20+BS!L14+BS!L17+BS!L18+BS!L19+BS!L16 -> 20649.03 | P55: =BS!M7+BS!M13+BS!M20+BS!M14+BS!M17+BS!M18+BS!M19+BS!M16 -> 24384.064 | Q55: =BS!N7+BS!N13+BS!N20+BS!N14+BS!N17+BS!N18+BS!N19+BS!N16 -> 27251.457 | R55: =BS!O7+BS!O13+BS!O20+BS!O14+BS!O17+BS!O18+BS!O19+BS!O16 -> 34713.203 | ... AB55: =BS!Y7+BS!Y13+BS!Y20+BS!Y14+BS!Y17+BS!Y18+BS!Y19+BS!Y16 -> 64786.95
A56: @HKINDU068 | B56: Total Current Assets | C56: Total Current Assets | K56: =BS!H41 -> 8916.767 | L56: =BS!I41 -> 14406.747 | M56: =BS!J41 -> 20437.89 | N56: =BS!K41 -> 29053.373 | O56: =BS!L41 -> 34329.607 | P56: =BS!M41 -> 32418.461 | Q56: =BS!N41 -> 40143.72 | R56: =BS!O41 -> 55477.637 | ... AB56: =BS!Y41 -> 206818.2
A57: @HKINDU061 | B57: Cash and cash equivalents | C57: Cash and cash equivalents | K57: =BS!H38+BS!H39 -> 3729.743 | L57: =BS!I38+BS!I39 -> 5458.66 | M57: =BS!J38+BS!J39 -> 6717.429 | N57: =BS!K38+BS!K39 -> 8126.345 | O57: =BS!L38+BS!L39 -> 7452.448 | P57: =BS!M38+BS!M39 -> 8026.224 | Q57: =BS!N38+BS!N39 -> 11484.652 | R57: =BS!O38+BS!O39 -> 17593.203 | ... AB57: =BS!Y38+BS!Y39 -> 31330.235
A58: @HKINDU063 | B58: Short-term Investment in securities | C58: Short-term Investment in securities | K58: =BS!H35+BS!H36 -> 10.519 | L58: =BS!I35+BS!I36 -> 11.209 | M58: =BS!J35+BS!J36 -> 16.345 | N58: =BS!K35+BS!K36 -> 18.988 | O58: =BS!L35+BS!L36 -> 11.559 | P58: =BS!M35+BS!M36 -> 41.271 | Q58: =BS!N35+BS!N36 -> 42.263 | R58: =BS!O35+BS!O36 -> 30.315 | ... AB58: =BS!Y35+BS!Y36 -> 1034.5346
A59: @HKINDU064 | B59: Inventories, net | C59: Inventories, net | K59: =BS!H27 -> 117.711 | L59: =BS!I27 -> 149.559 | M59: =BS!J27 -> 185.374 | N59: =BS!K27 -> 163.427 | O59: =BS!L27 -> 160.289 | P59: =BS!M27 -> 108.835 | Q59: =BS!N27 -> 131.365 | R59: =BS!O27 -> 214.039 | ... AB59: =BS!Y27 -> 599.57459
A60: @HKINDU066 | B60: Account Receivables, net | C60: Account Receivables, net | K60: =BS!H29+BS!H30+BS!H31+BS!H32 -> 5027.184 | L60: =BS!I29+BS!I30+BS!I31+BS!I32 -> 8600.44 | M60: =BS!J29+BS!J30+BS!J31+BS!J32 -> 13351.628 | N60: =BS!K29+BS!K30+BS!K31+BS!K32 -> 20581.142 | O60: =BS!L29+BS!L30+BS!L31+BS!L32 -> 26621.591 | P60: =BS!M29+BS!M30+BS!M31+BS!M32 -> 22683.317 | Q60: =BS!N29+BS!N30+BS!N31+BS!N32 -> 27405.374 | R60: =BS!O29+BS!O30+BS!O31+BS!O32 -> 37181.367 | ... AB60: =BS!Y29+BS!Y30+BS!Y31+BS!Y32 -> 162101.56
A61: @HKINDU067 | B61: Other Current Assets | C61: Other Current Assets | K61: =BS!H26+BS!H34+BS!H40+BS!H28 -> 31.61 | L61: =BS!I26+BS!I34+BS!I40+BS!I28 -> 186.879 | M61: =BS!J26+BS!J34+BS!J40+BS!J28 -> 167.114 | N61: =BS!K26+BS!K34+BS!K40+BS!K28 -> 163.471 | O61: =BS!L26+BS!L34+BS!L40+BS!L28 -> 83.72 | P61: =BS!M26+BS!M34+BS!M40+BS!M28 -> 1558.814 | Q61: =BS!N26+BS!N34+BS!N40+BS!N28 -> 1080.066 | R61: =BS!O26+BS!O34+BS!O40+BS!O28 -> 458.713 | ... AB61: =BS!Y26+BS!Y34+BS!Y40+BS!Y28 -> 11752.298
A62: @HKINDU069 | B62: Total Assets | C62: Total Assets | K62: =BS!H43 -> 18679.422 | L62: =BS!I43 -> 26733.144 | M62: =BS!J43 -> 37212.795 | N62: =BS!K43 -> 52450.664 | O62: =BS!L43 -> 66579.107 | P62: =BS!M43 -> 73104.095 | Q62: =BS!N43 -> 86174.445 | R62: =BS!O43 -> 118518.27 | ... AB62: =BS!Y43 -> 314085.17
A63: @HKINDU091 | B63: Liabilities | C63: Liabilities
A64: @HKINDU076 | B64: Total Non Current Liabilities | C64: Total Non Current Liabilities | K64: =BS!H56 -> 5823.759 | L64: =BS!I56 -> 5659.22 | M64: =BS!J56 -> 10884.353 | N64: =BS!K56 -> 13501.946 | O64: =BS!L56 -> 15360.373 | P64: =BS!M56 -> 18112.61 | Q64: =BS!N56 -> 20788.013 | R64: =BS!O56 -> 27247.65 | ... AB64: =BS!Y56 -> 76373.992
A65: @HKINDU077 | B65: Long Term Debt | C65: Long Term Debt | K65: =BS!H50+BS!H52 -> 5350.899 | L65: =BS!I50+BS!I52 -> 4961.268 | M65: =BS!J50+BS!J52 -> 9996.359 | N65: =BS!K50+BS!K52 -> 8600.258 | O65: =BS!L50+BS!L52 -> 10361.804 | P65: =BS!M50+BS!M52 -> 13085.694 | Q65: =BS!N50+BS!N52 -> 15849.056 | R65: =BS!O50+BS!O52 -> 20592.443 | ... AB65: =BS!Y50+BS!Y52 -> 61761.628
A66: @HKINDU079 | B66: Deferred Tax Liabilities | C66: Deferred Tax Liabilities | K66: =BS!H49 -> 228.813 | L66: =BS!I49 -> 276.014 | M66: =BS!J49 -> 362.265 | N66: =BS!K49 -> 398.32 | O66: =BS!L49 -> 389.477 | P66: =BS!M49 -> 406.265 | Q66: =BS!N49 -> 348.891 | R66: =BS!O49 -> 446.655 | ... AB66: =BS!Y49 -> 616.53064
A67: @HKINDU078 | B67: Other LT Liabilities | C67: Other LT Liabilities | K67: =BS!H47+BS!H51+BS!H48+BS!H53 -> 244.047 | L67: =BS!I47+BS!I51+BS!I48+BS!I53 -> 421.938 | M67: =BS!J47+BS!J51+BS!J48+BS!J53 -> 525.729 | N67: =BS!K47+BS!K51+BS!K48+BS!K53 -> 4503.368 | O67: =BS!L47+BS!L51+BS!L48+BS!L53 -> 4609.092 | P67: =BS!M47+BS!M51+BS!M48+BS!M53 -> 4620.651 | Q67: =BS!N47+BS!N51+BS!N48+BS!N53 -> 4590.066 | R67: =BS!O47+BS!O51+BS!O48+BS!O53 -> 6208.552 | ... AB67: =BS!Y47+BS!Y51+BS!Y48+BS!Y53 -> 13961.303
A68: @HKINDU070 | B68: Total Current Liabilities | C68: Total Current Liabilities | K68: =BS!H69 -> 8232.263 | L68: =BS!I69 -> 11576.848 | M68: =BS!J69 -> 12475.474 | N68: =BS!K69 -> 22761.392 | O68: =BS!L69 -> 31221.072 | P68: =BS!M69 -> 31706.669 | Q68: =BS!N69 -> 39716.114 | R68: =BS!O69 -> 52807.712 | ... AB68: =BS!Y69 -> 143084.18
A69: @HKINDU071 | B69: Short Term Debt | C69: Short Term Debt | K69: =BS!H66+BS!H68 -> 0 | L69: =BS!I66+BS!I68 -> 1297.867 | M69: =BS!J66+BS!J68 -> 48.78 | N69: =BS!K66+BS!K68 -> 261.889 | O69: =BS!L66+BS!L68 -> 587.269 | P69: =BS!M66+BS!M68 -> 808.197 | Q69: =BS!N66+BS!N68 -> 1455.62 | R69: =BS!O66+BS!O68 -> 2580.59 | ... AB69: =BS!Y66+BS!Y68 -> 18806.355
A70: @HKINDU074 | B70: Current portion of long-term debt | C70: Current portion of long-term debt | K70: 0 | L70: 0 | M70: 0 | N70: 0 | O70: 0 | P70: 0 | Q70: 0 | R70: 0 | S70: 0 | T70: 0 | U70: 0 | V70: 0 | W70: 0 | X70: 0 | Y70: 0 | Z70: 0 | AA70: 0 | AB70: 0
A71: @HKINDU072 | B71: Accounts Payable | C71: Accounts Payable | K71: =BS!H58+BS!H60 -> 4809.876 | L71: =BS!I58+BS!I60 -> 6457.923 | M71: =BS!J58+BS!J60 -> 7717.999 | N71: =BS!K58+BS!K60 -> 14923.112 | O71: =BS!L58+BS!L60 -> 21054.37 | P71: =BS!M58+BS!M60 -> 26595.993 | Q71: =BS!N58+BS!N60 -> 34304.815 | R71: =BS!O58+BS!O60 -> 33133.986 | ... AB71: =BS!Y58+BS!Y60 -> 106587.81
A72: @HKINDU065 | B72: Taxation Payable | C72: Taxation Payable | K72: =BS!H62 -> 112.362 | L72: =BS!I62 -> 313.787 | M72: =BS!J62 -> 594.57 | N72: =BS!K62 -> 608.633 | O72: =BS!L62 -> 930.971 | P72: =BS!M62 -> 2015.547 | Q72: =BS!N62 -> 2392.708 | R72: =BS!O62 -> 3247.384 | ... AB72: =BS!Y62 -> 6006.1844
A73: @HKINDU060 | B73: Other payables and accruals | C73: Other payables and accruals | K73: =BS!H59 -> 2621.18 | L73: =BS!I59 -> 2807.397 | M73: =BS!J59 -> 2974.048 | N73: =BS!K59 -> 477.505 | O73: =BS!L59 -> 380.591 | P73: =BS!M59 -> 1563.386 | Q73: =BS!N59 -> 735.03 | R73: =BS!O59 -> 2308.456 | ... AB73: =BS!Y59 -> 1932.841
A74: @HKINDU073 | B74: Other Current Liabilities | C74: Other Current Liabilities | K74: =BS!H63+BS!H64+BS!H61+BS!H68 -> 688.845 | L74: =BS!I63+BS!I64+BS!I61+BS!I68 -> 1640.025 | M74: =BS!J63+BS!J64+BS!J61+BS!J68 -> 1140.077 | N74: =BS!K63+BS!K64+BS!K61+BS!K68 -> 6490.253 | O74: =BS!L63+BS!L64+BS!L61+BS!L68 -> 8267.871 | P74: =BS!M63+BS!M64+BS!M61+BS!M68 -> 723.546 | Q74: =BS!N63+BS!N64+BS!N61+BS!N68 -> 827.941 | R74: =BS!O63+BS!O64+BS!O61+BS!O68 -> 11537.296 | ... AB74: =BS!Y63+BS!Y64+BS!Y61+BS!Y68 -> 8651.2222
A75: @HKINDU080 | B75: Total Liabilities | C75: Total Liabilities | K75: =BS!H71 -> 14056.022 | L75: =BS!I71 -> 17236.068 | M75: =BS!J71 -> 23359.827 | N75: =BS!K71 -> 36263.338 | O75: =BS!L71 -> 46581.445 | P75: =BS!M71 -> 49819.279 | Q75: =BS!N71 -> 60504.127 | R75: =BS!O71 -> 80055.362 | ... AB75: =BS!Y71 -> 219458.17
A76: @HKINDU085 | B76: Minority Interests | C76: Minority Interests | K76: =BS!H80 -> 3.95 | L76: =BS!I80 -> 6.724 | M76: =BS!J80 -> 343.144 | N76: =BS!K80 -> 253.737 | O76: =BS!L80 -> 167.566 | P76: =BS!M80 -> 100.262 | Q76: =BS!N80 -> 222.36 | R76: =BS!O80 -> 375.282 | ... AB76: =BS!Y80 -> 3672.6417
A77: @HKINDU092 | B77: Equity | C77: Equity
A78: @HKINDU082 | B78: Share Capital | C78: Share Capital | K78: =BS!H75 -> 74.486 | L78: =BS!I75 -> 89.668 | M78: =BS!J75 -> 97.186 | N78: =BS!K75 -> 97.219 | O78: =BS!L75 -> 100.31 | P78: =BS!M75 -> 101.408 | Q78: =BS!N75 -> 112.203 | R78: =BS!O75 -> 126.229 | ... AB78: =BS!Y75 -> 123.8
A79: @HKINDU083 | B79: Reserves (Including Retained Earnings) | C79: Reserves (Including Retained Earnings) | K79: =BS!H76 -> 4544.964 | L79: =BS!I76 -> 9400.684 | M79: =BS!J76 -> 13412.638 | N79: =BS!K76 -> 15836.417 | O79: =BS!L76 -> 19729.786 | P79: =BS!M76 -> 23083.146 | Q79: =BS!N76 -> 25335.755 | R79: =BS!O76 -> 37961.4 | ... AB79: =BS!Y76 -> 84088.841
A80: @HKINDU086 | B80: Total Equity | C80: Total Equity | E80: =BS!B77+BS!B79 -> #VALUE! | F80: =BS!C77+BS!C79 -> 827.806 | G80: =BS!D77+BS!D79 -> 974.201 | H80: =BS!E77+BS!E79 -> 2155.683 | I80: =BS!F77+BS!F79 -> 2523.257 | J80: =BS!G77+BS!G79 -> 4304.782 | K80: =BS!H77+BS!H79 -> 4619.45 | L80: =BS!I77+BS!I79 -> 9490.352 | ... AB80: =BS!Y77+BS!Y79 -> 90954.351
A81: @HKINDU088 | B81: Total Equity and Liabilities | C81: Total Equity and Liabilities | K81: =BS!H84 -> 18679.422 | L81: =BS!I84 -> 26733.144 | M81: =BS!J84 -> 37212.795 | N81: =BS!K84 -> 52450.711 | O81: =BS!L84 -> 66579.107 | P81: =BS!M84 -> 73104.095 | Q81: =BS!N84 -> 86174.445 | R81: =BS!O84 -> 118518.27 | ... AB81: =BS!Y84 -> 314085.16
B83: 现金流量表 | C83: Cash Flow Statement
A85: @HKINDU150 | B85: Cash flows from operating activities | C85: Cash flows from operating activities | K85: =CF!H11 -> 41.023 | L85: =CF!I11 -> -1004.495 | M85: =CF!J11 -> -3339.814 | N85: =CF!K11 -> -3085.435 | O85: =CF!L11 -> -1688.938 | P85: =CF!M11 -> 298 | Q85: =CF!N11 -> 2867 | R85: =CF!O11 -> -4845.706 | ... AB85: =CF!Y11 -> 2464.4305
A86: @HKINDU151 | B86: Profit Before Tax (After-extraordinaries) | C86: Profit Before Tax (After-extraordinaries) | K86: =PL!H103 -> 1333.467 | L86: =PL!I103 -> 1844.301 | M86: =PL!J103 -> 2541.397 | N86: =PL!K103 -> 3173.758 | O86: =PL!L103 -> 4047.594 | P86: =PL!M103 -> 5132.245 | Q86: =PL!N103 -> 6011.72 | R86: =PL!O103 -> 6789.966 | ... AB86: =PL!Y103 -> 14554.861
A87: @HKINDU152 | B87: Associates Profit (+/-) | C87: Associates Profit (+/-) | K87: =CF!H5 -> 83.971 | L87: =CF!I5 -> 2.774 | M87: =CF!J5 -> 5.042 | N87: =CF!K5 -> -78.864 | O87: =CF!L5 -> -69.532 | P87: =CF!M5 -> -51.443 | Q87: =CF!N5 -> -122.85 | R87: =CF!O5 -> 44.213 | ... AB87: =CF!Y5 -> 228.79432
A88: @HKINDU153 | B88: Associates Dividends (+) | C88: Associates Dividends (+)
A89: @HKINDU154 | B89: Depreciation (+) | C89: Depreciation (+) | K89: =CF!H6 -> 81.227 | L89: =CF!I6 -> 179.858 | M89: =CF!J6 -> 254.52 | N89: =CF!K6 -> 279.305 | O89: =CF!L6 -> 294.425 | P89: =CF!M6 -> 326.396 | Q89: =CF!N6 -> 350.518 | R89: =CF!O6 -> 345.899 | ... AB89: =CF!Y6 -> 851.28692
A90: @HKINDU155 | B90: Amortization (+) | C90: Amortization (+) | K90: 0 | L90: 0 | M90: 0 | N90: 0 | O90: 0 | P90: 0 | Q90: 0 | R90: 0 | S90: 0 | T90: 0 | U90: 0 | V90: 0 | W90: 0 | X90: 0 | Y90: 0 | Z90: 0 | AA90: 0 | AB90: 0
A91: @HKINDU156 | B91: Tax Paid (-) | C91: Tax Paid (-) | K91: 0 | L91: 0 | M91: 0 | N91: 0 | O91: 0 | P91: 0 | Q91: 0 | R91: 0 | S91: 0 | T91: 0 | U91: 0 | V91: 0 | W91: 0 | X91: 0 | Y91: 0 | Z91: 0 | AA91: 0 | AB91: 0
A92: @HKINDU157 | B92: Change in Working Capital (-/+) | C92: Change in Working Capital (-/+) | K92: =CF!H7 -> 2496.985 | L92: =CF!I7 -> -1708.864 | M92: =CF!J7 -> -2639.29 | N92: =CF!K7 -> 7317.143 | O92: =CF!L7 -> 1220.783 | P92: =CF!M7 -> 418.395 | Q92: =CF!N7 -> 2622.141 | R92: =CF!O7 -> -1751.558 | ... AB92: =CF!Y7 -> -6563.018
A93: @HKINDU158 | B93: Change in Provisions (+/-) | C93: Change in Provisions (+/-)
A94: @HKINDU159 | B94: Profit on disposal of FAs/Subsidiaries/Investments (-) | C94: Profit on disposal of FAs/Subsidiaries/Investments (-) | K94: =CF!H9 -> -459.97 | L94: =CF!I9 -> -746.398 | M94: =CF!J9 -> -735.227 | N94: =CF!K9 -> -760.382 | O94: =CF!L9 -> -742.084 | P94: =CF!M9 -> -1255.95 | Q94: =CF!N9 -> -551.209 | R94: =CF!O9 -> -1117.661 | ... AB94: =CF!Y9 -> -281.47053
A95: @HKINDU160 | B95: Other Items | C95: Other Items | K95: =CF!H10+CF!H8 -> -3197.468 | L95: =CF!I10+CF!I8 -> -239.27 | M95: =CF!J10+CF!J8 -> -3166.11 | N95: =CF!K10+CF!K8 -> -12592.188 | O95: =CF!L10+CF!L8 -> -5849.94 | P95: =CF!M10+CF!M8 -> -3663.524 | Q95: =CF!N10+CF!N8 -> -4561.666 | R95: =CF!O10+CF!O8 -> -7856.69 | ... AB95: =CF!Y10+CF!Y8 -> -2265.9123
A96: @HKINDU161 | B96: Cash flows from investing activities | C96: Cash flows from investing activities | K96: =CF!H18 -> -1424.945 | L96: =CF!I18 -> -163.836 | M96: =CF!J18 -> -457.458 | N96: =CF!K18 -> 130.056 | O96: =CF!L18 -> -2091.319 | P96: =CF!M18 -> -935.204 | Q96: =CF!N18 -> -5690.531 | R96: =CF!O18 -> -4800.189 | ... AB96: =CF!Y18 -> -1663.3214
A97: @HKINDU162 | B97: Capital Expenditure | C97: Capital Expenditure | K97: =CF!H15 -> -364.538 | L97: =CF!I15 -> -522.2 | M97: =CF!J15 -> -402.206 | N97: =CF!K15 -> -378.543 | O97: =CF!L15 -> -514.487 | P97: =CF!M15 -> -425.478 | Q97: =CF!N15 -> -177.743 | R97: =CF!O15 -> -1410.112 | ... AB97: =CF!Y15 -> -911.68157
A98: @HKINDU163 | B98: Change in long-term investment | C98: Change in long-term investment | K98: =CF!H16 -> -1451.812 | L98: =CF!I16 -> 29.558 | M98: =CF!J16 -> 128.644 | N98: =CF!K16 -> 62.415 | O98: =CF!L16 -> -203.191 | P98: =CF!M16 -> -269.495 | Q98: =CF!N16 -> 288.207 | R98: =CF!O16 -> -1440.774 | ... AB98: =CF!Y16 -> -61.629469
A99: @HKINDU164 | B99: Acquisition of Subsidiaries/ Investments | C99: Acquisition of Subsidiaries/ Investments
A100: @HKINDU165 | B100: Other Items | C100: Other Items | K100: =CF!H17 -> 391.405 | L100: =CF!I17 -> 328.806 | M100: =CF!J17 -> -183.896 | N100: =CF!K17 -> 446.184 | O100: =CF!L17 -> -1373.641 | P100: =CF!M17 -> -240.231 | Q100: =CF!N17 -> -5800.995 | R100: =CF!O17 -> -1949.303 | ... AB100: =CF!Y17 -> -690.01032
A101: @HKINDU166 | B101: Cash flows from financing activities | C101: Cash flows from financing activities | K101: =CF!H28 -> -777.448 | L101: =CF!I28 -> 2894.112 | M101: =CF!J28 -> 5021.845 | N101: =CF!K28 -> 4046.082 | O101: =CF!L28 -> 3172.269 | P101: =CF!M28 -> 1309.448 | Q101: =CF!N28 -> 6497.667 | R101: =CF!O28 -> 15252.916 | ... AB101: =CF!Y28 -> -1237.4412
A102: @HKINDU167 | B102: Proceeds from Share Issues | C102: Proceeds from Share Issues | K102: =CF!H23 -> -470.049 | L102: =CF!I23 -> 3551.538 | M102: =CF!J23 -> 2229.861 | N102: =CF!K23 -> 0.293 | O102: =CF!L23 -> 1.441 | P102: =CF!M23 -> 9.895 | Q102: =CF!N23 -> 4809.959 | R102: =CF!O23 -> 6307.337 | ... AB102: =CF!Y23 -> 0
A103: @HKINDU168 | B103: Dividends Paid | C103: Dividends Paid | L103: =CF!I26 -> -708.238 | M103: =CF!J26 -> -873.849 | N103: =CF!K26 -> -1449.77 | O103: =CF!L26 -> -1754.04 | P103: =CF!M26 -> -1822.621 | Q103: =CF!N26 -> -2084.177 | R103: =CF!O26 -> -2536.214 | S103: =CF!P26 -> -3536.172 | ... AB103: =CF!Y26 -> -6121.675
A104: @HKINDU169 | B104: Change in bankloan | C104: Change in bankloan | K104: =CF!H24 -> 1256.475 | L104: =CF!I24 -> 2345.381 | M104: =CF!J24 -> 4620.924 | N104: =CF!K24 -> 5649.901 | O104: =CF!L24 -> 4739.638 | P104: =CF!M24 -> 3113.528 | Q104: =CF!N24 -> 3740.152 | R104: =CF!O24 -> 11373.414 | ... AB104: =CF!Y24 -> 4884.2338
...

Sheet Cover
A1: =TODAY() -> 46120
A2: 8.49 | J2: =14.2/A2-1 -> 0.67255595
A3: 主要财务数据
A4: （百万人民币） | B4: 2005A | C4: 2006A | D4: 2007A | E4: 2008A | F4: 2009A | G4: 2010A | H4: 2011A | I4: 2012A | J4: 2013A | K4: 2014A | L4: 2015A | M4: 2016A | N4: 2017A | O4: 2018A | P4: =PL!Q3 -> 2019A | Q4: =PL!R3 -> 2020A | R4: =PL!S3 -> 2021A | S4: =PL!T3 -> 2022A | T4: =PL!U3 -> 2023A | U4: =PL!V3 -> 2024A | V4: =PL!W3 -> 2025A | W4: =PL!X3 -> 2026E | X4: =PL!Y3 -> 2027E
A5: 主营业务收入 | B5: =PL!C4 -> 7664.252 | C5: =PL!D4 -> 10294.826 | D5: =PL!E4 -> 10168.321 | E5: =PL!F4 -> 11021.405 | F5: =PL!G4 -> 11341.998 | G5: =PL!H4 -> 11982.871 | H5: =PL!I4 -> 16379.311 | I5: =PL!J4 -> 21910.66 | ... X5: =PL!Y4 -> 114194.84
A6: (+/-%) | C6: =(C5/B5-1)*1 -> 0.34322645 | D6: =(D5/C5-1)*1 -> -0.012288212 | E6: =(E5/D5-1)*1 -> 0.08389625 | F6: =(F5/E5-1)*1 -> 0.029088215 | G6: =(G5/F5-1)*1 -> 0.056504418 | H6: =(H5/G5-1)*1 -> 0.36689371 | I6: =(I5/H5-1)*1 -> 0.3377034 | J6: =(J5/I5-1)*1 -> 0.24531256 | ... X6: =(X5/W5-1)*1 -> 0.10268765
A7: 税前利润 | B7: =PL!C103 -> 201.524 | C7: =PL!D103 -> 271.044 | D7: =PL!E103 -> 530.31 | E7: =PL!F103 -> 570.665 | F7: =PL!G103 -> 722.08 | G7: =PL!H103 -> 1333.467 | H7: =PL!I103 -> 1844.301 | I7: =PL!J103 -> 2541.397 | ... X7: =PL!Y103 -> 14554.861
A8: (+/-%) | C8: =(C7/B7-1)*1 -> 0.34497132 | D8: =(D7/C7-1)*1 -> 0.9565458 | E8: =(E7/D7-1)*1 -> 0.076097 | F8: =(F7/E7-1)*1 -> 0.2653308 | G8: =(G7/F7-1)*1 -> 0.84670258 | H8: =(H7/G7-1)*1 -> 0.3830871 | I8: =(I7/H7-1)*1 -> 0.37797301 | J8: =(J7/I7-1)*1 -> 0.24882417 | ... X8: =(X7/W7-1)*1 -> 0.084244145
A9: 净利润 | B9: =PL!C112 -> 152.021 | C9: =PL!D112 -> 222.182 | D9: =PL!E112 -> 404.893 | E9: =PL!F112 -> 489.321 | F9: =PL!G112 -> 612.531 | G9: =PL!H112 -> 1036.278 | H9: =PL!I112 -> 1507.405 | I9: =PL!J112 -> 2941.251 | ... X9: =PL!Y112 -> 10494.75
A10: (+/-%) | C10: =(C9/B9-1)*1 -> 0.46152176 | D10: =(D9/C9-1)*1 -> 0.82234835 | E10: =(E9/D9-1)*1 -> 0.20851929 | F10: =(F9/E9-1)*1 -> 0.2517979 | G10: =(G9/F9-1)*1 -> 0.69179682 | H10: =(H9/G9-1)*1 -> 0.4546338 | I10: =(I9/H9-1)*1 -> 0.95120157 | J10: =(J9/I9-1)*1 -> -0.065176348 | ... X10: =(X9/W9-1)*1 -> 0.086239244
A11: 摊薄每股盈利(HK$) | B11: =PL!C122 -> 0.028779773 | C11: =PL!D122 -> 0.042062265 | D11: =PL!E122 -> 0.076652099 | E11: =PL!F122 -> 0.092635541 | F11: =PL!G122 -> 0.11596098 | G11: =PL!H122 -> 0.19618241 | H11: =PL!I122 -> 0.28537356 | I11: =PL!J122 -> 0.55682134 | ... X11: =PL!Y122 -> 1.9868079
A12: 市盈率 | B12: =PL!C123 -> 0 | C12: =PL!D123 -> 201.84362 | D12: =PL!E123 -> 110.76018 | E12: =PL!F123 -> 91.649489 | F12: =PL!G123 -> 73.214286 | G12: =PL!H123 -> 43.276051 | H12: =PL!I123 -> 29.750478 | I12: =PL!J123 -> 15.24726 | ... X12: =PL!Y123 -> 4.2731861
A13: 市净率 | B13: =PL!C128 -> 0 | C13: =PL!D128 -> 46.033642 | D13: =PL!E128 -> 20.803625 | E13: =PL!F128 -> 17.773069 | F13: =PL!G128 -> 10.417721 | G13: =PL!H128 -> 9.7080864 | H13: =PL!I128 -> 4.7254327 | I13: =PL!J128 -> 3.3195118 | ... X13: =PL!Y128 -> 0.53253311
A14: EV/EBITDA | B14: =PL!C138 -> 0 | C14: =PL!D138 -> 121.95838 | D14: =PL!E138 -> 74.952155 | E14: =PL!F138 -> 62.542272 | F14: =PL!G138 -> 42.3423 | G14: =PL!H138 -> 25.810928 | H14: =PL!I138 -> 16.794395 | I14: =PL!J138 -> 13.019921 | ... X14: =PL!Y138 -> 5.7751923
A15: 净资产收益率(%) | B15: =PL!C140 -> 0 | C15: =PL!D140 -> 0.24659394 | D15: =PL!E140 -> 0.25872716 | E15: =PL!F140 -> 0.20915891 | F15: =PL!G140 -> 0.17941637 | G15: =PL!H140 -> 0.23223914 | H15: =PL!I140 -> 0.21366778 | I15: =PL!J140 -> 0.255759 | ... X15: =PL!Y140 -> 0.13011735
A16: 现金分红收益率(%) | B16: =PL!C132 -> 0 | C16: =PL!D132 -> 0.0042676655 | D16: =PL!E132 -> 0.00501694 | E16: =PL!F132 -> 0.0096297093 | F16: =PL!G132 -> 0.0074385906 | G16: =PL!H132 -> 0.0099448499 | H16: =PL!I132 -> 0.014133382 | I16: =PL!J132 -> 0.018848986 | ... X16: =PL!Y132 -> 0.093265883
A17: 净利润率 | B17: =PL!C139 -> 0 | C17: =PL!D139 -> 0.021581909 | D17: =PL!E139 -> 0.039819062 | E17: =PL!F139 -> 0.044397334 | F17: =PL!G139 -> 0.054005564 | G17: =PL!H139 -> 0.086479943 | H17: =PL!I139 -> 0.092031038 | I17: =PL!J139 -> 0.13423836 | ... X17: =PL!Y139 -> 0.091902139
A18: 总资产回报率 | B18: =PL!C141 -> 0 | C18: =PL!D141 -> 0.041082886 | D18: =PL!E141 -> 0.053222823 | E18: =PL!F141 -> 0.054467865 | F18: =PL!G141 -> 0.046546741 | G18: =PL!H141 -> 0.055476984 | H18: =PL!I141 -> 0.05638712 | I18: =PL!J141 -> 0.079038702 | ... X18: =PL!Y141 -> 0.033413708
A19: 资产负债率 | B19: =BS!C95 -> 0 | C19: =BS!D95 -> 0.81986395 | D19: =BS!E95 -> 0.7166374 | E19: =BS!F95 -> 0.7191283 | F19: =BS!G95 -> 0.67287603 | G19: =BS!H95 -> 0.75248699 | H19: =BS!I95 -> 0.64474526 | I19: =BS!J95 -> 0.62773643 | ... X19: =BS!Y95 -> 0.69872186
A21: (RMB mn) | B21: =B4 -> 2005A | C21: =C4 -> 2006A | D21: =D4 -> 2007A | E21: =E4 -> 2008A | F21: =F4 -> 2009A | G21: =G4 -> 2010A | H21: =H4 -> 2011A | I21: =I4 -> 2012A | ... X21: =X4 -> 2027E
A22: Revenue | B22: =PL!C4 -> 7664.252 | C22: =PL!D4 -> 10294.826 | D22: =PL!E4 -> 10168.321 | E22: =PL!F4 -> 11021.405 | F22: =PL!G4 -> 11341.998 | G22: =PL!H4 -> 11982.871 | H22: =PL!I4 -> 16379.311 | I22: =PL!J4 -> 21910.66 | ... X22: =PL!Y4 -> 114194.84
A23: (+/-%) | C23: =PL!D5 -> 0.34322645 | D23: =PL!E5 -> -0.012288212 | E23: =PL!F5 -> 0.08389625 | F23: =PL!G5 -> 0.029088215 | G23: =PL!H5 -> 0.056504418 | H23: =PL!I5 -> 0.36689371 | I23: =PL!J5 -> 0.3377034 | J23: =PL!K5 -> 0.24531256 | ... X23: =PL!Y5 -> 0.10268765
A24: Profit Before Tax | B24: =B7 -> 201.524 | C24: =C7 -> 271.044 | D24: =D7 -> 530.31 | E24: =E7 -> 570.665 | F24: =F7 -> 722.08 | G24: =G7 -> 1333.467 | H24: =PL!I103 -> 1844.301 | I24: =PL!J103 -> 2541.397 | J24: =PL!K103 -> 3173.758 | K24: =PL!L103 -> 4047.594 | L24: =PL!M103 -> 5132.245 | M24: =PL!N103 -> 6011.72 | N24: =PL!O103 -> 6789.966 | O24: =PL!P103 -> 6205.505 | ... X24: =PL!Y103 -> 14554.861
A25: (+/-%) | C25: =C8 -> 0.34497132 | D25: =D8 -> 0.9565458 | E25: =E8 -> 0.076097 | F25: =F8 -> 0.2653308 | G25: =G8 -> 0.84670258 | H25: =H24/G24-1 -> 0.3830871 | I25: =I24/H24-1 -> 0.37797301 | J25: =J24/I24-1 -> 0.24882417 | K25: =K24/J24-1 -> 0.27533164 | L25: =L24/K24-1 -> 0.26797426 | M25: =M24/L24-1 -> 0.17136263 | N25: =N24/M24-1 -> 0.1294548 | O25: =O24/N24-1 -> -0.086077162 | ... X25: =X24/W24-1 -> 0.084244145
A26: Net Profit | B26: =B9 -> 152.021 | C26: =PL!D112 -> 222.182 | D26: =PL!E112 -> 404.893 | E26: =PL!F112 -> 489.321 | F26: =PL!G112 -> 612.531 | G26: =PL!H112 -> 1036.278 | H26: =PL!I112 -> 1507.405 | I26: =PL!J112 -> 2941.251 | J26: =PL!K112 -> 2749.551 | ... X26: =PL!Y112 -> 10494.75
A27: (+/-%) | C27: =PL!D113 -> 0.46152176 | D27: =PL!E113 -> 0.82234835 | E27: =PL!F113 -> 0.20851929 | F27: =PL!G113 -> 0.2517979 | G27: =PL!H113 -> 0.69179682 | H27: =PL!I113 -> 0.4546338 | I27: =PL!J113 -> 0.95120157 | J27: =PL!K113 -> -0.065176348 | ... X27: =PL!Y113 -> 0.086239244
A28: EPS (HK$ per share) | B28: =B11 -> 0.028779773 | C28: =PL!D122 -> 0.042062265 | D28: =PL!E122 -> 0.076652099 | E28: =PL!F122 -> 0.092635541 | F28: =PL!G122 -> 0.11596098 | G28: =PL!H122 -> 0.19618241 | H28: =PL!I122 -> 0.28537356 | I28: =PL!J122 -> 0.55682134 | J28: =PL!K122 -> 0.52052976 | ... X28: =PL!Y122 -> 1.9868079
A29: P/E (x) | B29: =B12 -> 0 | C29: =PL!D123 -> 201.84362 | D29: =PL!E123 -> 110.76018 | E29: =PL!F123 -> 91.649489 | F29: =PL!G123 -> 73.214286 | G29: =PL!H123 -> 43.276051 | H29: =PL!I123 -> 29.750478 | I29: =PL!J123 -> 15.24726 | J29: =PL!K123 -> 16.310307 | ... X29: =PL!Y123 -> 4.2731861
A30: P/B (x) | B30: =B13 -> 0 | C30: =PL!D128 -> 46.033642 | D30: =PL!E128 -> 20.803625 | E30: =PL!F128 -> 17.773069 | F30: =PL!G128 -> 10.417721 | G30: =PL!H128 -> 9.7080864 | H30: =PL!I128 -> 4.7254327 | I30: =PL!J128 -> 3.3195118 | J30: =PL!K128 -> 2.8145503 | ... X30: =PL!Y128 -> 0.53253311
A31: EV/EBITDA (X) | B31: =B14 -> 0 | C31: =PL!D138 -> 121.95838 | D31: =PL!E138 -> 74.952155 | E31: =PL!F138 -> 62.542272 | F31: =PL!G138 -> 42.3423 | G31: =PL!H138 -> 25.810928 | H31: =PL!I138 -> 16.794395 | I31: =PL!J138 -> 13.019921 | J31: =PL!K138 -> 11.412272 | ... X31: =PL!Y138 -> 5.7751923
A32: ROE (%) | B32: =B15 -> 0 | C32: =PL!D140 -> 0.24659394 | D32: =PL!E140 -> 0.25872716 | E32: =PL!F140 -> 0.20915891 | F32: =PL!G140 -> 0.17941637 | G32: =PL!H140 -> 0.23223914 | H32: =PL!I140 -> 0.21366778 | I32: =PL!J140 -> 0.255759 | J32: =PL!K140 -> 0.1867682 | ... X32: =PL!Y140 -> 0.13011735
A33: Dividend Yield | B33: =B16 -> 0 | C33: =PL!D132 -> 0.0042676655 | D33: =PL!E132 -> 0.00501694 | E33: =PL!F132 -> 0.0096297093 | F33: =PL!G132 -> 0.0074385906 | G33: =PL!H132 -> 0.0099448499 | H33: =PL!I132 -> 0.014133382 | I33: =PL!J132 -> 0.018848986 | J33: =PL!K132 -> 0.024737838 | ... X33: =PL!Y132 -> 0.093265883
A34: Net Profit Margin | C34: =C17 -> 0.021581909 | D34: =D17 -> 0.039819062 | E34: =E17 -> 0.044397334 | F34: =F17 -> 0.054005564 | G34: =G17 -> 0.086479943 | H34: =PL!I139 -> 0.092031038 | I34: =PL!J139 -> 0.13423836 | J34: =PL!K139 -> 0.10076923 | K34: =PL!L139 -> 0.10039061 | L34: =PL!M139 -> 0.11905007 | M34: =PL!N139 -> 0.11102235 | N34: =PL!O139 -> 0.10946789 | O34: =PL!P139 -> 0.080899641 | ... X34: =PL!Y139 -> 0.091902139
A35: ROA (%) | C35: =C18 -> 0.041082886 | D35: =D18 -> 0.053222823 | E35: =E18 -> 0.054467865 | F35: =F18 -> 0.046546741 | G35: =G18 -> 0.055476984 | H35: =PL!I141 -> 0.05638712 | I35: =PL!J141 -> 0.079038702 | J35: =PL!K141 -> 0.052421615 | K35: =PL!L141 -> 0.051929354 | L35: =PL!M141 -> 0.061886082 | M35: =PL!N141 -> 0.059531175 | N35: =PL!O141 -> 0.046322739 | O35: =PL!P141 -> 0.033059645 | ... X35: =PL!Y141 -> 0.033413708
A36: D/A | C36: =C19 -> 0.81986395 | D36: =D19 -> 0.7166374 | E36: =E19 -> 0.7191283 | F36: =F19 -> 0.67287603 | G36: =G19 -> 0.75248699 | H36: =BS!I95 -> 0.64474526 | I36: =BS!J95 -> 0.62773643 | J36: =BS!K95 -> 0.69137934 | K36: =BS!L95 -> 0.69964058 | L36: =BS!M95 -> 0.68148411 | M36: =BS!N95 -> 0.70211217 | N36: =BS!O95 -> 0.67546852 | O36: =BS!P95 -> 0.68353226 | ... X36: =BS!Y95 -> 0.69872186
A37: CPS (HK$/sh) | F37: =CF!G11/BS!$M$89 -> 0.21752175 | G37: =CF!H11/BS!$M$89 -> 0.0077662471 | H37: =CF!I11/BS!$N$89 -> -0.19016543 | I37: =CF!J11/BS!$N$89 -> -0.63227508 | J37: =CF!K11/BS!$N$89 -> -0.58411746 | K37: =CF!L11/BS!$N$89 -> -0.31974038 | L37: =CF!M11/BS!$N$89 -> 0.056415709 | M37: =CF!N11/BS!$N$89 -> 0.54276456 | N37: =CF!O11/BS!$N$89 -> -0.91736221 | O37: =CF!P11/BS!$N$89 -> -0.36435366 | ... X37: =CF!Y11/BS!$N$89 -> 0.46655233
A39: (RMB mn) | B39: =B4 -> 2005A | C39: =C4 -> 2006A | D39: =D4 -> 2007A | E39: =E4 -> 2008A | F39: =F4 -> 2009A | G39: =G4 -> 2010A | H39: =H4 -> 2011A | I39: =I4 -> 2012A | ... X39: =X4 -> 2027E
A40: Revenue | B40: =B5 -> 7664.252 | C40: =C5 -> 10294.826 | D40: =D5 -> 10168.321 | E40: =E5 -> 11021.405 | F40: =F5 -> 11341.998 | G40: =G5 -> 11982.871 | H40: =H5 -> 16379.311 | I40: =I5 -> 21910.66 | ... L40: =L5 -> 38001.876 | M40: =M22 -> 46207.508 | N40: =N22 -> 50152.524 | O40: =O22 -> 55626.304 | P40: =P22 -> 61669.678 | Q40: =Q22 -> 62458.009 | R40: =R22 -> 77309.614 | S40: =S22 -> 101975.26 | T40: =T22 -> 113734.01 | ... X40: =X22 -> 114194.84
A41: (+/-%) | C41: =C6 -> 0.34322645 | D41: =D6 -> -0.012288212 | E41: =E6 -> 0.08389625 | F41: =F6 -> 0.029088215 | G41: =G6 -> 0.056504418 | H41: =H40/G40-1 -> 0.36689371 | I41: =I40/H40-1 -> 0.3377034 | J41: =J40/I40-1 -> 0.24531256 | K41: =K40/J40-1 -> 0.26218774 | L41: =L40/K40-1 -> 0.10343626 | M41: =M40/L40-1 -> 0.21592702 | N41: =N40/M40-1 -> 0.085376082 | O41: =O40/N40-1 -> 0.10914266 | ... X41: =X40/W40-1 -> 0.10268765
A42: Profit Before Tax | B42: =B7 -> 201.524 | C42: =C7 -> 271.044 | D42: =D7 -> 530.31 | E42: =E7 -> 570.665 | F42: =F7 -> 722.08 | G42: =G7 -> 1333.467 | H42: =H24 -> 1844.301 | I42: =I24 -> 2541.397 | J42: =J24 -> 3173.758 | K42: =K24 -> 4047.594 | L42: =L24 -> 5132.245 | M42: =M24 -> 6011.72 | N42: =N24 -> 6789.966 | O42: =O24 -> 6205.505 | ... X42: =X24 -> 14554.861
A43: (+/-%) | C43: =C8 -> 0.34497132 | D43: =D8 -> 0.9565458 | E43: =E8 -> 0.076097 | F43: =F8 -> 0.2653308 | G43: =G8 -> 0.84670258 | H43: =H42/G42-1 -> 0.3830871 | I43: =I42/H42-1 -> 0.37797301 | J43: =J42/I42-1 -> 0.24882417 | K43: =K42/J42-1 -> 0.27533164 | L43: =L42/K42-1 -> 0.26797426 | M43: =M42/L42-1 -> 0.17136263 | N43: =N42/M42-1 -> 0.1294548 | O43: =O42/N42-1 -> -0.086077162 | ... X43: =X42/W42-1 -> 0.084244145
A44: Net Profit | B44: =B9 -> 152.021 | C44: =C9 -> 222.182 | D44: =D9 -> 404.893 | E44: =E9 -> 489.321 | F44: =F9 -> 612.531 | G44: =G9 -> 1036.278 | H44: =H9 -> 1507.405 | I44: =I9 -> 2941.251 | ... L44: =L9 -> 4524.126 | M44: =M26 -> 5130.066 | N44: =N26 -> 5490.091 | O44: =O26 -> 4500.148 | P44: =P26 -> 5413.208 | Q44: =Q26 -> 6015.368 | R44: =R26 -> 6800.879 | S44: =S26 -> 7956.876 | T44: =T26 -> 9164.045 | ... X44: =X26 -> 10494.75
A45: (+/-%) | C45: =C10 -> 0.46152176 | D45: =D10 -> 0.82234835 | E45: =E10 -> 0.20851929 | F45: =F10 -> 0.2517979 | G45: =G10 -> 0.69179682 | H45: =H44/G44-1 -> 0.4546338 | I45: =I44/H44-1 -> 0.95120157 | J45: =J44/I44-1 -> -0.065176348 | K45: =K44/J44-1 -> 0.25744531 | L45: =L44/K44-1 -> 0.30853037 | M45: =M44/L44-1 -> 0.13393526 | N45: =N44/M44-1 -> 0.070179409 | O45: =O44/N44-1 -> -0.1803145 | ... X45: =X44/W44-1 -> 0.086239244
A46: EPS (HK$/sh) | B46: =PL!C161 -> 0 | C46: =C11 -> 0.042062265 | D46: =D11 -> 0.076652099 | E46: =E11 -> 0.092635541 | F46: =F11 -> 0.11596098 | G46: =G11 -> 0.19618241 | H46: =H11 -> 0.28537356 | I46: =I11 -> 0.55682134 | J46: =J11 -> 0.52052976 | ... L46: =L11 -> 0.85648247 | M46: =M28 -> 0.97119567 | N46: =N28 -> 1.0393536 | O46: =O28 -> 0.85194309 | P46: =P28 -> 1.0247985 | Q46: =Q28 -> 1.1387961 | R46: =R28 -> 1.2875047 | S46: =S28 -> 1.5063517 | T46: =T28 -> 1.7348862 | ... X46: =X28 -> 1.9868079
A47: EV/EBITDA | B47: =PL!C174 -> 0 | C47: =C14 -> 121.95838 | D47: =D14 -> 74.952155 | E47: =E14 -> 62.542272 | F47: =F14 -> 42.3423 | G47: =G14 -> 25.810928 | H47: =H14 -> 16.794395 | I47: =I14 -> 13.019921 | J47: =J14 -> 11.412272 | ... L47: =L14 -> 7.7399307 | M47: =M31 -> 7.1004261 | N47: =N31 -> 6.4986503 | O47: =O31 -> 7.5830406 | P47: =P31 -> 6.3915119 | Q47: =Q31 -> 6.5030235 | R47: =R31 -> 6.7746921 | S47: =S31 -> 6.0045744 | T47: =T31 -> 5.5924149 | ... X47: =X31 -> 5.7751923
A48: ROE (%) | B48: =PL!C176 -> 0 | C48: =C15 -> 0.24659394 | D48: =D15 -> 0.25872716 | E48: =E15 -> 0.20915891 | F48: =F15 -> 0.17941637 | G48: =G15 -> 0.23223914 | H48: =H15 -> 0.21366778 | I48: =I15 -> 0.255759 | J48: =J15 -> 0.1867682 | ... L48: =L15 -> 0.2103528 | M48: =M32 -> 0.21097269 | N48: =N32 -> 0.1728194 | O48: =O32 -> 0.11758638 | P48: =P32 -> 0.13431855 | Q48: =Q32 -> 0.13185532 | R48: =R32 -> 0.12887783 | S48: =S32 -> 0.13930553 | T48: =T32 -> 0.15335571 | ... X48: =X32 -> 0.13011735
A49: Dividend Yield | B49: =PL!C168 -> 0 | C49: =C16 -> 0.0042676655 | D49: =D16 -> 0.00501694 | E49: =E16 -> 0.0096297093 | F49: =F16 -> 0.0074385906 | G49: =G16 -> 0.0099448499 | H49: =H16 -> 0.014133382 | I49: =I16 -> 0.018848986 | J49: =J16 -> 0.024737838 | ... L49: =L16 -> 0.038852305 | M49: =M33 -> 0.038867002 | N49: =N33 -> 0.04122497 | O49: =O33 -> 0.03180212 | P49: =P33 -> 0.037691401 | Q49: =Q33 -> 0.042402827 | R49: =R33 -> 0.047723741 | S49: =S33 -> 0.056537102 | T49: =T33 -> 0.065959953 | ... X49: =X33 -> 0.093265883
A50: Net Profit Margin | B50: =PL!C175 -> 0 | C50: =C17 -> 0.021581909 | D50: =D17 -> 0.039819062 | E50: =E17 -> 0.044397334 | F50: =F17 -> 0.054005564 | G50: =G17 -> 0.086479943 | H50: =H17 -> 0.092031038 | I50: =I17 -> 0.13423836 | J50: =J17 -> 0.10076923 | ... L50: =L17 -> 0.11905007 | M50: =M34 -> 0.11102235 | N50: =N34 -> 0.10946789 | O50: =O34 -> 0.080899641 | P50: =P34 -> 0.087777465 | Q50: =Q34 -> 0.096310595 | R50: =R34 -> 0.087969382 | S50: =S34 -> 0.07802751 | T50: =T34 -> 0.080574357 | ... X50: =X34 -> 0.091902139
A51: ROA (%) | B51: =PL!C177 -> 0 | C51: =C18 -> 0.041082886 | D51: =D18 -> 0.053222823 | E51: =E18 -> 0.054467865 | F51: =F18 -> 0.046546741 | G51: =G18 -> 0.055476984 | H51: =H18 -> 0.05638712 | I51: =I18 -> 0.079038702 | J51: =J18 -> 0.052421615 | ... L51: =L18 -> 0.061886082 | M51: =M35 -> 0.059531175 | N51: =N35 -> 0.046322739 | O51: =O35 -> 0.033059645 | P51: =P35 -> 0.033534117 | Q51: =Q35 -> 0.032200235 | R51: =R35 -> 0.031013963 | S51: =S35 -> 0.034768938 | T51: =T35 -> 0.036762839 | ... X51: =X35 -> 0.033413708
A52: D/A | B52: =BS!C140 -> 0 | C52: =C19 -> 0.81986395 | D52: =D19 -> 0.7166374 | E52: =E19 -> 0.7191283 | F52: =F19 -> 0.67287603 | G52: =G19 -> 0.75248699 | H52: =H19 -> 0.64474526 | I52: =I19 -> 0.62773643 | J52: =J19 -> 0.69137934 | ... L52: =L19 -> 0.68148411 | M52: =M36 -> 0.70211217 | N52: =N36 -> 0.67546852 | O52: =O36 -> 0.68353226 | P52: =P36 -> 0.68463428 | Q52: =Q36 -> 0.68802987 | R52: =R36 -> 0.69803477 | S52: =S36 -> 0.70375173 | T52: =T36 -> 0.70202502 | ... X52: =X36 -> 0.69872186
A53: P/E (x) | B53: =PL!C162 -> 0 | C53: =C12 -> 201.84362 | D53: =D12 -> 110.76018 | E53: =E12 -> 91.649489 | F53: =F12 -> 73.214286 | G53: =G12 -> 43.276051 | H53: =H12 -> 29.750478 | I53: =I12 -> 15.24726 | J53: =J12 -> 16.310307 | ... X53: =X12 -> 4.2731861
A54: P/B (x) | B54: =PL!C164 -> 0 | C54: =C13 -> 46.033642 | D54: =D13 -> 20.803625 | E54: =E13 -> 17.773069 | F54: =F13 -> 10.417721 | G54: =G13 -> 9.7080864 | H54: =H13 -> 4.7254327 | I54: =I13 -> 3.3195118 | J54: =J13 -> 2.8145503 | ... X54: =X13 -> 0.53253311
A55: CPS (HK$/sh) | F55: =CF!G11/BS!$M$89 -> 0.21752175 | G55: =CF!H11/BS!$M$89 -> 0.0077662471 | H55: =CF!I11/BS!$M$89 -> -0.19016543 | I55: =CF!J11/BS!$M$89 -> -0.63227508 | J55: =CF!K11/BS!$M$89 -> -0.58411746 | K55: =CF!L11/BS!$M$89 -> -0.31974038 | L55: =CF!M11/BS!$M$89 -> 0.056415709 | M55: =CF!N11/BS!$M$89 -> 0.54276456 | ... X55: =CF!Y11/BS!$M$89 -> 0.46655233

Sheet DCF
A1: Discounted Cash Flow
A2: Rmb mn
A3: Free cashflow forecast | J3: =PL!T3 -> 2022A | K3: =PL!U3 -> 2023A | L3: =PL!V3 -> 2024A | M3: =PL!W3 -> 2025A | N3: =PL!X3 -> 2026E | O3: =PL!Y3 -> 2027E | P3: =PL!Z3 -> 2028E | Q3: =PL!AA3 -> 2029E | ... W3: =PL!AG3 -> 2035E
B4: Net Revenue | J4: =PL!T4 -> 101975.26 | K4: =PL!U4 -> 113734.01 | L4: =PL!V4 -> 105322.67 | M4: =PL!W4 -> 100448.5 | N4: =PL!X4 -> 103560.46 | O4: =PL!Y4 -> 114194.84 | P4: =PL!Z4 -> 122886.67 | Q4: =PL!AA4 -> 134839.16 | ... W4: =PL!AG4 -> 195930.32
C5: YoY | J5: =PL!T5 -> 0.31905024 | K5: =PL!U5 -> 0.11530981 | L5: =PL!V5 -> -0.073956258 | M5: =PL!W5 -> -0.04627846 | N5: =PL!X5 -> 0.03098065 | O5: =PL!Y5 -> 0.10268765 | P5: =PL!Z5 -> 0.076113993 | Q5: =PL!AA5 -> 0.097264352 | ... W5: =PL!AG5 -> 0.050254062
B6: EBIT | J6: =PL!T133 -> 13770.104 | K6: =PL!U133 -> 15307.856 | L6: =PL!V133 -> 14787.551 | M6: =PL!W133 -> 14437.14 | N6: =PL!X133 -> 16024.37 | O6: =PL!Y133 -> 17294.995 | P6: =PL!Z133 -> 18132.901 | Q6: =PL!AA133 -> 19969.489 | ... W6: =PL!AG133 -> 29014.296
C7: YoY | J7: =PL!T133/PL!R133-1 -> 0.26048453 | K7: =PL!U133/PL!S133-1 -> 0.27000526 | L7: =PL!V133/PL!T133-1 -> 0.073888113 | M7: =PL!W133/PL!U133-1 -> -0.056880336 | N7: =PL!X133/PL!V133-1 -> 0.083639235 | O7: =PL!Y133/PL!W133-1 -> 0.19795163 | P7: =PL!Z133/PL!X133-1 -> 0.13158273 | Q7: =PL!AA133/PL!Y133-1 -> 0.15463972 | ... W7: =PL!AG133/PL!AE133-1 -> 0.10402064
C8: EBIT Margin | J8: =PL!T134 -> 0.13503377 | K8: =PL!U134 -> 0.13459347 | L8: =PL!V134 -> 0.14040235 | M8: =PL!W134 -> 0.14372679 | N8: =PL!X134 -> 0.15473445 | O8: =PL!Y134 -> 0.15145164 | P8: =PL!Z134 -> 0.14755792 | Q8: =PL!AA134 -> 0.14809859 | ... W8: =PL!AG134 -> 0.14808477
B9: EBIT*(1 - t) | J9: =J6*(1-PL!T106) -> 10820.003 | K9: =K6*(1-PL!U106) -> 12284.367 | L9: =L6*(1-PL!V106) -> 11516.398 | M9: =M6*(1-PL!W106) -> 10863.768 | N9: =N6*(1-PL!X106) -> 12058.14 | O9: =O6*(1-PL!Y106) -> 13014.269 | P9: =P6*(1-PL!Z106) -> 13644.783 | Q9: =Q6*(1-PL!AA106) -> 15026.792 | ... W9: =W6*(1-PL!AG106) -> 21832.897
B10: + | C10: Depreciation and Amortization | J10: =CAPEX!T43 -> 587.962 | K10: =CAPEX!U43 -> 731.641 | L10: =CAPEX!V43 -> 765.48 | M10: =CAPEX!W43 -> 1002.475 | N10: =CAPEX!X43 -> 949.41469 | O10: =CAPEX!Y43 -> 1004.5909 | P10: =CAPEX!Z43 -> 1059.8073 | Q10: =CAPEX!AA43 -> 1120.0331 | ... W10: =CAPEX!AG43 -> 1540.1001
B11: - | C11: Change in working capital | J11: =-WC!T7 -> -6972.483 | K11: =-WC!U7 -> -5342.665 | L11: =-WC!V7 -> -8369.435 | M11: =-WC!W7 -> -7275.46 | N11: =-WC!X7 -> -6226.549 | O11: =-WC!Y7 -> -6563.018 | P11: =-WC!Z7 -> -5918.9921 | Q11: =-WC!AA7 -> -8408.1448 | ... W11: =-WC!AG7 -> -9212.3905
B12: - | C12: Capex | J12: =-CAPEX!T3 -> -875.5373 | K12: =-CAPEX!U3 -> -1015.6575 | L12: =-CAPEX!V3 -> -968.17594 | M12: =-CAPEX!W3 -> -838.78107 | N12: =-CAPEX!X3 -> -847.74686 | O12: =-CAPEX!Y3 -> -911.68157 | P12: =-CAPEX!Z3 -> -952.20502 | Q12: =-CAPEX!AA3 -> -1016.4418 | ... W12: =-CAPEX!AG3 -> -1232.6982
B13: Free Cash Flows | J13: =SUM(J9:J12) -> 3559.9443 | K13: =SUM(K9:K12) -> 6657.6851 | L13: =SUM(L9:L12) -> 2944.2672 | M13: =SUM(M9:M12) -> 3752.0024 | N13: =SUM(N9:N12) -> 5933.2585 | O13: =SUM(O9:O12) -> 6544.1605 | P13: =SUM(P9:P12) -> 7833.3928 | Q13: =SUM(Q9:Q12) -> 6722.2387 | ... W13: =SUM(W9:W12) -> 12927.908
C14: YoY | K14: =K13/J13-1 -> 0.87016552 | L14: =L13/K13-1 -> -0.55776412 | M14: =M13/L13-1 -> 0.27434167 | N14: =N13/M13-1 -> 0.58135787 | O14: =O13/N13-1 -> 0.1029623 | P14: =P13/O13-1 -> 0.197005 | Q14: =Q13/P13-1 -> -0.14184839 | R14: =R13/Q13-1 -> 0.14852741 | ... W14: =W13/V13-1 -> 0.066799166
A15: DCF Analysis
B16: PV of FCF | J16: =NPV(T24,O13:W13)+N13 -> 57513.925 | R16: Tax rate | T16: 0.15
B17: Terminal value | J17: =W13*(1+T25)/(T24-T25) -> 146477.43 | R17: Debt ratio | T17: 0.3
B18: PV of terminal value | J18: =J17/(1+T24)^9 -> 65416.423 | R18: Beta | T18: 1.4
B19: Enterprise Value | J19: =J16+J18 -> 122930.35 | R19: Risk free rate | T19: 0.042
B20: Net Cash/(Debt), Minority interests | J20: =-BS!X80-BS!X100 -> -60750.495 | R20: Risk permium | T20: 0.05
B21: Equity Value | J21: =J19+J20 -> 62179.853 | R21: Equity cost | T21: =T19+T20*T18 -> 0.112
B22: Equity value per share (HK$) | J22: =J21/BS!$X$89 -> 11.771545 | R22: Debt cost | T22: 0.06
R23: Debt cost (After tax) | T23: =T22*(1-T16) -> 0.051
R24: WACC | T24: =T23*T17+T21*(1-T17) -> 0.0937
R25: Perpetual Growth | T25: 0.005
G28: Equity value per share (HK$)
G29: Perpetual Growth | J29: =K29-0.5% -> -0.015 | K29: =L29-0.5% -> -0.01 | L29: =M29-0.5% -> -0.005 | M29: =N29-0.5% -> 0 | N29: =T25 -> 0.005 | O29: =N29+0.5% -> 0.01 | P29: =O29+0.5% -> 0.015 | Q29: =P29+0.5% -> 0.02 | R29: =Q29+0.5% -> 0.025
G30: WACC | I30: =I31-0.5% -> 0.0787 | J30: =(NPV($I30,$O$13:$W$13)+$N$13+($W$13*(1+J$29)/($I30-J$29))/(1+$I30)^9+$J$20)/BS!$X$88 -> 13.099938 | K30: =(NPV($I30,$O$13:$W$13)+$N$13+($W$13*(1+K$29)/($I30-K$29))/(1+$I30)^9+$J$20)/BS!$X$88 -> 13.903119 | L30: =(NPV($I30,$O$13:$W$13)+$N$13+($W$13*(1+L$29)/($I30-L$29))/(1+$I30)^9+$J$20)/BS!$X$88 -> 14.802259 | M30: =(NPV($I30,$O$13:$W$13)+$N$13+($W$13*(1+M$29)/($I30-M$29))/(1+$I30)^9+$J$20)/BS!$X$88 -> 15.815649 | N30: =(NPV($I30,$O$13:$W$13)+$N$13+($W$13*(1+N$29)/($I30-N$29))/(1+$I30)^9+$J$20)/BS!$X$88 -> 16.96654 | O30: =(NPV($I30,$O$13:$W$13)+$N$13+($W$13*(1+O$29)/($I30-O$29))/(1+$I30)^9+$J$20)/BS!$X$88 -> 18.284956 | P30: =(NPV($I30,$O$13:$W$13)+$N$13+($W$13*(1+P$29)/($I30-P$29))/(1+$I30)^9+$J$20)/BS!$X$88 -> 19.810344 | Q30: =(NPV($I30,$O$13:$W$13)+$N$13+($W$13*(1+Q$29)/($I30-Q$29))/(1+$I30)^9+$J$20)/BS!$X$88 -> 21.595595 | R30: =(NPV($I30,$O$13:$W$13)+$N$13+($W$13*(1+R$29)/($I30-R$29))/(1+$I30)^9+$J$20)/BS!$X$88 -> 23.713294
I31: =I32-0.5% -> 0.0837 | J31: =(NPV($I31,$O$13:$W$13)+$N$13+($W$13*(1+J$29)/($I31-J$29))/(1+$I31)^9+$J$20)/BS!$X$88 -> 11.695309 | K31: =(NPV($I31,$O$13:$W$13)+$N$13+($W$13*(1+K$29)/($I31-K$29))/(1+$I31)^9+$J$20)/BS!$X$88 -> 12.390898 | L31: =(NPV($I31,$O$13:$W$13)+$N$13+($W$13*(1+L$29)/($I31-L$29))/(1+$I31)^9+$J$20)/BS!$X$88 -> 13.164908 | M31: =(NPV($I31,$O$13:$W$13)+$N$13+($W$13*(1+M$29)/($I31-M$29))/(1+$I31)^9+$J$20)/BS!$X$88 -> 14.031391 | N31: =(NPV($I31,$O$13:$W$13)+$N$13+($W$13*(1+N$29)/($I31-N$29))/(1+$I31)^9+$J$20)/BS!$X$88 -> 15.007975 | O31: =(NPV($I31,$O$13:$W$13)+$N$13+($W$13*(1+O$29)/($I31-O$29))/(1+$I31)^9+$J$20)/BS!$X$88 -> 16.117066 | P31: =(NPV($I31,$O$13:$W$13)+$N$13+($W$13*(1+P$29)/($I31-P$29))/(1+$I31)^9+$J$20)/BS!$X$88 -> 17.387597 | Q31: =(NPV($I31,$O$13:$W$13)+$N$13+($W$13*(1+Q$29)/($I31-Q$29))/(1+$I31)^9+$J$20)/BS!$X$88 -> 18.857583 | R31: =(NPV($I31,$O$13:$W$13)+$N$13+($W$13*(1+R$29)/($I31-R$29))/(1+$I31)^9+$J$20)/BS!$X$88 -> 20.577993
I32: =I33-0.5% -> 0.0887 | J32: =(NPV($I32,$O$13:$W$13)+$N$13+($W$13*(1+J$29)/($I32-J$29))/(1+$I32)^9+$J$20)/BS!$X$88 -> 10.432539 | K32: =(NPV($I32,$O$13:$W$13)+$N$13+($W$13*(1+K$29)/($I32-K$29))/(1+$I32)^9+$J$20)/BS!$X$88 -> 11.038326 | L32: =(NPV($I32,$O$13:$W$13)+$N$13+($W$13*(1+L$29)/($I32-L$29))/(1+$I32)^9+$J$20)/BS!$X$88 -> 11.708766 | M32: =(NPV($I32,$O$13:$W$13)+$N$13+($W$13*(1+M$29)/($I32-M$29))/(1+$I32)^9+$J$20)/BS!$X$88 -> 12.45479 | N32: =(NPV($I32,$O$13:$W$13)+$N$13+($W$13*(1+N$29)/($I32-N$29))/(1+$I32)^9+$J$20)/BS!$X$88 -> 13.289945 | O32: =(NPV($I32,$O$13:$W$13)+$N$13+($W$13*(1+O$29)/($I32-O$29))/(1+$I32)^9+$J$20)/BS!$X$88 -> 14.231219 | P32: =(NPV($I32,$O$13:$W$13)+$N$13+($W$13*(1+P$29)/($I32-P$29))/(1+$I32)^9+$J$20)/BS!$X$88 -> 15.30021 | Q32: =(NPV($I32,$O$13:$W$13)+$N$13+($W$13*(1+Q$29)/($I32-Q$29))/(1+$I32)^9+$J$20)/BS!$X$88 -> 16.524804 | R32: =(NPV($I32,$O$13:$W$13)+$N$13+($W$13*(1+R$29)/($I32-R$29))/(1+$I32)^9+$J$20)/BS!$X$88 -> 17.941642
I33: =T24 -> 0.0937 | J33: =(NPV($I33,$O$13:$W$13)+$N$13+($W$13*(1+J$29)/($I33-J$29))/(1+$I33)^9+$J$20)/BS!$X$88 -> 9.2918222 | K33: =(NPV($I33,$O$13:$W$13)+$N$13+($W$13*(1+K$29)/($I33-K$29))/(1+$I33)^9+$J$20)/BS!$X$88 -> 9.8220812 | L33: =(NPV($I33,$O$13:$W$13)+$N$13+($W$13*(1+L$29)/($I33-L$29))/(1+$I33)^9+$J$20)/BS!$X$88 -> 10.406065 | M33: =(NPV($I33,$O$13:$W$13)+$N$13+($W$13*(1+M$29)/($I33-M$29))/(1+$I33)^9+$J$20)/BS!$X$88 -> 11.052373 | N33: =(NPV($I33,$O$13:$W$13)+$N$13+($W$13*(1+N$29)/($I33-N$29))/(1+$I33)^9+$J$20)/BS!$X$88 -> 11.771545 | O33: =(NPV($I33,$O$13:$W$13)+$N$13+($W$13*(1+O$29)/($I33-O$29))/(1+$I33)^9+$J$20)/BS!$X$88 -> 12.576641 | P33: =(NPV($I33,$O$13:$W$13)+$N$13+($W$13*(1+P$29)/($I33-P$29))/(1+$I33)^9+$J$20)/BS!$X$88 -> 13.484035 | Q33: =(NPV($I33,$O$13:$W$13)+$N$13+($W$13*(1+Q$29)/($I33-Q$29))/(1+$I33)^9+$J$20)/BS!$X$88 -> 14.51455 | R33: =(NPV($I33,$O$13:$W$13)+$N$13+($W$13*(1+R$29)/($I33-R$29))/(1+$I33)^9+$J$20)/BS!$X$88 -> 15.695066
I34: =I33+0.5% -> 0.0987 | J34: =(NPV($I34,$O$13:$W$13)+$N$13+($W$13*(1+J$29)/($I34-J$29))/(1+$I34)^9+$J$20)/BS!$X$88 -> 8.2568492 | K34: =(NPV($I34,$O$13:$W$13)+$N$13+($W$13*(1+K$29)/($I34-K$29))/(1+$I34)^9+$J$20)/BS!$X$88 -> 8.7231423 | L34: =(NPV($I34,$O$13:$W$13)+$N$13+($W$13*(1+L$29)/($I34-L$29))/(1+$I34)^9+$J$20)/BS!$X$88 -> 9.2344011 | M34: =(NPV($I34,$O$13:$W$13)+$N$13+($W$13*(1+M$29)/($I34-M$29))/(1+$I34)^9+$J$20)/BS!$X$88 -> 9.7974591 | N34: =(NPV($I34,$O$13:$W$13)+$N$13+($W$13*(1+N$29)/($I34-N$29))/(1+$I34)^9+$J$20)/BS!$X$88 -> 10.420609 | O34: =(NPV($I34,$O$13:$W$13)+$N$13+($W$13*(1+O$29)/($I34-O$29))/(1+$I34)^9+$J$20)/BS!$X$88 -> 11.114012 | P34: =(NPV($I34,$O$13:$W$13)+$N$13+($W$13*(1+P$29)/($I34-P$29))/(1+$I34)^9+$J$20)/BS!$X$88 -> 11.890259 | Q34: =(NPV($I34,$O$13:$W$13)+$N$13+($W$13*(1+Q$29)/($I34-Q$29))/(1+$I34)^9+$J$20)/BS!$X$88 -> 12.76514 | R34: =(NPV($I34,$O$13:$W$13)+$N$13+($W$13*(1+R$29)/($I34-R$29))/(1+$I34)^9+$J$20)/BS!$X$88 -> 13.758729
I35: =I34+0.5% -> 0.1037 | J35: =(NPV($I35,$O$13:$W$13)+$N$13+($W$13*(1+J$29)/($I35-J$29))/(1+$I35)^9+$J$20)/BS!$X$88 -> 7.3140654 | K35: =(NPV($I35,$O$13:$W$13)+$N$13+($W$13*(1+K$29)/($I35-K$29))/(1+$I35)^9+$J$20)/BS!$X$88 -> 7.7258428 | L35: =(NPV($I35,$O$13:$W$13)+$N$13+($W$13*(1+L$29)/($I35-L$29))/(1+$I35)^9+$J$20)/BS!$X$88 -> 8.1755022 | M35: =(NPV($I35,$O$13:$W$13)+$N$13+($W$13*(1+M$29)/($I35-M$29))/(1+$I35)^9+$J$20)/BS!$X$88 -> 8.6685232 | N35: =(NPV($I35,$O$13:$W$13)+$N$13+($W$13*(1+N$29)/($I35-N$29))/(1+$I35)^9+$J$20)/BS!$X$88 -> 9.2114957 | O35: =(NPV($I35,$O$13:$W$13)+$N$13+($W$13*(1+O$29)/($I35-O$29))/(1+$I35)^9+$J$20)/BS!$X$88 -> 9.8124161 | P35: =(NPV($I35,$O$13:$W$13)+$N$13+($W$13*(1+P$29)/($I35-P$29))/(1+$I35)^9+$J$20)/BS!$X$88 -> 10.481084 | Q35: =(NPV($I35,$O$13:$W$13)+$N$13+($W$13*(1+Q$29)/($I35-Q$29))/(1+$I35)^9+$J$20)/BS!$X$88 -> 11.229641 | R35: =(NPV($I35,$O$13:$W$13)+$N$13+($W$13*(1+R$29)/($I35-R$29))/(1+$I35)^9+$J$20)/BS!$X$88 -> 12.073312
I36: =I35+0.5% -> 0.1087 | J36: =(NPV($I36,$O$13:$W$13)+$N$13+($W$13*(1+J$29)/($I36-J$29))/(1+$I36)^9+$J$20)/BS!$X$88 -> 6.4521159 | K36: =(NPV($I36,$O$13:$W$13)+$N$13+($W$13*(1+K$29)/($I36-K$29))/(1+$I36)^9+$J$20)/BS!$X$88 -> 6.8171633 | L36: =(NPV($I36,$O$13:$W$13)+$N$13+($W$13*(1+L$29)/($I36-L$29))/(1+$I36)^9+$J$20)/BS!$X$88 -> 7.2143169 | M36: =(NPV($I36,$O$13:$W$13)+$N$13+($W$13*(1+M$29)/($I36-M$29))/(1+$I36)^9+$J$20)/BS!$X$88 -> 7.6480071 | N36: =(NPV($I36,$O$13:$W$13)+$N$13+($W$13*(1+N$29)/($I36-N$29))/(1+$I36)^9+$J$20)/BS!$X$88 -> 8.123519 | O36: =(NPV($I36,$O$13:$W$13)+$N$13+($W$13*(1+O$29)/($I36-O$29))/(1+$I36)^9+$J$20)/BS!$X$88 -> 8.6472084 | P36: =(NPV($I36,$O$13:$W$13)+$N$13+($W$13*(1+P$29)/($I36-P$29))/(1+$I36)^9+$J$20)/BS!$X$88 -> 9.2267878 | Q36: =(NPV($I36,$O$13:$W$13)+$N$13+($W$13*(1+Q$29)/($I36-Q$29))/(1+$I36)^9+$J$20)/BS!$X$88 -> 9.8717087 | R36: =(NPV($I36,$O$13:$W$13)+$N$13+($W$13*(1+R$29)/($I36-R$29))/(1+$I36)^9+$J$20)/BS!$X$88 -> 10.593681
G39: % change from DCF TP upon WACC/perpetual growth change
G40: Perpetual Growth | J40: =J29 -> -0.015 | K40: =K29 -> -0.01 | L40: =L29 -> -0.005 | M40: =M29 -> 0 | N40: =N29 -> 0.005 | O40: =O29 -> 0.01 | P40: =P29 -> 0.015 | Q40: =Q29 -> 0.02 | R40: =R29 -> 0.025
G41: WACC | I41: =I30 -> 0.0787 | J41: =J30/$N$33-1 -> 0.11284775 | K41: =K30/$N$33-1 -> 0.18107846 | L41: =L30/$N$33-1 -> 0.257461 | M41: =M30/$N$33-1 -> 0.34354907 | N41: =N30/$N$33-1 -> 0.44131801 | O41: =O30/$N$33-1 -> 0.55331824 | P41: =P30/$N$33-1 -> 0.68290093 | Q41: =Q30/$N$33-1 -> 0.83455903 | R41: =R30/$N$33-1 -> 1.0144589
I42: =I31 -> 0.0837 | J42: =J31/$N$33-1 -> -0.0064763009 | K42: =K31/$N$33-1 -> 0.052614414 | L42: =L31/$N$33-1 -> 0.11836699 | M42: =M31/$N$33-1 -> 0.19197531 | N42: =N31/$N$33-1 -> 0.27493666 | O42: =O31/$N$33-1 -> 0.36915463 | P42: =P31/$N$33-1 -> 0.47708702 | Q42: =Q31/$N$33-1 -> 0.60196326 | R42: =R31/$N$33-1 -> 0.74811314
I43: =I32 -> 0.0887 | J43: =J32/$N$33-1 -> -0.11374944 | K43: =K32/$N$33-1 -> -0.062287413 | L43: =L32/$N$33-1 -> -0.0053331744 | M43: =M32/$N$33-1 -> 0.05804206 | N43: =N32/$N$33-1 -> 0.12898901 | O43: =O32/$N$33-1 -> 0.20895081 | P43: =P32/$N$33-1 -> 0.29976226 | Q43: =Q32/$N$33-1 -> 0.40379225 | R43: =R32/$N$33-1 -> 0.52415348
I44: =I33 -> 0.0937 | J44: =J33/$N$33-1 -> -0.210654 | K44: =K33/$N$33-1 -> -0.16560817 | L44: =L33/$N$33-1 -> -0.11599843 | M44: =M33/$N$33-1 -> -0.061094156 | N44: =N33/$N$33-1 -> 0 | O44: =O33/$N$33-1 -> 0.068393338 | P44: =P33/$N$33-1 -> 0.14547706 | Q44: =Q33/$N$33-1 -> 0.23301991 | R44: =R33/$N$33-1 -> 0.33330552
I45: =I34 -> 0.0987 | J45: =J34/$N$33-1 -> -0.29857559 | K45: =K34/$N$33-1 -> -0.2589637 | L45: =L34/$N$33-1 -> -0.21553196 | M45: =M34/$N$33-1 -> -0.16769983 | N45: =N34/$N$33-1 -> -0.11476289 | O45: =O34/$N$33-1 -> -0.055857865 | P45: =P34/$N$33-1 -> 0.010084801 | Q45: =Q34/$N$33-1 -> 0.084406459 | R45: =R34/$N$33-1 -> 0.16881247
I46: =I35 -> 0.1037 | J46: =J35/$N$33-1 -> -0.37866566 | K46: =K35/$N$33-1 -> -0.34368491 | L46: =L35/$N$33-1 -> -0.30548607 | M46: =M35/$N$33-1 -> -0.26360363 | N46: =N35/$N$33-1 -> -0.21747779 | O46: =O35/$N$33-1 -> -0.16642923 | P46: =P35/$N$33-1 -> -0.10962548 | Q46: =Q35/$N$33-1 -> -0.046035134 | R46: =R35/$N$33-1 -> 0.025635301
I47: =I36 -> 0.1087 | J47: =J36/$N$33-1 -> -0.45188879 | K47: =K36/$N$33-1 -> -0.42087779 | L47: =L36/$N$33-1 -> -0.38713935 | M47: =M36/$N$33-1 -> -0.3502971 | N47: =N36/$N$33-1 -> -0.30990207 | O47: =O36/$N$33-1 -> -0.26541434 | P47: =P36/$N$33-1 -> -0.21617871 | Q47: =Q36/$N$33-1 -> -0.16139229 | R47: =R36/$N$33-1 -> -0.10006029
A51: DCF 模型
A52: 港币 百万元
A53: 自由现金流预测 | J53: =J3 -> 2022A | K53: =K3 -> 2023A | L53: =L3 -> 2024A | M53: =M3 -> 2025A | N53: =N3 -> 2026E | O53: =O3 -> 2027E | P53: =P3 -> 2028E | Q53: =Q3 -> 2029E | ... W53: =W3 -> 2035E
B54: 营业收入 | J54: =J4 -> 101975.26 | K54: =K4 -> 113734.01 | L54: =L4 -> 105322.67 | M54: =M4 -> 100448.5 | N54: =N4 -> 103560.46 | O54: =O4 -> 114194.84 | P54: =P4 -> 122886.67 | Q54: =Q4 -> 134839.16 | ... W54: =W4 -> 195930.32
C55: YoY | J55: =J5 -> 0.31905024 | K55: =K5 -> 0.11530981 | L55: =L5 -> -0.073956258 | M55: =M5 -> -0.04627846 | N55: =N5 -> 0.03098065 | O55: =O5 -> 0.10268765 | P55: =P5 -> 0.076113993 | Q55: =Q5 -> 0.097264352 | ... W55: =W5 -> 0.050254062
B56: EBIT | J56: =J6 -> 13770.104 | K56: =K6 -> 15307.856 | L56: =L6 -> 14787.551 | M56: =M6 -> 14437.14 | N56: =N6 -> 16024.37 | O56: =O6 -> 17294.995 | P56: =P6 -> 18132.901 | Q56: =Q6 -> 19969.489 | ... W56: =W6 -> 29014.296
C57: YoY | J57: =J7 -> 0.26048453 | K57: =K7 -> 0.27000526 | L57: =L7 -> 0.073888113 | M57: =M7 -> -0.056880336 | N57: =N7 -> 0.083639235 | O57: =O7 -> 0.19795163 | P57: =P7 -> 0.13158273 | Q57: =Q7 -> 0.15463972 | ... W57: =W7 -> 0.10402064
C58: 息税前利润率 | J58: =J8 -> 0.13503377 | K58: =K8 -> 0.13459347 | L58: =L8 -> 0.14040235 | M58: =M8 -> 0.14372679 | N58: =N8 -> 0.15473445 | O58: =O8 -> 0.15145164 | P58: =P8 -> 0.14755792 | Q58: =Q8 -> 0.14809859 | ... W58: =W8 -> 0.14808477
B59: EBIT*(1-t) | J59: =J9 -> 10820.003 | K59: =K9 -> 12284.367 | L59: =L9 -> 11516.398 | M59: =M9 -> 10863.768 | N59: =N9 -> 12058.14 | O59: =O9 -> 13014.269 | P59: =P9 -> 13644.783 | Q59: =Q9 -> 15026.792 | ... W59: =W9 -> 21832.897
B60: + | C60: 折旧及摊销 | J60: =J10 -> 587.962 | K60: =K10 -> 731.641 | L60: =L10 -> 765.48 | M60: =M10 -> 1002.475 | N60: =N10 -> 949.41469 | O60: =O10 -> 1004.5909 | P60: =P10 -> 1059.8073 | Q60: =Q10 -> 1120.0331 | ... W60: =W10 -> 1540.1001
B61: - | C61: 营运资金变化 | J61: =J11 -> -6972.483 | K61: =K11 -> -5342.665 | L61: =L11 -> -8369.435 | M61: =M11 -> -7275.46 | N61: =N11 -> -6226.549 | O61: =O11 -> -6563.018 | P61: =P11 -> -5918.9921 | Q61: =Q11 -> -8408.1448 | ... W61: =W11 -> -9212.3905
B62: - | C62: 资本支出 | J62: =J12 -> -875.5373 | K62: =K12 -> -1015.6575 | L62: =L12 -> -968.17594 | M62: =M12 -> -838.78107 | N62: =N12 -> -847.74686 | O62: =O12 -> -911.68157 | P62: =P12 -> -952.20502 | Q62: =Q12 -> -1016.4418 | ... W62: =W12 -> -1232.6982
B63: 自由现金流 | J63: =J13 -> 3559.9443 | K63: =K13 -> 6657.6851 | L63: =L13 -> 2944.2672 | M63: =M13 -> 3752.0024 | N63: =N13 -> 5933.2585 | O63: =O13 -> 6544.1605 | P63: =P13 -> 7833.3928 | Q63: =Q13 -> 6722.2387 | ... W63: =W13 -> 12927.908
C64: YoY | J64: =J14 -> 0 | K64: =K14 -> 0.87016552 | L64: =L14 -> -0.55776412 | M64: =M14 -> 0.27434167 | N64: =N14 -> 0.58135787 | O64: =O14 -> 0.1029623 | P64: =P14 -> 0.197005 | Q64: =Q14 -> -0.14184839 | ... W64: =W14 -> 0.066799166
A65: DCF 分析
B66: 预测期自由现金流现值 | J66: =J16 -> 57513.925 | R66: 税率 | T66: =T16 -> 0.15
B67: 自由现金流终值 | J67: =J17 -> 146477.43 | R67: 目标债务资本比 | T67: =T17 -> 0.3
B68: 永续自由现金流现值 | J68: =J18 -> 65416.423 | R68: 贝塔系数 | T68: =T18 -> 1.4
B69: 企业价值 | J69: =J19 -> 122930.35 | R69: 无风险收益率 | T69: =T19 -> 0.042
B70: 净现金 | J70: =J20 -> -60750.495 | R70: 风险溢价 | T70: =T20 -> 0.05
B71: 权益价值 | J71: =J21 -> 62179.853 | R71: 权益资本成本 | T71: =T21 -> 0.112
B72: 每股权益价值（港元） | J72: =J22 -> 11.771545 | R72: 债务资本成本 | T72: =T22 -> 0.06
R73: 税后债务资本成本 | T73: =T23 -> 0.051
R74: WACC | T74: =T24 -> 0.0937
R75: 永续增长率 | T75: =T25 -> 0.005
G78: 每股权益价值（港元）
G79: 永续增长率 | J79: =J29 -> -0.015 | K79: =K29 -> -0.01 | L79: =L29 -> -0.005 | M79: =M29 -> 0 | N79: =N29 -> 0.005 | O79: =O29 -> 0.01 | P79: =P29 -> 0.015 | Q79: =Q29 -> 0.02 | R79: =R29 -> 0.025
G80: WACC | I80: =I30 -> 0.0787 | J80: =J30 -> 13.099938 | K80: =K30 -> 13.903119 | L80: =L30 -> 14.802259 | M80: =M30 -> 15.815649 | N80: =N30 -> 16.96654 | O80: =O30 -> 18.284956 | P80: =P30 -> 19.810344 | ... R80: =R30 -> 23.713294
I81: =I31 -> 0.0837 | J81: =J31 -> 11.695309 | K81: =K31 -> 12.390898 | L81: =L31 -> 13.164908 | M81: =M31 -> 14.031391 | N81: =N31 -> 15.007975 | O81: =O31 -> 16.117066 | P81: =P31 -> 17.387597 | ... R81: =R31 -> 20.577993
I82: =I32 -> 0.0887 | J82: =J32 -> 10.432539 | K82: =K32 -> 11.038326 | L82: =L32 -> 11.708766 | M82: =M32 -> 12.45479 | N82: =N32 -> 13.289945 | O82: =O32 -> 14.231219 | P82: =P32 -> 15.30021 | ... R82: =R32 -> 17.941642
I83: =I33 -> 0.0937 | J83: =J33 -> 9.2918222 | K83: =K33 -> 9.8220812 | L83: =L33 -> 10.406065 | M83: =M33 -> 11.052373 | N83: =N33 -> 11.771545 | O83: =O33 -> 12.576641 | P83: =P33 -> 13.484035 | ... R83: =R33 -> 15.695066
I84: =I34 -> 0.0987 | J84: =J34 -> 8.2568492 | K84: =K34 -> 8.7231423 | L84: =L34 -> 9.2344011 | M84: =M34 -> 9.7974591 | N84: =N34 -> 10.420609 | O84: =O34 -> 11.114012 | P84: =P34 -> 11.890259 | ... R84: =R34 -> 13.758729
I85: =I35 -> 0.1037 | J85: =J35 -> 7.3140654 | K85: =K35 -> 7.7258428 | L85: =L35 -> 8.1755022 | M85: =M35 -> 8.6685232 | N85: =N35 -> 9.2114957 | O85: =O35 -> 9.8124161 | P85: =P35 -> 10.481084 | ... R85: =R35 -> 12.073312
I86: =I36 -> 0.1087 | J86: =J36 -> 6.4521159 | K86: =K36 -> 6.8171633 | L86: =L36 -> 7.2143169 | M86: =M36 -> 7.6480071 | N86: =N36 -> 8.123519 | O86: =O36 -> 8.6472084 | P86: =P36 -> 9.2267878 | ... R86: =R36 -> 10.593681
G89: 基于WACC/永续增长率变化的DCF目标价敏感性分析（%）
G90: 永续增长率 | J90: =J40 -> -0.015 | K90: =K40 -> -0.01 | L90: =L40 -> -0.005 | M90: =M40 -> 0 | N90: =N40 -> 0.005 | O90: =O40 -> 0.01 | P90: =P40 -> 0.015 | Q90: =Q40 -> 0.02 | R90: =R40 -> 0.025
G91: WACC | I91: =I41 -> 0.0787 | J91: =J41 -> 0.11284775 | K91: =K41 -> 0.18107846 | L91: =L41 -> 0.257461 | M91: =M41 -> 0.34354907 | N91: =N41 -> 0.44131801 | O91: =O41 -> 0.55331824 | P91: =P41 -> 0.68290093 | ... R91: =R41 -> 1.0144589
I92: =I42 -> 0.0837 | J92: =J42 -> -0.0064763009 | K92: =K42 -> 0.052614414 | L92: =L42 -> 0.11836699 | M92: =M42 -> 0.19197531 | N92: =N42 -> 0.27493666 | O92: =O42 -> 0.36915463 | P92: =P42 -> 0.47708702 | ... R92: =R42 -> 0.74811314
I93: =I43 -> 0.0887 | J93: =J43 -> -0.11374944 | K93: =K43 -> -0.062287413 | L93: =L43 -> -0.0053331744 | M93: =M43 -> 0.05804206 | N93: =N43 -> 0.12898901 | O93: =O43 -> 0.20895081 | P93: =P43 -> 0.29976226 | ... R93: =R43 -> 0.52415348
I94: =I44 -> 0.0937 | J94: =J44 -> -0.210654 | K94: =K44 -> -0.16560817 | L94: =L44 -> -0.11599843 | M94: =M44 -> -0.061094156 | N94: =N44 -> 0 | O94: =O44 -> 0.068393338 | P94: =P44 -> 0.14547706 | ... R94: =R44 -> 0.33330552
I95: =I45 -> 0.0987 | J95: =J45 -> -0.29857559 | K95: =K45 -> -0.2589637 | L95: =L45 -> -0.21553196 | M95: =M45 -> -0.16769983 | N95: =N45 -> -0.11476289 | O95: =O45 -> -0.055857865 | P95: =P45 -> 0.010084801 | ... R95: =R45 -> 0.16881247
I96: =I46 -> 0.1037 | J96: =J46 -> -0.37866566 | K96: =K46 -> -0.34368491 | L96: =L46 -> -0.30548607 | M96: =M46 -> -0.26360363 | N96: =N46 -> -0.21747779 | O96: =O46 -> -0.16642923 | P96: =P46 -> -0.10962548 | ... R96: =R46 -> 0.025635301
I97: =I47 -> 0.1087 | J97: =J47 -> -0.45188879 | K97: =K47 -> -0.42087779 | L97: =L47 -> -0.38713935 | M97: =M47 -> -0.3502971 | N97: =N47 -> -0.30990207 | O97: =O47 -> -0.26541434 | P97: =P47 -> -0.21617871 | ... R97: =R47 -> -0.10006029

Sheet QoQ
A1: 百万人民币 | B1: (Rmb mn) | D1: 1Q13 | E1: 1~2Q13 | F1: 1~3Q13 | G1: 1~4Q13 | H1: 1Q14 | I1: 1~2Q14 | J1: 1~3Q14 | K1: 1~4Q14 | L1: 1Q15 | M1: 1~2Q15 | N1: 1~3Q15 | O1: 1~4Q15 | P1: 1Q16 | Q1: 1~2Q16 | R1: 1~3Q16 | S1: 1~4Q16 | T1: 1Q17 | U1: 1-2Q17 | V1: 1-3Q17 | W1: 1-4Q17 | X1: 1Q18 | Y1: 1-2Q18 | Z1: 1-3Q18 | AA1: 1-4Q18 | AB1: 1Q19 | AC1: 1-2Q19 | AD1: 1-3Q19 | AE1: 2019 | AF1: 1Q20 | AG1: 1-2Q20 | AH1: 1-3Q20 | AI1: 2020 | AJ1: 1Q21 | AK1: 1-2Q21 | AL1: 1-3Q21 | AM1: 2021 | AN1: 1Q22 | AO1: 1-2Q22 | AP1: 1-3Q22 | AQ1: 1-4Q22 | AR1: 1Q23 | AS1: 1-2Q23 | AT1: 1-3Q23 | AU1: 1-4Q23 | AV1: 1Q24 | AW1: 1H24 | AX1: 1-3Q24 | AY1: 2024 | AZ1: 1Q25 | BA1: 1H25 | BB1: 1-3Q25 | BC1: 2025
A2: 金额 | B2: Amount
A3: 集团营业额 | B3: Group revenue | H3: =6292599000/1000000 -> 6292.599 | I3: 14283.426 | J3: =22553807000/1000000 -> 22553.807 | K3: =34439575/1000 -> 34439.575 | L3: =7382647000/1000000 -> 7382.647 | M3: 17017.498 | N3: =25727859000/1000000 -> 25727.859 | O3: =38001876/1000 -> 38001.876 | P3: =8747118000/1000000 -> 8747.118 | Q3: 18845.053 | R3: =30237074000/1000000 -> 30237.074 | S3: =46207508/1000 -> 46207.508 | T3: =10610028000/1000000 -> 10610.028 | U3: =22966135/1000 -> 22966.135 | V3: =33688348000/1000000 -> 33688.348 | W3: 50152.524 | X3: =11617901000/1000000 -> 11617.901 | Y3: =27105613/1000 -> 27105.613 | Z3: =38199455000/1000000 -> 38199.455 | AA3: =55626304*(10^(-3)) -> 55626.304 | AB3: =11555483000*(10^(-6)) -> 11555.483 | AC3: 27542.5 | AD3: 40561.896 | AE3: 61669.678 | AF3: 9949.155 | AG3: 28002.101 | AH3: 42249.91 | AI3: 62458.009 | AJ3: 13959.135 | AK3: 36370.988 | AL3: 52835.893 | AM3: 77309.614 | AN3: 17325.929 | AO3: 53810.559 | AP3: =73411573000*(10^(-6)) -> 73411.573 | AQ3: 101975.26 | AR3: =21639304000/1000000 -> 21639.304 | AS3: 55111 | AT3: 79488.136 | AU3: 113734.01 | AV3: 22087.638 | AW3: 56567.777 | AX3: 81522.806 | AY3: 105322.67 | AZ3: 22887.286 | BA3: 56643.42 | BB3: 77702.518 | BC3: 100448.5
A4: 应占合营企业营业额 | B4: Share of revenue of JVs | M4: 588.865 | N4: =898825000/1000000 -> 898.825 | O4: =1169129/1000 -> 1169.129 | Q4: 1423.928 | R4: =1856275000/1000000 -> 1856.275 | S4: =2878125/1000 -> 2878.125 | T4: =288898000/1000000 -> 288.898 | U4: =2461251/1000 -> 2461.251 | V4: =4463208000/1000000 -> 4463.208 | W4: 4674.94 | X4: =370039000/1000000 -> 370.039 | Y4: =1236101/1000 -> 1236.101 | Z4: =1776247000/1000000 -> 1776.247 | AA4: =4519203*(10^(-3)) -> 4519.203 | AB4: =476546000*(10^(-6)) -> 476.546 | AC4: 968.904 | AD4: 1266.26 | AE4: 1721.811 | AF4: 246.811 | AG4: 542.714 | AH4: 980.111 | AI4: 1552.509 | AJ4: 348.025 | AK4: 516.635 | AL4: 934.796 | AM4: 2563.559 | AN4: 717.146 | AO4: 2014.292 | AP4: =2638729000*(10^(-6)) -> 2638.729 | AQ4: 4400.665 | AR4: =671303000/1000000 -> 671.303 | AS4: 1770.897 | AT4: 2440.26 | AU4: 3717.868 | AV4: 555.444 | AW4: 1758.34 | AX4: 2285.039 | AY4: 3207.7 | AZ4: 994.667 | BA4: 1914.935 | BB4: 2684.081 | BC4: 3636.25
A5: 经营及应占合营企业收入 | B5: Group revenue & share of revenue of JVs | N5: =SUM(N3:N4) -> 26626.684 | O5: =SUM(O3:O4) -> 39171.005 | Q5: =SUM(Q3:Q4) -> 20268.981 | R5: =SUM(R3:R4) -> 32093.349 | S5: =SUM(S3:S4) -> 49085.633 | T5: =SUM(T3:T4) -> 10898.926 | U5: =SUM(U3:U4) -> 25427.386 | V5: =SUM(V3:V4) -> 38151.556 | W5: =SUM(W3:W4) -> 54827.464 | X5: =SUM(X3:X4) -> 11987.94 | ... BC5: =SUM(BC3:BC4) -> 104084.75
A7: 经营盈利 | B7: Group results | I7: 1901.044 | K7: =4364261/1000 -> 4364.261 | M7: 2341.696 | O7: =5154724/1000 -> 5154.724 | P7: =1196743000/1000000 -> 1196.743 | Q7: 1922.575 | S7: =5436591/1000 -> 5436.591 | T7: =1377619000/1000000 -> 1377.619 | U7: =2900752/1000 -> 2900.752 | W7: =6815392/1000 -> 6815.392 | Y7: =3867695/1000 -> 3867.695 | AA7: =8064949*(10^(-3)) -> 8064.949 | AC7: 4046.673 | AE7: 8502.783 | AG7: 4800.372 | AI7: 8313.182 | AK7: 5530.095 | AM7: 10873.171 | AO7: 6606.34 | AQ7: 12570.522 | AS7: 7768.392 | AU7: 14536.336 | AW7: 7850.528 | AY7: 14562.39 | BA7: 7811.028 | BC7: 14172.14
A8: 应占合营企业盈利 | B8: Share of results of JVs | I8: 171.639 | K8: =294345/1000 -> 294.345 | M8: 167.906 | O8: =423728/1000 -> 423.728 | Q8: 239.963 | S8: =420295/1000 -> 420.295 | T8: =T9-T7 -> 71.396 | U8: =416360/1000 -> 416.36 | W8: 731.38 | Y8: =384923/1000 -> 384.923 | AA8: =705024*(10^(-3)) -> 705.024 | AC8: 320.195 | AE8: 452.654 | AG8: 112.162 | AI8: 701.944 | AK8: 219.817 | AM8: 369.246 | AO8: 89.601 | AQ8: 275.196 | AS8: 345.238 | AU8: 629.969 | AW8: 605.709 | AY8: 583.499 | BA8: 798.78 | BC8: 846.409
A9: 经营及应占合营企业盈利 | B9: Operating profit & share of profits of JVs | H9: =855331000/1000000 -> 855.331 | I9: =SUM(I7:I8) -> 2072.683 | J9: =2833067000/1000000 -> 2833.067 | K9: =SUM(K7:K8) -> 4658.606 | L9: =1070076000/1000000 -> 1070.076 | M9: =SUM(M7:M8) -> 2509.602 | N9: =3543966000/1000000 -> 3543.966 | O9: =SUM(O7:O8) -> 5578.452 | P9: =1286763000/1000000 -> 1286.763 | Q9: =SUM(Q7:Q8) -> 2162.538 | R9: =3736250000/1000000 -> 3736.25 | S9: =SUM(S7:S8) -> 5856.886 | T9: =1449015000/1000000 -> 1449.015 | U9: =SUM(U7:U8) -> 3317.112 | V9: =5024756000/1000000 -> 5024.756 | W9: =SUM(W7:W8) -> 7546.772 | X9: =1684902000/1000000 -> 1684.902 | Y9: =SUM(Y7:Y8) -> 4252.618 | Z9: =5812992000/1000000 -> 5812.992 | AA9: =SUM(AA7:AA8) -> 8769.973 | AB9: =2164569000*(10^(-6)) -> 2164.569 | AC9: =SUM(AC7:AC8) -> 4366.868 | AD9: 6248.137 | AE9: =SUM(AE7:AE8) -> 8955.437 | AF9: 1716.843 | AG9: =SUM(AG7:AG8) -> 4912.534 | AH9: 7081.776 | AI9: =SUM(AI7:AI8) -> 9015.126 | AJ9: 2406.654 | AK9: =SUM(AK7:AK8) -> 5749.912 | AL9: 8371.57 | AM9: =SUM(AM7:AM8) -> 11242.417 | AN9: 2904.704 | AO9: =SUM(AO7:AO8) -> 6695.941 | AP9: =9828671000*(10^(-6)) -> 9828.671 | AQ9: =SUM(AQ7:AQ8) -> 12845.718 | AR9: =3398564000/1000000 -> 3398.564 | AS9: =SUM(AS7:AS8) -> 8113.63 | AT9: 11560.019 | AU9: =SUM(AU7:AU8) -> 15166.305 | AV9: 3575.514 | AW9: =SUM(AW7:AW8) -> 8456.237 | AX9: 11901.606 | AY9: =SUM(AY7:AY8) -> 15145.889 | AZ9: 3963.014 | BA9: =SUM(BA7:BA8) -> 8609.808 | BB9: 11923.338 | BC9: =SUM(BC7:BC8) -> 15018.549
A10: 增速 | B10: YoY
A11: 集团营业额 | B11: Group revenue | L11: =L3/H3-1 -> 0.17322699 | M11: =M3/I3-1 -> 0.1914157 | N11: =N3/J3-1 -> 0.14073243 | O11: =O3/K3-1 -> 0.10343626 | P11: =P3/L3-1 -> 0.18482138 | Q11: =Q3/M3-1 -> 0.1073927 | R11: =R3/N3-1 -> 0.17526585 | S11: =S3/O3-1 -> 0.21592702 | ... BC11: =BC3/AY3-1 -> -0.046278451
A12: 应占合营企业营业额 | B12: Share of revenue of JVs | Q12: =Q4/M4-1 -> 1.418089 | R12: =R4/N4-1 -> 1.065224 | S12: =S4/O4-1 -> 1.4617685 | U12: =U4/Q4-1 -> 0.728494 | V12: =V4/R4-1 -> 1.4043894 | W12: =W4/S4-1 -> 0.62430054 | X12: =X4/T4-1 -> 0.28086383 | Y12: =Y4/U4-1 -> -0.49777532 | Z12: =Z4/V4-1 -> -0.6020246 | AA12: =AA4/W4-1 -> -0.033313155 | AB12: =AB4/X4-1 -> 0.28782642 | ... BC12: =BC4/AY4-1 -> 0.1336004
A13: 合计 | B13: Group revenue & share of revenue of JVs | R13: =R5/N5-1 -> 0.20530777 | S13: =S5/O5-1 -> 0.2531114 | U13: =U5/Q5-1 -> 0.2544975 | V13: =V5/R5-1 -> 0.1887683 | W13: =W5/S5-1 -> 0.1169758 | X13: =X5/T5-1 -> 0.099919387 | Y13: =Y5/U5-1 -> 0.11461375 | Z13: =Z5/V5-1 -> 0.047813148 | AA13: =AA5/W5-1 -> 0.096995969 | AB13: =AB5/X5-1 -> 0.0036777795 | ... BC13: =BC5/AY5-1 -> -0.040961991
A15: 经营盈利 | B15: Group results | O15: =O7/K7-1 -> 0.18112184 | Q15: =Q7/M7-1 -> -0.17898181 | S15: =S7/O7-1 -> 0.054681298 | T15: =T7/P7-1 -> 0.15114022 | U15: =U7/Q7-1 -> 0.50878483 | W15: =W7/S7-1 -> 0.253615 | Y15: =Y7/U7-1 -> 0.33334218 | AA15: =AA7/W7-1 -> 0.18334338 | AC15: =AC7/Y7-1 -> 0.046275107 | AE15: =AE7/AA7-1 -> 0.054288502 | AG15: =AG7/AC7-1 -> 0.18625152 | AI15: =AI7/AE7-1 -> -0.022298699 | AK15: =AK7/AG7-1 -> 0.15201384 | AM15: =AM7/AI7-1 -> 0.30794334 | AO15: =AO7/AK7-1 -> 0.19461601
A16: 应占合营企业盈利 | B16: Share of results of JVs | O16: =O8/K8-1 -> 0.43956242 | Q16: =Q8/M8-1 -> 0.42915083 | S16: =S8/O8-1 -> -0.0081018956 | U16: =U8/Q8-1 -> 0.73510083 | W16: =W8/S8-1 -> 0.7401587 | Y16: =Y8/U8-1 -> -0.075504371 | AA16: =AA8/W8-1 -> -0.036035987 | AC16: =AC8/Y8-1 -> -0.16815831 | AE16: =AE8/AA8-1 -> -0.35795945 | AG16: =AG8/AC8-1 -> -0.64970721 | AI16: =AI8/AE8-1 -> 0.5507297 | AK16: =AK8/AG8-1 -> 0.95981705 | AM16: =AM8/AI8-1 -> -0.47396658 | AO16: =AO8/AK8-1 -> -0.59238366
A17: 经营及应占合营企业盈利 | B17: Operating profit & share of profits of JVs | L17: =L9/H9-1 -> 0.25106655 | M17: =M9/I9-1 -> 0.21079876 | N17: =N9/J9-1 -> 0.25092912 | O17: =O9/K9-1 -> 0.19745091 | P17: =P9/L9-1 -> 0.20249683 | Q17: =Q9/M9-1 -> -0.13829444 | R17: =R9/N9-1 -> 0.054256728 | S17: =S9/O9-1 -> 0.049912413 | ... BC17: =BC9/AY9-1 -> -0.0084075619
A18: 经营及应占合营企业盈利/收入 | B18: Operating profit & share of profits of JVs Margin | N18: =N9/N5 -> 0.13309829 | O18: =O9/O5 -> 0.14241279 | Q18: =Q9/Q5 -> 0.10669199 | R18: =R9/R5 -> 0.1164182 | S18: =S9/S5 -> 0.11931976 | T18: =T9/T5 -> 0.13295026 | U18: =U9/U5 -> 0.13045431 | V18: =V9/V5 -> 0.13170514 | W18: =W9/W5 -> 0.13764583 | X18: =X9/X5 -> 0.14054975 | ... BC18: =BC9/BC5 -> 0.14429154
A20: 百万人民币 | B20: (Rmb mn) | D20: 1Q13 | E20: 2Q13 | F20: 3Q13 | G20: 4Q13 | H20: 1Q14 | I20: 2Q14 | J20: 3Q14 | K20: 4Q14 | L20: 1Q15 | M20: 2Q15 | N20: 3Q15 | O20: 4Q15 | P20: 1Q16 | Q20: 2Q16 | R20: 3Q16 | S20: 4Q16 | T20: 1Q17 | U20: 2Q17 | V20: 3Q17 | W20: 4Q17 | X20: 1Q18 | Y20: 2Q18 | Z20: 3Q18 | AA20: 4Q18 | AB20: 1Q19 | AC20: 2Q19 | AD20: 3Q19 | AE20: 4Q19 | AF20: 1Q20 | AG20: 2Q20 | AH20: 3Q20 | AI20: 4Q20 | AJ20: 1Q21 | AK20: 2Q21 | AL20: 3Q21 | AM20: 4Q21 | AN20: 1Q22 | AO20: 2Q22 | AP20: 3Q22 | AQ20: 4Q22 | AR20: 1Q23 | AS20: 2Q23 | AT20: 3Q23 | AU20: 4Q23 | AV20: =AV1 -> 1Q24 | AW20: 2Q24 | AX20: 3Q24 | AY20: 4Q24 | AZ20: =AZ1 -> 1Q25 | BA20: 2Q25 | BB20: 3Q25 | BC20: 4Q25
A21: 金额 | B21: Amount
A22: 集团营业额 | B22: Group revenue | H22: =H3 -> 6292.599 | I22: =I3-H3 -> 7990.827 | J22: =J3-I3 -> 8270.381 | K22: =K3-J3 -> 11885.768 | L22: =L3 -> 7382.647 | M22: =M3-L3 -> 9634.851 | N22: =N3-M3 -> 8710.361 | O22: =O3-N3 -> 12274.017 | P22: =P3 -> 8747.118 | Q22: =Q3-P3 -> 10097.935 | R22: =R3-Q3 -> 11392.021 | S22: =S3-R3 -> 15970.434 | T22: =T3 -> 10610.028 | U22: =U3-T3 -> 12356.107 | V22: =V3-U3 -> 10722.213 | W22: =W3-V3 -> 16464.176 | X22: =X3 -> 11617.901 | Y22: =Y3-X3 -> 15487.712 | Z22: =Z3-Y3 -> 11093.842 | AA22: =AA3-Z3 -> 17426.849 | AB22: =AB3 -> 11555.483 | AC22: =AC3-AB3 -> 15987.017 | AD22: =AD3-AC3 -> 13019.396 | AE22: =AE3-AD3 -> 21107.782 | AF22: =AF3 -> 9949.155 | AG22: =AG3-AF3 -> 18052.946 | AH22: =AH3-AG3 -> 14247.809 | AI22: =AI3-AH3 -> 20208.099 | AJ22: =AJ3 -> 13959.135 | AK22: =AK3-AJ3 -> 22411.853 | AL22: =AL3-AK3 -> 16464.905 | AM22: =AM3-AL3 -> 24473.721 | AN22: =AN3 -> 17325.929 | AO22: =AO3-AN3 -> 36484.63 | AP22: =AP3-AO3 -> 19601.014 | AQ22: =AQ3-AP3 -> 28563.692 | AR22: =AR3 -> 21639.304 | AS22: =AS3-AR3 -> 33471.696 | AT22: =AT3-AS3 -> 24377.136 | AU22: =AU3-AT3 -> 34245.877 | AV22: =AV3 -> 22087.638 | AW22: =AW3-AV3 -> 34480.139 | AX22: =AX3-AW3 -> 24955.029 | AY22: =AY3-AX3 -> 23799.864 | AZ22: =AZ3 -> 22887.286 | BA22: =BA3-AZ3 -> 33756.134 | BB22: =BB3-BA3 -> 21059.098 | BC22: =BC3-BB3 -> 22745.982
A23: 应占合营企业营业额 | B23: Share of revenue of JVs | N23: =N4-M4 -> 309.96 | O23: =O4-N4 -> 270.304 | R23: =R4-Q4 -> 432.347 | S23: =S4-R4 -> 1021.85 | T23: =T4 -> 288.898 | U23: =U4-T4 -> 2172.353 | V23: =V4-U4 -> 2001.957 | W23: =W4-V4 -> 211.732 | X23: =X4 -> 370.039 | Y23: =Y4-X4 -> 866.062 | Z23: =Z4-Y4 -> 540.146 | AA23: =AA4-Z4 -> 2742.956 | AB23: =AB4 -> 476.546 | AC23: =AC4-AB4 -> 492.358 | AD23: =AD4-AC4 -> 297.356 | AE23: =AE4-AD4 -> 455.551 | AF23: =AF4 -> 246.811 | AG23: =AG4-AF4 -> 295.903 | AH23: =AH4-AG4 -> 437.397 | AI23: =AI4-AH4 -> 572.398 | AJ23: =AJ4 -> 348.025 | AK23: =AK4-AJ4 -> 168.61 | AL23: =AL4-AK4 -> 418.161 | AM23: =AM4-AL4 -> 1628.763 | AN23: =AN4 -> 717.146 | AO23: =AO4-AN4 -> 1297.146 | AP23: =AP4-AO4 -> 624.437 | AQ23: =AQ4-AP4 -> 1761.936 | AR23: =AR4 -> 671.303 | AS23: =AS4-AR4 -> 1099.594 | AT23: =AT4-AS4 -> 669.363 | AU23: =AU4-AT4 -> 1277.608 | AV23: =AV4 -> 555.444 | AW23: =AW4-AV4 -> 1202.896 | AX23: =AX4-AW4 -> 526.699 | AY23: =AY4-AX4 -> 922.661 | AZ23: =AZ4 -> 994.667 | BA23: =BA4-AZ4 -> 920.268 | BB23: =BB4-BA4 -> 769.146 | BC23: =BC4-BB4 -> 952.169
A24: 经营及应占合营企业收入 | B24: Group revenue & share of revenue of JVs | N24: =SUM(N22:N23) -> 9020.321 | O24: =O5-N5 -> 12544.321 | R24: =SUM(R22:R23) -> 11824.368 | S24: =SUM(S22:S23) -> 16992.284 | T24: =SUM(T22:T23) -> 10898.926 | U24: =SUM(U22:U23) -> 14528.46 | V24: =V5-U5 -> 12724.17 | W24: =W5-V5 -> 16675.908 | X24: =SUM(X22:X23) -> 11987.94 | Y24: =SUM(Y22:Y23) -> 16353.774 | Z24: =SUM(Z22:Z23) -> 11633.988 | AA24: =AA5-Z5 -> 20169.805 | AB24: =SUM(AB22:AB23) -> 12032.029 | AC24: =SUM(AC22:AC23) -> 16479.375 | AD24: =SUM(AD22:AD23) -> 13316.752 | AE24: =SUM(AE22:AE23) -> 21563.333 | AF24: =SUM(AF22:AF23) -> 10195.966 | AG24: =SUM(AG22:AG23) -> 18348.849 | AH24: =SUM(AH22:AH23) -> 14685.206 | AI24: =SUM(AI22:AI23) -> 20780.497 | ... BC24: =SUM(BC22:BC23) -> 23698.151
A26: 经营盈利 | B26: Group results | P26: =P7 -> 1196.743 | Q26: =Q7-P7 -> 725.832 | T26: =T7 -> 1377.619 | U26: =U7-T7 -> 1523.133 | X26: =X7
A27: 应占合营企业盈利 | B27: Share of results of JVs | T27: =T8 -> 71.396 | U27: =U8-T8 -> 344.964
A28: 经营及应占合营企业盈利 | B28: Operating profit & share of profits of JVs | H28: =H9 -> 855.331 | I28: =I9-H9 -> 1217.352 | J28: =J9-I9 -> 760.384 | K28: =K9-J9 -> 1825.539 | L28: =L9 -> 1070.076 | M28: =M9-L9 -> 1439.526 | N28: =N9-M9 -> 1034.364 | O28: =O9-N9 -> 2034.486 | P28: =P9 -> 1286.763 | Q28: =Q9-P9 -> 875.775 | R28: =R9-Q9 -> 1573.712 | S28: =S9-R9 -> 2120.636 | T28: =T9 -> 1449.015 | U28: =U9-T9 -> 1868.097 | V28: =V9-U9 -> 1707.644 | W28: =W9-V9 -> 2522.016 | X28: =X9 -> 1684.902 | Y28: =Y9-X9 -> 2567.716 | Z28: =Z9-Y9 -> 1560.374 | AA28: =AA9-Z9 -> 2956.981 | AB28: =AB9 -> 2164.569 | AC28: =AC9-AB9 -> 2202.299 | AD28: =AD9-AC9 -> 1881.269 | AE28: =AE9-AD9 -> 2707.3 | AF28: =AF9 -> 1716.843 | AG28: =AG9-AF9 -> 3195.691 | AH28: =AH9-AG9 -> 2169.242 | AI28: =AI9-AH9 -> 1933.35 | AJ28: =AJ9 -> 2406.654 | AK28: =AK9-AJ9 -> 3343.258 | AL28: =AL9-AK9 -> 2621.658 | AM28: =AM9-AL9 -> 2870.847 | AN28: =AN9 -> 2904.704 | AO28: =AO9-AN9 -> 3791.237 | AP28: =AP9-AO9 -> 3132.73 | AQ28: =AQ9-AP9 -> 3017.047 | AR28: =AR9 -> 3398.564 | AS28: =AS9-AR9 -> 4715.066 | AT28: =AT9-AS9 -> 3446.389 | AU28: =AU9-AT9 -> 3606.286 | AV28: =AV9 -> 3575.514 | AW28: =AW9-AV9 -> 4880.723 | AX28: =AX9-AW9 -> 3445.369 | AY28: =AY9-AX9 -> 3244.283 | AZ28: =AZ9 -> 3963.014 | BA28: =BA9-AZ9 -> 4646.794 | BB28: =BB9-BA9 -> 3313.53 | BC28: =BC9-BB9 -> 3095.211
A29: 增速 | B29: YoY
A30: 集团营业额 | B30: Group revenue | L30: =L22/H22-1 -> 0.17322699 | M30: =M22/I22-1 -> 0.20573891 | N30: =N22/J22-1 -> 0.053199484 | O30: =O22/K22-1 -> 0.032665033 | P30: =P22/L22-1 -> 0.18482138 | Q30: =Q22/M22-1 -> 0.048063431 | R30: =R22/N22-1 -> 0.30787013 | S30: =S22/O22-1 -> 0.30115788 | ... BC30: =BC22/AY22-1 -> -0.044281009
A31: 应占合营企业营业额 | B31: Share of revenue of JVs | R31: =R23/N23-1 -> 0.39484772 | S31: =S23/O23-1 -> 2.7803732 | V31: =V23/R23-1 -> 3.6304404 | W31: =W23/S23-1 -> -0.79279542 | X31: =X23/T23-1 -> 0.28086383 | Y31: =Y23/U23-1 -> -0.60132538 | Z31: =Z23/V23-1 -> -0.73019101 | AA31: =AA23/W23-1 -> 11.954849 | AB31: =AB23/X23-1 -> 0.28782642 | AC31: =AC23/Y23-1 -> -0.43149798 | ... BC31: =BC23/AY23-1 -> 0.03198141
A32: 合计 | B32: Group revenue & share of revenue of JVs | R32: =R24/N24-1 -> 0.31085889 | S32: =S24/O24-1 -> 0.35457981 | V32: =V24/R24-1 -> 0.076097259 | W32: =W24/S24-1 -> -0.018618804 | X32: =X24/T24-1 -> 0.099919387 | Y32: =Y24/U24-1 -> 0.12563713 | Z32: =Z24/V24-1 -> -0.085678044 | AA32: =AA24/W24-1 -> 0.20951765 | AB32: =AB24/X24-1 -> 0.0036777795 | AC32: =AC24/Y24-1 -> 0.0076802456 | ... BC32: =BC24/AY24-1 -> -0.041434845
A34: 经营盈利 | B34: Group results | T34: =T26/P26-1 -> 0.15114022 | U34: =U26/Q26-1 -> 1.0984649
A35: 应占合营企业盈利 | B35: Share of results of JVs
A36: 经营及应占合营企业盈利 | B36: Operating profit & share of profits of JVs | L36: =L28/H28-1 -> 0.25106655 | M36: =M28/I28-1 -> 0.18250596 | N36: =N28/J28-1 -> 0.36031794 | O36: =O28/K28-1 -> 0.1144577 | P36: =P28/L28-1 -> 0.20249683 | Q36: =Q28/M28-1 -> -0.39162266 | R36: =R28/N28-1 -> 0.52142959 | S36: =S28/O28-1 -> 0.042344848 | ... BC36: =BC28/AY28-1 -> -0.045949136
A37: 经营及应占合营企业盈利/收入 | B37: Operating profit & share of profits of JVs Margin | N37: =N28/N24 -> 0.11467042 | O37: =O28/O24 -> 0.16218383 | R37: =R28/R24 -> 0.13309058 | S37: =S28/S24 -> 0.12479994 | T37: =T28/T24 -> 0.13295026 | U37: =U28/U24 -> 0.1285819 | V37: =V28/V24 -> 0.13420475 | W37: =W28/W24 -> 0.1512371 | X37: =X28/X24 -> 0.14054975 | Y37: =Y28/Y24 -> 0.15701061 | ... BC37: =BC28/BC24 -> 0.13060981
AD38: =AD37-Z37 -> 0.007148837 | AN38: =TEXT(100*(AN37-AM37),"0.0ppt") -> 5.1ppt | AO38: =TEXT(100*(AO37-AN37),"0.0ppt") -> -6.1ppt | AP38: =TEXT(100*(AP37-AO37),"0.0ppt") -> 5.5ppt | AQ38: =TEXT(100*(AQ37-AP37),"0.0ppt") -> -5.5ppt | AR38: =TEXT(100*(AR37-AQ37),"0.0ppt") -> 5.3ppt | AS38: =TEXT(100*(AS37-AR37),"0.0ppt") -> -1.6ppt | AT38: =TEXT(100*(AT37-AS37),"0.0ppt") -> 0.1ppt | AU38: =TEXT(100*(AU37-AT37),"0.0ppt") -> -3.6ppt | ... BC38: =TEXT(100*(BC37-BB37),"0.0ppt") -> -2.1ppt
AB45: 1H15 | AC45: 2H15 | AD45: 1H16 | AE45: 2H16 | AF45: 1H17 | AG45: 2H17 | AH45: 1H18 | AI45: 2H18 | AJ45: 1H19 | AK45: 2H19 | AL45: 1H20 | AM45: 2H20 | AN45: 1H21 | AO45: 2H21
A46: 经营及应占合营企业盈利 | AB46: =M9 -> 2509.602 | AC46: =O9-M9 -> 3068.85 | AD46: =Q9 -> 2162.538 | AE46: =S9-Q9 -> 3694.348 | AF46: =U9 -> 3317.112 | AG46: =W9-U9 -> 4229.66 | AH46: =Y9 -> 4252.618 | AI46: =AA9-Y9 -> 4517.355 | AJ46: =AC9 -> 4366.868 | AK46: =AE9-AC9 -> 4588.569 | AL46: =AG9 -> 4912.534 | AM46: =AI9-AG9 -> 4102.592 | AN46: =AK9 -> 5749.912 | AO46: =AM9-AK9 -> 5492.505
A47: YoY | AD47: =AD46/AB46-1 -> -0.13829444 | AE47: =AE46/AC46-1 -> 0.20382163 | AF47: =AF46/AD46-1 -> 0.53389767 | AG47: =AG46/AE46-1 -> 0.14490026 | AH47: =AH46/AF46-1 -> 0.28202424 | AI47: =AI46/AG46-1 -> 0.06801847 | AJ47: =AJ46/AH46-1 -> 0.026865804 | AK47: =AK46/AI46-1 -> 0.015764535 | ... AO47: =AO46/AM46-1 -> 0.33878899
A48: 利润总额 | AB48: =HoH!AM21 -> 2226.515 | AC48: =HoH!AN21 -> 2905.73 | AD48: =HoH!AO21 -> 2676.523 | AE48: =HoH!AP21 -> 3335.197 | AF48: =HoH!AQ21 -> 3175.935 | AG48: =HoH!AR21 -> 3614.031 | AH48: =HoH!AS21 -> 3296.469 | AI48: =HoH!AT21 -> 2909.036 | ... AO48: =HoH!AZ21 -> 4582.379
A49: YoY | AD49: =AD48/AB48-1 -> 0.20211317 | AE49: =AE48/AC48-1 -> 0.14780004 | AF49: =AF48/AD48-1 -> 0.18658984 | AG49: =AG48/AE48-1 -> 0.083603457 | AH49: =AH48/AF48-1 -> 0.037952288 | AI49: =AI48/AG48-1 -> -0.19507165 | AJ49: =AJ48/AH48-1 -> 0.12899348 | AK49: =AK48/AI48-1 -> 0.2247284 | ... AO49: =AO48/AM48-1 -> 0.066734781
A50: 净利润 | AB50: =HoH!AM25 -> 1871.359 | AC50: =HoH!AN25 -> 2652.767 | AD50: =HoH!AO25 -> 2253.309 | AE50: =HoH!AP25 -> 2876.757 | AF50: =HoH!AQ25 -> 2493.401 | AG50: =HoH!AR25 -> 2996.69 | AH50: =HoH!AS25 -> 2522.32 | AI50: =HoH!AT25 -> 1977.828 | ... AO50: =HoH!AZ25 -> 3300.678
A51: YoY | AD51: =AD50/AB50-1 -> 0.20410301 | AE51: =AE50/AC50-1 -> 0.084436364 | AF51: =AF50/AD50-1 -> 0.10655085 | AG51: =AG50/AE50-1 -> 0.041690348 | AH51: =AH50/AF50-1 -> 0.011598215 | AI51: =AI50/AG50-1 -> -0.3399958 | AJ51: =AJ50/AH50-1 -> 0.13452893 | AK51: =AK50/AI50-1 -> 0.29008336 | ... AO51: =AO50/AM50-1 -> 0.058633015

Sheet HoH
A1: 营业收入同比增速 | B1: Revenue YoY growth | E1: =E7/D7-1 -> -0.11933905 | F1: =F7/E7-1 -> 0.23456847 | G1: =G7/F7-1 -> 0.36689371 | H1: =H7/G7-1 -> 0.3377034 | I1: =I7/H7-1 -> 0.24531256 | J1: =J7/I7-1 -> 0.26218774 | K1: =K7/J7-1 -> 0.10343626 | L1: =L7/K7-1 -> 0.21592702 | ... U1: =U7/T7-1 -> -0.04627846 | AA1: =AA7/Y7-1 -> 0.011548337 | AB1: =AB7/Z7-1 -> -0.24687049 | AC1: =AC7/AA7-1 -> -0.091642765 | AD1: =AD7/AB7-1 -> 0.66147753 | AE1: =AE7/AC7-1 -> 0.2147522 | AF1: =AF7/AD7-1 -> 0.47574821 | AG1: =AG7/AE7-1 -> 0.47549321 | AH1: =AH7/AF7-1 -> 0.2565529 | ... BH1: =BH7/BF7-1 -> -0.10152445
A2: 毛利润同比增速 | B2: Gross profit YoY growth | E2: =E9/D9-1 -> -0.17577769 | F2: =F9/E9-1 -> 0.75554405 | G2: =G9/F9-1 -> 0.36655282 | H2: =H9/G9-1 -> 0.51164564 | I2: =I9/H9-1 -> 0.37808902 | J2: =J9/I9-1 -> 0.26619371 | K2: =K9/J9-1 -> 0.078013035 | L2: =L9/K9-1 -> 0.17010433 | ... U2: =U9/T9-1 -> -0.021303192 | AA2: =AA9/Y9-1 -> 0.08112901 | AB2: =AB9/Z9-1 -> -0.40589568 | AC2: =AC9/AA9-1 -> 0.13830708 | AD2: =AD9/AB9-1 -> 1.7616458 | AE2: =AE9/AC9-1 -> 0.10756322 | AF2: =AF9/AD9-1 -> 0.54055864 | AG2: =AG9/AE9-1 -> 0.7156802 | AH2: =AH9/AF9-1 -> 0.41309137 | ... BH2: =BH9/BF9-1 -> -0.016444731
A3: 利润总额同比增速 | B3: Profit before income tax growth | E3: =E21/D21-1 -> 0.30184189 | F3: =F21/E21-1 -> 0.66502096 | G3: =G21/F21-1 -> 0.3830871 | H3: =H21/G21-1 -> 0.46616415 | I3: =I21/H21-1 -> 0.17370624 | J3: =J21/I21-1 -> 0.27533164 | K3: =K21/J21-1 -> 0.26797426 | L3: =L21/K21-1 -> 0.17136263 | ... U3: =U21/T21-1 -> 0.010831186 | AA3: =AA21/Y21-1 -> 0.077160275 | AB3: =AB21/Z21-1 -> 0.5315618 | AC3: =AC21/AA21-1 -> 0.73472458 | AD3: =AD21/AB21-1 -> 0.61489851 | AE3: =AE21/AC21-1 -> 0.22866101 | AF3: =AF21/AD21-1 -> 0.50237128 | AG3: =AG21/AE21-1 -> 0.5028858 | AH3: =AH21/AF21-1 -> 0.44296675 | ... BH3: =BH21/BF21-1 -> -0.044825857
A4: 净利润同比增速 | B4: Core earnings YoY growth | E4: =E26/D26-1 -> 0.2517979 | F4: =F26/E26-1 -> 0.69179682 | G4: =G26/F26-1 -> 0.4546338 | H4: =H26/G26-1 -> 0.41399226 | I4: =I26/H26-1 -> 0.2899854 | J4: =J26/I26-1 -> 0.25744531 | K4: =K26/J26-1 -> 0.20118817 | L4: =L26/K26-1 -> 0.00013147123 | ... U4: =U26/T26-1 -> 0.0025816866 | AA4: =AA26/Y26-1 -> 0.083125647 | AB4: =AB26/Z26-1 -> 0.46083643 | AC4: =AC26/AA26-1 -> 0.52903732 | AD4: =AD26/AB26-1 -> 0.54415926 | AE4: =AE26/AC26-1 -> 0.40772689 | AF4: =AF26/AD26-1 -> 0.49264119 | AG4: =AG26/AE26-1 -> 0.35837648 | AH4: =AH26/AF26-1 -> 1.4042252 | ... BH4: =BH26/BF26-1 -> -0.064824648
A5: 净利润占全年比重 | B5: Half year core earnings as % of full year | AA5: =AA26/SUM(AA26:AB26) -> 0.4500316 | AB5: =AB26/SUM(AA26:AB26) -> 0.5499684 | AC5: =AC26/SUM(AC26:AD26) -> 0.44759707 | AD5: =AD26/SUM(AC26:AD26) -> 0.55240293 | AE5: =AE26/SUM(AE26:AF26) -> 0.43316362 | AF5: =AF26/SUM(AE26:AF26) -> 0.56683638 | AG5: =AG26/SUM(AG26:AH26) -> 0.3015574 | AH5: =AH26/SUM(AG26:AH26) -> 0.6984426 | AI5: =AI26/SUM(AI26:AJ26) -> 0.42654092 | AJ5: =AJ26/SUM(AI26:AJ26) -> 0.57345908 | AK5: =AK26/SUM(AK26:AL26) -> 0.42199132 | AL5: =AL26/SUM(AK26:AL26) -> 0.57800868 | AM5: =AM26/SUM(AM26:AN26) -> 0.4293282 | AN5: =AN26/SUM(AM26:AN26) -> 0.5706718 | AO5: =AO26/SUM(AO26:AP26) -> 0.31322634 | AP5: =AP26/SUM(AO26:AP26) -> 0.68677366 | AQ5: =AQ26/SUM(AP26:AQ26) -> 0.42313922 | AR5: =AR26/SUM(AQ26:AR26) -> 0.58750274 | AS5: =AS26/SUM(AR26:AS26) -> 0.45840027 | AT5: =AT26/SUM(AS26:AT26) -> 0.52623378 | AU5: =AU26/SUM(AT26:AU26) -> 0.50529629 | AV5: =AV26/SUM(AU26:AV26) -> 0.47135876 | AW5: =AW26/SUM(AV26:AW26) -> 0.5317428 | ... BH5: =BH26/SUM(BG26:BH26) -> 0.38761499
A6: （百万） | B6: (RMB mn) | D6: 2008A | E6: 2009A | F6: 2010A | G6: 2011A | H6: 2012A | I6: 2013A | J6: 2014A | K6: 2015A | L6: 2016A | M6: 2017A | N6: 2018A | O6: 2019A | P6: 2020A | Q6: 2021A | R6: 2022A | S6: 2023A | T6: 2024A | U6: 2025A | V6: YoY | X6: CICC Comments | Y6: 1H08 | Z6: 2H08 | AA6: 1H09 | AB6: 2H09 | AC6: 1H10 | AD6: 2H10 | AE6: 1H11 | AF6: 2H11 | AG6: 1H12 | AH6: 2H12 | AI6: 1H13 | AJ6: 2H13 | AK6: 1H14 | AL6: 2H14 | AM6: 1H15 | AN6: 2H15 | AO6: 1H16 | AP6: 2H16 | AQ6: 1H17 | AR6: 2H17 | AS6: 1H18 | AT6: 2H18 | AU6: 1H19 | AV6: 2H19 | AW6: 1H20 | AX6: 2H20 | AY6: 1H21 | AZ6: 2H21 | BA6: 1H22 | BB6: 2H22 | BC6: 1H23 | BD6: 2H23 | BE6: 1H24 | BF6: 2H24 | BG6: 1H25 | BH6: 2H25 | BI6: YoY | BJ6: HoH | BL6: 1H19 | BM6: 1H20 | BN6: 1H21 | BO6: 1H22 | BP6: 1H23 | BQ6: 1H24 | BR6: 1H25 | BS6: YoY
A7: 主营业务收入 | B7: Revenue | D7: =PL!F4 -> 11021.405 | E7: 9706.121 | F7: 11982.871 | G7: 16379.311 | H7: =PL!J4 -> 21910.66 | I7: =PL!K4 -> 27285.62 | J7: =PL!L4 -> 34439.575 | K7: =PL!M4 -> 38001.876 | L7: =PL!N4 -> 46207.508 | M7: =PL!O4 -> 50152.524 | N7: ='PL（org）'!Q3 -> 55626.304 | O7: =PL!Q4 -> 61669.678 | P7: =PL!R4 -> 62458.009 | Q7: =PL!S4 -> 77309.614 | R7: =PL!T4 -> 101975.26 | S7: =PL!U4 -> 113734.01 | T7: =PL!V4 -> 105322.67 | U7: =PL!W4 -> 100448.5 | V7: =U7/T7-1 -> -0.04627846 | X7: PRC market pushed a high growth of revenue | Y7: 5439.138 | Z7: =D7-Y7 -> 5582.267 | AA7: 5501.951 | AB7: =E7-AA7 -> 4204.17 | AC7: 4997.737 | AD7: =F7-AC7 -> 6985.134 | AE7: 6071.012 | AF7: =G7-AE7 -> 10308.299 | AG7: 8957.737 | AH7: =H7-AG7 -> 12952.923 | AI7: 11508.961 | AJ7: =(I7-AI7) -> 15776.659 | AK7: 14283.426 | AL7: =J7-AK7 -> 20156.149 | AM7: 17017.498 | AN7: =K7-AM7 -> 20984.378 | AO7: 18845.053 | AP7: =L7-AO7 -> 27362.455 | AQ7: =22966135/1000 -> 22966.135 | AR7: =M7-AQ7 -> 27186.389 | AS7: 27105.613 | AT7: =N7-AS7 -> 28520.691 | AU7: 27542.5 | AV7: =O7-AU7 -> 34127.178 | AW7: 28002.101 | AX7: =P7-AW7 -> 34455.908 | AY7: 36370.988 | AZ7: =Q7-AY7 -> 40938.626 | BA7: 53810.559 | BB7: =R7-BA7 -> 48164.706 | BC7: 55110.712 | BD7: =S7-BC7 -> 58623.301 | BE7: 56567.777 | BF7: =T7-BE7 -> 48754.894 | BG7: 56643.42 | BH7: =U7-BG7 -> 43805.08 | BI7: =BH7/BF7-1 -> -0.10152445 | BJ7: =BH7/BG7-1 -> -0.22665192 | BL7: =AU7/AU$7 -> 1 | BM7: =AW7/AW$7 -> 1 | BN7: =AY7/AY$7 -> 1 | BO7: =BA7/$BA$7 -> 1 | BP7: =BC7/$BC$7 -> 1 | BQ7: =BE7/$BE$7 -> 1 | BR7: =BF7/$BF$7 -> 1 | BS7: =BR7-BQ7 -> 0
A8: 销售成本 | B8: Cost of sales | D8: =PL!F19 -> 10112.012 | E8: 8956.579 | F8: 10667.017 | G8: 14581.127 | H8: =PL!J19 -> 19192.443 | I8: =PL!K19 -> 23539.675 | J8: =PL!L19 -> 29696.483 | K8: =PL!M19 -> 32888.761 | L8: =PL!N19 -> 40224.63 | M8: =PL!O19 -> 42537.494 | N8: =PL!P19 -> 46929.883 | O8: =PL!Q19 -> 52433.975 | ... U8: =PL!W19 -> 84466.8 | V8: =U8/T8-1 -> -0.050861236 | Y8: =(4823688+185764)/1000 -> 5009.452 | Z8: =D8-Y8 -> 5102.56 | AA8: =(4870294+167111)/1000 -> 5037.405 | AB8: =E8-AA8 -> 3919.174 | AC8: 4468.941 | AD8: =F8-AC8 -> 6198.076 | AE8: 5485.337 | AF8: =G8-AE8 -> 9095.79 | AG8: 7952.906 | AH8: =H8-AG8 -> 11239.537 | AI8: 9887.777 | AJ8: =(I8-AI8) -> 13651.898 | AK8: 12271.891 | AL8: =J8-AK8 -> 17424.592 | AM8: 14471.644 | AN8: =K8-AM8 -> 18417.117 | AO8: 16537.621 | AP8: =L8-AO8 -> 23687.009 | AQ8: 19712.731 | AR8: =M8-AQ8 -> 22824.763 | AS8: 23000.814 | AT8: =N8-AS8 -> 23929.069 | AU8: 23190.337 | AV8: =O8-AU8 -> 29243.638 | AW8: 22934.093 | AX8: =P8-AW8 -> 30239.757 | AY8: 30358.018 | AZ8: =Q8-AY8 -> 34968.853 | BA8: 46593.286 | BB8: =R8-BA8 -> 41363.446 | BC8: 46484.974 | BD8: =S8-BC8 -> 50910.129 | BE8: 47816.073 | BF8: =T8-BE8 -> 41177.026 | BG8: 48114.972 | BH8: =U8-BG8 -> 36351.828 | BI8: =BH8/BF8-1 -> -0.1171818 | BJ8: =BH8/BG8-1 -> -0.24447991 | BL8: =AU8/AU$7 -> 0.84198373 | BM8: =AW8/AW$7 -> 0.81901329 | BN8: =AY8/AY$7 -> 0.83467675 | BO8: =BA8/$BA$7 -> 0.86587627 | BP8: =BC8/$BC$7 -> 0.84348346 | BQ8: =BE8/$BE$7 -> 0.84528818 | BR8: =BF8/$BF$7 -> 0.84457216 | BS8: =BR8-BQ8 -> -0.00071601807
A9: 毛利 | B9: Gross profit | D9: =D7-D8 -> 909.393 | E9: 749.542 | F9: 1315.854 | G9: 1798.184 | H9: =PL!J40 -> 2718.217 | I9: =PL!K40 -> 3745.945 | J9: =PL!L40 -> 4743.092 | K9: =PL!M40 -> 5113.115 | L9: =L7-L8 -> 5982.878 | M9: =M7-M8 -> 7615.03 | N9: =N7-N8 -> 8696.421 | O9: =O7-O8 -> 9235.703 | P9: =P7-P8 -> 9284.159 | Q9: =Q7-Q8 -> 11982.743 | R9: =R7-R8 -> 14018.533 | S9: =S7-S8 -> 16338.91 | ... U9: =U7-U8 -> 15981.7 | V9: =U9/T9-1 -> -0.021303192 | X9: Gross margin improved | Y9: =Y7-Y8 -> 429.686 | Z9: =Z7-Z8 -> 479.707 | AA9: =AA7-AA8 -> 464.546 | AB9: =AB7-AB8 -> 284.996 | AC9: 528.796 | AD9: =F9-AC9 -> 787.058 | AE9: 585.675 | AF9: =G9-AE9 -> 1212.509 | AG9: =AG7-AG8 -> 1004.831 | AH9: =H9-AG9 -> 1713.386 | AI9: =AI7-AI8 -> 1621.184 | AJ9: =(I9-AI9) -> 2124.761 | AK9: =AK7-AK8 -> 2011.535 | AL9: =AL7-AL8 -> 2731.557 | AM9: =AM7-AM8 -> 2545.854 | AN9: =K9-AM9 -> 2567.261 | AO9: =AO7-AO8 -> 2307.432 | AP9: =L9-AO9 -> 3675.446 | AQ9: 3253.404 | AR9: =M9-AQ9 -> 4361.626 | AS9: 4104.799 | AT9: =N9-AS9 -> 4591.622 | AU9: 4352.163 | AV9: =O9-AU9 -> 4883.54 | AW9: 5068.008 | AX9: =P9-AW9 -> 4216.151 | AY9: 6012.97 | AZ9: =Q9-AY9 -> 5969.773 | BA9: 7217.273 | BB9: =R9-BA9 -> 6801.26 | BC9: 8625.738 | BD9: =S9-BC9 -> 7713.172 | BE9: 8751.704 | BF9: =T9-BE9 -> 7577.868 | BG9: 8528.448 | BH9: =U9-BG9 -> 7453.252 | BI9: =BH9/BF9-1 -> -0.016444731 | BJ9: =BH9/BG9-1 -> -0.12607171 | BL9: =AU9/AU$7 -> 0.15801627 | BM9: =AW9/AW$7 -> 0.18098671 | BN9: =AY9/AY$7 -> 0.16532325 | BO9: =BA9/$BA$7 -> 0.13412373 | BP9: =BC9/$BC$7 -> 0.15651654 | BQ9: =BE9/$BE$7 -> 0.15471182 | BR9: =BF9/$BF$7 -> 0.15542784 | BS9: =BR9-BQ9 -> 0.00071601807
A10: 投资收入、其他收入及其他收益 | B10: Investment income, other income and other gains | D10: =D11+D12 -> 119.658 | E10: =E11+E12 -> 108.949 | F10: =F11+F12 -> 162.503 | G10: =G11+G12 -> 399.361 | H10: =H11+H12 -> 503.311 | I10: =I11+I12 -> 436.542 | J10: =J11+J12 -> 475.339 | K10: ='PL（org）'!N7 -> 1159.441 | L10: =PL!N61 -> 1260.12 | M10: =PL!O61 -> 747.678 | N10: =PL!P61 -> -360.25 | O10: ='PL（org）'!R7 -> 636.756 | P10: ='PL（org）'!S7 -> 979.166 | Q10: ='PL（org）'!T7 -> 1197.192 | R10: ='PL（org）'!U7 -> 1577.205 | S10: ='PL（org）'!V7 -> 647.339 | T10: ='PL（org）'!W7 -> 211.693 | U10: ='PL（org）'!X7 -> 248.706 | V10: =U10/T10-1 -> 0.17484281 | AG10: =AG11+AG12 -> 253.101 | AH10: =AH11+AH12 -> 250.21 | AI10: =AI11+AI12 -> 202.043 | AJ10: =AJ11+AJ12 -> 234.499 | AK10: =AK11+AK12 -> 266.885 | AL10: =AL11+AL12 -> 208.454 | AM10: 255.394 | AN10: =K10-AM10 -> 904.047 | AO10: 1089.615 | AP10: =L10-AO10 -> 170.505 | AQ10: 527.436 | AR10: =M10-AQ10 -> 220.242 | AS10: 280.528 | AT10: =N10-AS10 -> -640.778 | AU10: 315.908 | AV10: =O10-AU10 -> 320.848 | AW10: 371.986 | AX10: =P10-AW10 -> 607.18 | AY10: 255.531 | AZ10: =Q10-AY10 -> 941.661 | BA10: 617.02 | BB10: =R10-BA10 -> 960.185 | BC10: 29.97 | BD10: =S10-BC10 -> 617.369 | BE10: 115.941 | BF10: =T10-BE10 -> 95.752 | BG10: 164.935 | BH10: =U10-BG10 -> 83.771 | BI10: =BH10/BF10-1 -> -0.12512532 | BJ10: =BH10/BG10-1 -> -0.49209689 | BL10: =AU10/AU$7 -> 0.011469838 | BM10: =AW10/AW$7 -> 0.013284217 | BN10: =AY10/AY$7 -> 0.0070256821 | BO10: =BA10/$BA$7 -> 0.011466523 | BP10: =BC10/$BC$7 -> 0.00054381442 | BQ10: =BE10/$BE$7 -> 0.0020495944 | BR10: =BF10/$BF$7 -> 0.0019639464 | BS10: =BR10-BQ10 -> -8.5647989e-05
A11: 投资收益 | B11: Investment income | D11: =PL!F61 -> 77.987 | E11: 42.79 | F11: 85.58 | G11: 316.296 | H11: =PL!J61 -> 371.09 | I11: =PL!K61 -> 436.542 | J11: =PL!L61 -> 475.339 | V11: =U11/T11-1 -> #DIV/0! | X11: Dividend income from unlisted AFS investment in Macau, and interest of BT projects | Y11: 15.121 | Z11: =D11-Y11 -> 62.866 | AA11: 17.658 | AB11: =E11-AA11 -> 25.132 | AC11: 24.395 | AD11: =F11-AC11 -> 61.185 | AE11: 173.407 | AF11: =G11-AE11 -> 142.889 | AG11: 214.91 | AH11: =H11-AG11 -> 156.18 | AI11: 124.517 | AJ11: =(I11-AI11) -> 312.025 | AK11: 0 | AL11: =J11-AK11 -> 475.339 | AM11: 0 | AP11: =L11-AO11 -> 0 | AR11: =M11-AQ11 -> 0 | AT11: =N11-AS11 -> 0 | AV11: =O11-AU11 -> 0 | AX11: =P11-AW11 -> 0 | AY11: 0 | AZ11: =Q11-AY11 -> 0 | BB11: =R11-BA11 -> 0 | BC11: 0 | BD11: =S11-BC11 -> 0 | BE11: 0 | BF11: =T11-BE11 -> 0 | BG11: 0 | BH11: =V11-BG11 -> #DIV/0! | BI11: =BH11/BF11-1 -> #DIV/0! | BJ11: =BH11/BG11-1 -> #DIV/0! | BL11: =AU11/AU$7 -> 0 | BM11: =AW11/AW$7 -> 0 | BN11: =AY11/AY$7 -> 0 | BO11: =BA11/$BA$7 -> 0 | BP11: =BC11/$BC$7 -> 0 | BQ11: =BE11/$BE$7 -> 0 | BR11: =BF11/$BE$7 -> 0 | BS11: =BR11-BQ11 -> 0
A12: 其他收入及费用净额 | B12: Other income and other gains | D12: =+'PL（org）'!G9+'PL（org）'!G13 -> 41.671 | E12: =(88478-22319)/1000 -> 66.159 | F12: =(83623+19686-26386)/1000 -> 76.923 | G12: =(85705+20314-22954)/1000 -> 83.065 | H12: =PL!J76 -> 132.221 | I12: =PL!K76 -> 0 | J12: =PL!L76 -> 0 | V12: =U12/T12-1 -> #DIV/0! | Y12: =18.781-1.491 -> 17.29 | Z12: =D12-Y12 -> 24.381 | AA12: =26.053-5.282 -> 20.771 | AB12: =E12-AA12 -> 45.388 | AC12: =(16025-15444)/1000 -> 0.581 | AD12: =F12-AC12 -> 76.342 | AE12: =(38272+15524-672)/1000 -> 53.124 | AF12: =G12-AE12 -> 29.941 | AG12: =54.469+26-42.278 -> 38.191 | AH12: =H12-AG12 -> 94.03 | AI12: 77.526 | AJ12: =(I12-AI12) -> -77.526 | AK12: 266.885 | AL12: =J12-AK12 -> -266.885 | AM12: 167.386 | AP12: =L12-AO12 -> 0 | AR12: =M12-AQ12 -> 0 | AT12: =N12-AS12 -> 0 | AV12: =O12-AU12 -> 0 | AX12: =P12-AW12 -> 0 | AY12: 0 | AZ12: =Q12-AY12 -> 0 | BB12: =R12-BA12 -> 0 | BC12: 0 | BD12: =S12-BC12 -> 0 | BE12: 0 | BF12: =T12-BE12 -> 0 | BG12: 0 | BH12: =V12-BG12 -> #DIV/0! | BI12: =BH12/BF12-1 -> #DIV/0! | BJ12: =BH12/BG12-1 -> #DIV/0! | BL12: =AU12/AU$7 -> 0 | BM12: =AW12/AW$7 -> 0 | BN12: =AY12/AY$7 -> 0 | BO12: =BA12/$BA$7 -> 0 | BP12: =BC12/$BC$7 -> 0 | BQ12: =BE12/$BE$7 -> 0 | BR12: =BF12/$BE$7 -> 0 | BS12: =BR12-BQ12 -> 0
A13: 销售和管理费用 | B13: Distribution,selling and adminstrative expenses | D13: =D14+D15 -> 411.828 | E13: =E14+E15 -> 365.566 | F13: =F14+F15 -> 471.502 | G13: =G14+G15 -> 554.203 | H13: =H14+H15 -> 709.644 | I13: =I14+I15 -> 1042.458 | J13: =J14+J15 -> 1033.14 | K13: =-'PL（org）'!N10 -> 1007.396 | L13: =PL!N79 -> 1106.084 | M13: =PL!O79 -> 1394.668 | N13: =PL!P79 -> 1396.594 | O13: =-'PL（org）'!R10 -> 1681.8 | P13: =-'PL（org）'!S10 -> 1920.393 | Q13: =-'PL（org）'!T10 -> 2278.609 | R13: =-'PL（org）'!U10 -> 2434.764 | S13: =-'PL（org）'!V10 -> 2622.901 | T13: =-'PL（org）'!W10 -> 2582.026 | U13: =-'PL（org）'!X10 -> 2651.743 | V13: =U13/T13-1 -> 0.02700089 | AG13: =AG14+AG15 -> 307.758 | AH13: =AH14+AH15 -> 401.886 | AI13: =AI14+AI15 -> 473.833 | AJ13: =AJ14+AJ15 -> 568.625 | AK13: =AK14+AK15 -> 432.818 | AL13: =AL14+AL15 -> 600.322 | AM13: 450.814 | AN13: =K13-AM13 -> 556.582 | AO13: 645.732 | AP13: =L13-AO13 -> 460.352 | AQ13: 664.408 | AR13: =M13-AQ13 -> 730.26 | AS13: 623.367 | AT13: =N13-AS13 -> 773.227 | AU13: 770.652 | AV13: =O13-AU13 -> 911.148 | AW13: 789.088 | AX13: =P13-AW13 -> 1131.305 | AY13: 862.893 | AZ13: =Q13-AY13 -> 1415.716 | BA13: 1108.648 | BB13: =R13-BA13 -> 1326.116 | BC13: 1257.774 | BD13: =S13-BC13 -> 1365.127 | BE13: 1208.704 | BF13: =T13-BE13 -> 1373.322 | BG13: 1087.788 | BH13: =U13-BG13 -> 1563.955 | BI13: =BH13/BF13-1 -> 0.13881158 | BJ13: =BH13/BG13-1 -> 0.43773879 | BL13: =AU13/AU$7 -> 0.027980467 | BM13: =AW13/AW$7 -> 0.0281796 | BN13: =AY13/AY$7 -> 0.023724761 | BO13: =BA13/$BA$7 -> 0.020602797 | BP13: =BC13/$BC$7 -> 0.022822677 | BQ13: =BE13/$BE$7 -> 0.021367359 | BR13: =BF13/$BF$7 -> 0.02816788 | BS13: =BR13-BQ13 -> 0.0068005209
A14: 销售及营销费用 | B14: Distribution and selling expenses | D14: =-'PL（org）'!G12 -> 17.796 | E14: 9.843 | F14: 4.736 | G14: 15.523 | H14: =PL!J81 -> 5.505 | I14: =PL!K81 -> 82.946 | J14: =PL!L81 -> 133.871 | V14: =U14/T14-1 -> #DIV/0! | Y14: 1.219 | Z14: =D14-Y14 -> 16.577 | AA14: 6.751 | AB14: =E14-AA14 -> 3.092 | AC14: 0.892 | AD14: =F14-AC14 -> 3.844 | AE14: 5.671 | AF14: =G14-AE14 -> 9.852 | AG14: 3.503 | AH14: =H14-AG14 -> 2.002 | AI14: 53.234 | AJ14: =(I14-AI14) -> 29.712 | AK14: 41.856 | AL14: =J14-AK14 -> 92.015 | AM14: 25.653 | AP14: =L14-AO14 -> 0 | AR14: =M14-AQ14 -> 0 | AT14: =N14-AS14 -> 0 | AV14: =O14-AU14 -> 0 | AX14: =P14-AW14 -> 0 | AY14: 0 | AZ14: =Q14-AY14 -> 0 | BB14: =R14-BA14 -> 0 | BC14: 0 | BD14: =S14-BC14 -> 0 | BE14: 0 | BF14: =T14-BE14 -> 0 | BG14: 0 | BH14: =V14-BG14 -> #DIV/0! | BI14: =BH14/BF14-1 -> #DIV/0! | BJ14: =BH14/BG14-1 -> #DIV/0! | BL14: =AU14/AU$7 -> 0 | BM14: =AW14/AW$7 -> 0 | BN14: =AY14/AY$7 -> 0 | BO14: =BA14/$BA$7 -> 0 | BP14: =BC14/$BC$7 -> 0 | BQ14: =BE14/$BE$7 -> 0 | BR14: =BF14/$BE$7 -> 0 | BS14: =BR14-BQ14 -> 0
A15: 管理费用 | B15: Administrative Expenses | D15: =-'PL（org）'!G11 -> 394.032 | E15: 355.723 | F15: 466.766 | G15: 538.68 | H15: =PL!J83 -> 704.139 | I15: =PL!K83 -> 959.512 | J15: =PL!L83 -> 899.269 | V15: =U15/T15-1 -> #DIV/0! | Y15: 166.419 | Z15: =D15-Y15 -> 227.613 | AA15: 159.136 | AB15: =E15-AA15 -> 196.587 | AC15: 180.941 | AD15: =F15-AC15 -> 285.825 | AE15: 222.81 | AF15: =G15-AE15 -> 315.87 | AG15: 304.255 | AH15: =H15-AG15 -> 399.884 | AI15: 420.599 | AJ15: =(I15-AI15) -> 538.913 | AK15: 390.962 | AL15: =J15-AK15 -> 508.307 | AM15: 418.558 | AP15: =L15-AO15 -> 0 | AR15: =M15-AQ15 -> 0 | AT15: =N15-AS15 -> 0 | AV15: =O15-AU15 -> 0 | AX15: =P15-AW15 -> 0 | AY15: 0 | AZ15: =Q15-AY15 -> 0 | BB15: =R15-BA15 -> 0 | BC15: 0 | BD15: =S15-BC15 -> 0 | BE15: 0 | BF15: =T15-BE15 -> 0 | BG15: 0 | BH15: =V15-BG15 -> #DIV/0! | BI15: =BH15/BF15-1 -> #DIV/0! | BJ15: =BH15/BG15-1 -> #DIV/0! | BL15: =AU15/AU$7 -> 0 | BM15: =AW15/AW$7 -> 0 | BN15: =AY15/AY$7 -> 0 | BO15: =BA15/$BA$7 -> 0 | BP15: =BC15/$BC$7 -> 0 | BQ15: =BE15/$BE$7 -> 0 | BR15: =BF15/$BE$7 -> 0 | BS15: =BR15-BQ15 -> 0
A16: 资产减值 | B16: Impairment | D16: =+SUM('PL（org）'!G14:G16) -> 8.58 | E16: 0 | F16: 0 | G16: 0 | H16: =PL!J88 -> 0 | I16: =PL!K88 -> 0 | J16: =PL!L88 -> 0 | K16: =PL!M88 -> 0 | L16: =PL!N88 -> 0 | M16: =PL!O88 -> 0 | N16: =PL!P88 -> 0 | O16: =PL!Q88 -> 0 | ... U16: =PL!W88 -> 0 | V16: =U16/T16-1 -> #DIV/0! | Y16: 18.298 | Z16: =D16-Y16 -> -9.718 | AA16: 0 | AB16: =E16-AA16 -> 0 | AC16: 0 | AD16: =F16-AC16 -> 0 | AE16: 0 | AF16: =G16-AE16 -> 0 | AG16: =G16-AF16 -> 0 | AH16: =H16-AG16 -> 0 | AI16: 0 | AJ16: =(I16-AI16) -> 0 | AK16: 0 | AL16: =J16-AK16 -> 0 | AM16: 0 | AN16: =K16-AM16 -> 0 | AP16: =L16-AO16 -> 0 | AR16: =M16-AQ16 -> 0 | AT16: =N16-AS16 -> 0 | AV16: =O16-AU16 -> 0 | AX16: =P16-AW16 -> 0 | AY16: 0 | AZ16: =Q16-AY16 -> 0 | BB16: =R16-BA16 -> 0 | BC16: 0 | BD16: =S16-BC16 -> 0 | BE16: 0 | BF16: =T16-BE16 -> 0 | BG16: 0 | BH16: =V16-BG16 -> #DIV/0! | BI16: =BH16/BF16-1 -> #DIV/0! | BJ16: =BH16/BG16-1 -> #DIV/0! | BL16: =AU16/AU$7 -> 0 | BM16: =AW16/AW$7 -> 0 | BN16: =AY16/AY$7 -> 0 | BO16: =BA16/$BA$7 -> 0 | BP16: =BC16/$BC$7 -> 0 | BQ16: =BE16/$BE$7 -> 0 | BR16: =BF16/$BE$7 -> 0 | BS16: =BR16-BQ16 -> 0
A17: 财务费用 | B17: Finance costs | D17: =-'PL（org）'!G19 -> 20.065 | E17: 12.956 | F17: 15.552 | G17: 192.69 | H17: =PL!J90 -> 239.375 | I17: =PL!K90 -> 418.44 | J17: =PL!L90 -> 455.829 | K17: =PL!M90 -> 629.105 | L17: =PL!N90 -> 688.159 | M17: =PL!O90 -> 1069.754 | N17: =PL!P90 -> 1781.717 | O17: =PL!Q90 -> 2278.985 | ... U17: =PL!W90 -> 2469.668 | V17: =U17/T17-1 -> -0.1623451 | X17: Due to more bank loans | Y17: 6.654 | Z17: =D17-Y17 -> 13.411 | AA17: 5.639 | AB17: =E17-AA17 -> 7.317 | AC17: 4.021 | AD17: =F17-AC17 -> 11.531 | AE17: 98.073 | AF17: =G17-AE17 -> 94.617 | AG17: 110.058 | AH17: =H17-AG17 -> 129.317 | AI17: 184.578 | AJ17: =(I17-AI17) -> 233.862 | AK17: 267.455 | AL17: =J17-AK17 -> 188.374 | AM17: 304.591 | AN17: =K17-AM17 -> 324.514 | AO17: 323.952 | AP17: =L17-AO17 -> 364.207 | AQ17: 442.166 | AR17: =M17-AQ17 -> 627.588 | AS17: 838.598 | AT17: =N17-AS17 -> 943.119 | AU17: 1104.213 | AV17: =O17-AU17 -> 1174.772 | AW17: 1344.173 | AX17: =P17-AW17 -> 1335.804 | AY17: 1256.554 | AZ17: =Q17-AY17 -> 1411.648 | BA17: 1474.582 | BB17: =R17-BA17 -> 1516.837 | BC17: 1554.068 | BD17: =S17-BC17 -> 1650.241 | BE17: 1472.406 | BF17: =T17-BE17 -> 1475.906 | BG17: 1299.867 | BH17: =U17-BG17 -> 1169.801 | BI17: =BH17/BF17-1 -> -0.20740142 | BJ17: =BH17/BG17-1 -> -0.10006101 | BL17: =AU17/AU$7 -> 0.040091241 | BM17: =AW17/AW$7 -> 0.048002577 | BN17: =AY17/AY$7 -> 0.03454825 | BO17: =BA17/$BA$7 -> 0.027403209 | BP17: =BC17/$BC$7 -> 0.028199019 | BQ17: =BE17/$BE$7 -> 0.026029059 | BR17: =BF17/$BF$7 -> 0.030271956 | BS17: =BR17-BQ17 -> 0.004242897
A18: 应占联营企业利润 | B18: Share of profits of JV and associates | D18: =+'PL（org）'!G18 -> 9.445 | E18: =(11592+309310)/1000 -> 320.902 | F18: =(20419+321745)/1000 -> 342.164 | G18: =(13702+379947)/1000 -> 393.649 | H18: =PL!J100 -> 431.539 | I18: =PL!K100 -> 452.169 | J18: =PL!L100 -> 318.132 | K18: =PL!M100 -> 496.19 | L18: =PL!N100 -> 562.965 | M18: =PL!O100 -> 891.68 | N18: =PL!P100 -> 1047.645 | O18: =PL!Q100 -> 1372.797 | ... U18: =PL!W100 -> 858.477 | V18: =U18/T18-1 -> 0.036417437 | Y18: 4.899 | Z18: =D18-Y18 -> 4.546 | AA18: 3.55 | AB18: =E18-AA18 -> 317.352 | AC18: =(9546+203667)/1000 -> 213.213 | AD18: =F18-AC18 -> 128.951 | AE18: =(8241+220120)/1000 -> 228.361 | AF18: =G18-AE18 -> 165.288 | AG18: =6.965+225.999 -> 232.964 | AH18: =H18-AG18 -> 198.575 | AI18: =(226290+7607)/1000 -> 233.897 | AJ18: =(I18-AI18) -> 218.272 | AK18: =(171639+13757)/1000 -> 185.396 | AL18: =J18-AK18 -> 132.736 | AM18: =167.906+12.766 -> 180.672 | AN18: =K18-AM18 -> 315.518 | AO18: =239.963+9.197 -> 249.16 | AP18: =L18-AO18 -> 313.805 | AQ18: =416.36+85.309 -> 501.669 | AR18: =M18-AQ18 -> 390.011 | AS18: =384.923-11.816 -> 373.107 | AT18: =N18-AS18 -> 674.538 | AU18: =SUM(AU19:AU20) -> 928.486 | AV18: =O18-AU18 -> 444.311 | AW18: =SUM(AW19:AW20) -> 642.037 | AX18: =P18-AW18 -> 1939.484 | AY18: =SUM(AY19:AY20) -> 653.745 | AZ18: =Q18-AY18 -> 498.309 | BA18: =SUM(BA19:BA20) -> 314.334 | BB18: =R18-BA18 -> 294.796 | BC18: =SUM(BC19:BC20) -> 518.545 | BD18: =S18-BC18 -> 425.963 | BE18: =SUM(BE19:BE20) -> 610.681 | BF18: =T18-BE18 -> 217.631 | BG18: =SUM(BG19:BG20) -> 845.734 | BH18: =U18-BG18 -> 12.743 | BI18: =BH18/BF18-1 -> -0.94144676 | BJ18: =BH18/BG18-1 -> -0.98493261 | BL18: =AU18/AU$7 -> 0.033711028 | BM18: =AW18/AW$7 -> 0.022928172 | BN18: =AY18/AY$7 -> 0.017974354 | BO18: =BA18/$BA$7 -> 0.0058414929 | BP18: =BC18/$BC$7 -> 0.0094091508 | BQ18: =BE18/$BE$7 -> 0.010795563 | BR18: =BF18/$BF$7 -> 0.0044637775 | BS18: =BR18-BQ18 -> -0.0063317855
A19: 合营企业 | B19: JV | L19: n.a. | M19: ='PL（org）'!P17 -> 731.38 | N19: ='PL（org）'!Q17 -> 705.024 | O19: ='PL（org）'!R17 -> 452.654 | P19: ='PL（org）'!S17 -> 701.944 | Q19: ='PL（org）'!T17 -> 369.246 | R19: ='PL（org）'!U17 -> 275.196 | S19: ='PL（org）'!V17 -> 629.969 | T19: ='PL（org）'!W17 -> 583.499 | U19: ='PL（org）'!X17 -> 846.409 | V19: =U19/T19-1 -> 0.45057489 | AS19: 384.923 | AT19: =N19-AS19 -> 320.101 | AU19: 320.195 | AV19: =O19-AU19 -> 132.459 | AW19: 112.162 | AX19: =P19-AW19 -> 589.782 | AY19: 219.817 | AZ19: =Q19-AY19 -> 149.429 | BA19: 89.601 | BB19: =R19-BA19 -> 185.595 | BC19: 345.238 | BD19: =S19-BC19 -> 284.731 | BE19: 605.709 | BF19: =T19-BE19 -> -22.21 | BG19: 798.78 | BH19: =U19-BG19 -> 47.629 | BI19: =BH19/BF19-1 -> -3.1444845 | BJ19: =BH19/BG19-1 -> -0.94037282 | BL19: =AU19/AU$7 -> 0.011625488 | BM19: =AW19/AW$7 -> 0.0040054852 | BN19: =AY19/AY$7 -> 0.0060437456 | BO19: =BA19/$BA$7 -> 0.0016651193 | BP19: =BC19/$BC$7 -> 0.0062644446 | BQ19: =BE19/$BE$7 -> 0.010707668 | BR19: =BF19/$BF$7 -> -0.00045554401 | BS19: =BR19-BQ19 -> -0.011163212
A20: 联营公司 | B20: Associates | L20: n.a. | M20: ='PL（org）'!P18 -> 160.3 | N20: ='PL（org）'!Q18 -> 342.621 | O20: ='PL（org）'!R18 -> 920.143 | P20: ='PL（org）'!S18 -> 1879.577 | Q20: ='PL（org）'!T18 -> 782.808 | R20: ='PL（org）'!U18 -> 333.934 | S20: ='PL（org）'!V18 -> 314.539 | T20: ='PL（org）'!W18 -> 244.813 | U20: ='PL（org）'!X18 -> 12.068 | V20: =U20/T20-1 -> -0.95070523 | AS20: -11.816 | AT20: =N20-AS20 -> 354.437 | AU20: 608.291 | AV20: =O20-AU20 -> 311.852 | AW20: 529.875 | AX20: =P20-AW20 -> 1349.702 | AY20: 433.928 | AZ20: =Q20-AY20 -> 348.88 | BA20: 224.733 | BB20: =R20-BA20 -> 109.201 | BC20: 173.307 | BD20: =S20-BC20 -> 141.232 | BE20: 4.972 | BF20: =T20-BE20 -> 239.841 | BG20: 46.954 | BH20: =U20-BG20 -> -34.886 | BI20: =BH20/BF20-1 -> -1.1454547 | BJ20: =BH20/BG20-1 -> -1.7429825 | BL20: =AU20/AU$7 -> 0.022085541 | BM20: =AW20/AW$7 -> 0.018922687 | BN20: =AY20/AY$7 -> 0.011930608 | BO20: =BA20/$BA$7 -> 0.0041763736 | BP20: =BC20/$BC$7 -> 0.0031447062 | BQ20: =BE20/$BE$7 -> 8.7894562e-05 | BR20: =BF20/$BF$7 -> 0.0049193215 | BS20: =BR20-BQ20 -> 0.004831427
A21: 利润总额 | B21: Profit before income tax | D21: =+D9+D10-D14-D15+D16-D17+D18 -> 615.183 | E21: =+E9+E10-E14-E15+E16-E17+E18 -> 800.871 | F21: =+F9+F10-F14-F15+F16-F17+F18 -> 1333.467 | G21: =+G9+G10-G14-G15+G16-G17+G18 -> 1844.301 | H21: =+H9+H10-H14-H15+H16-H17+H18 -> 2704.048 | I21: =+I9+I10-I14-I15+I16-I17+I18 -> 3173.758 | J21: =PL!L103 -> 4047.594 | K21: =PL!M103 -> 5132.245 | L21: =PL!N103 -> 6011.72 | M21: =M9+M10-M13-M17+M18 -> 6789.966 | N21: =N9+N10-N13-N17+N18 -> 6205.505 | O21: =O9+O10-O13-O17+O18 -> 7284.471 | P21: =P9+P10-P13-P17+P18 -> 8244.476 | Q21: =Q9+Q10-Q13-Q17+Q18 -> 9385.178 | R21: =R9+R10-R13-R17+R18 -> 10778.685 | S21: =S9+S10-S13-S17+S18 -> 12103.547 | T21: =T9+T10-T13-T17+T18 -> 11839.239 | U21: =U9+U10-U13-U17+U18 -> 11967.472 | V21: =U21/T21-1 -> 0.010831186 | Y21: =+Y9+Y11+Y12-Y14-Y15+Y16-Y17+Y18 -> 311.002 | Z21: =+Z9+Z11+Z12-Z14-Z15+Z16-Z17+Z18 -> 304.181 | AA21: =+AA9+AA11+AA12-AA14-AA15+AA16-AA17+AA18 -> 334.999 | AB21: =+AB9+AB11+AB12-AB14-AB15+AB16-AB17+AB18 -> 465.872 | AC21: 581.131 | AD21: =F21-AC21 -> 752.336 | AE21: 714.013 | AF21: =G21-AE21 -> 1130.288 | AG21: 1073.08 | AH21: =H21-AG21 -> 1630.968 | AI21: 1398.713 | AJ21: =(I21-AI21) -> 1775.045 | AK21: 1763.543 | AL21: =J21-AK21 -> 2284.051 | AM21: =AM9+AM10-AM13-AM17+AM18 -> 2226.515 | AN21: =K21-AM21 -> 2905.73 | AO21: =AO9+AO10-AO13-AO17+AO18 -> 2676.523 | AP21: =L21-AO21 -> 3335.197 | AQ21: 3175.935 | AR21: =M21-AQ21 -> 3614.031 | AS21: =AS9+AS10-AS13-AS17+AS18 -> 3296.469 | AT21: =AT9+AT10-AT13-AT17+AT18 -> 2909.036 | AU21: =AU9+AU10-AU13-AU17+AU18 -> 3721.692 | AV21: =AV9+AV10-AV13-AV17+AV18 -> 3562.779 | AW21: =AW9+AW10-AW13-AW17+AW18 -> 3948.77 | AX21: =AX9+AX10-AX13-AX17+AX18 -> 4295.706 | AY21: =AY9+AY10-AY13-AY17+AY18 -> 4802.799 | AZ21: =AZ9+AZ10-AZ13-AZ17+AZ18 -> 4582.379 | BA21: =BA9+BA10-BA13-BA17+BA18 -> 5565.397 | BB21: =R21-BA21 -> 5213.288 | BC21: =BC9+BC10-BC13-BC17+BC18 -> 6362.411 | BD21: =S21-BC21 -> 5741.136 | BE21: =BE9+BE10-BE13-BE17+BE18 -> 6797.216 | BF21: =T21-BE21 -> 5042.023 | BG21: =BG9+BG10-BG13-BG17+BG18 -> 7151.462 | BH21: =U21-BG21 -> 4816.01 | BI21: =BH21/BF21-1 -> -0.044825857 | BJ21: =BH21/BG21-1 -> -0.32656987 | BL21: =AU21/AU$7 -> 0.13512542 | BM21: =AW21/AW$7 -> 0.14101692 | BN21: =AY21/AY$7 -> 0.13205028 | BO21: =BA21/$BA$7 -> 0.10342574 | BP21: =BC21/$BC$7 -> 0.11544781 | BQ21: =BE21/$BE$7 -> 0.12016056 | BR21: =BF21/$BF$7 -> 0.10341573 | BS21: =BR21-BQ21 -> -0.016744833
A22: 减：所得税 | B22: Income tax expense | D22: =-'PL（org）'!G23 -> 66.276 | E22: 72.39 | F22: 213.218 | G22: 334.122 | H22: =PL!J105 -> -404.896 | I22: =PL!K105 -> 503.071 | J22: =PL!L105 -> 659.716 | K22: =PL!M105 -> 659.562 | L22: =PL!N105 -> 1004.504 | M22: =PL!O105 -> 1255.662 | N22: =PL!P105 -> 1648.872 | O22: =PL!Q105 -> 1560.891 | ... U22: =PL!W105 -> 2962.098 | V22: =U22/T22-1 -> 0.13102201 | Y22: 23.814 | Z22: =D22-Y22 -> 42.462 | AA22: 31.648 | AB22: =E22-AA22 -> 40.742 | AC22: 73.228 | AD22: =F22-AC22 -> 139.99 | AE22: 62.74 | AF22: =G22-AE22 -> 271.382 | AG22: 183.634 | AH22: =H22-AG22 -> -588.53 | AI22: 238.822 | AJ22: =(I22-AI22) -> 264.249 | AK22: 315.756 | AL22: =J22-AK22 -> 343.96 | AM22: 353.818 | AN22: =K22-AM22 -> 305.744 | AO22: 433.028 | AP22: =L22-AO22 -> 571.476 | AQ22: 641.4 | AR22: =M22-AQ22 -> 614.262 | AS22: 753.205 | AT22: =N22-AS22 -> 895.667 | AU22: 706.924 | AV22: =O22-AU22 -> 853.967 | AW22: 801.344 | AX22: =P22-AW22 -> 958.958 | AY22: 1004.769 | AZ22: =Q22-AY22 -> 944.525 | BA22: 1047.28 | BB22: =R22-BA22 -> 1261.941 | BC22: 1227.557 | BD22: =S22-BC22 -> 1163.042 | BE22: 1430.343 | BF22: =T22-BE22 -> 1188.614 | BG22: 1642.57 | BH22: =U22-BG22 -> 1319.528 | BI22: =BH22/BF22-1 -> 0.11014005 | BJ22: =BH22/BG22-1 -> -0.19666864 | BL22: =AU22/AU$7 -> 0.025666661 | BM22: =AW22/AW$7 -> 0.028617281 | BN22: =AY22/AY$7 -> 0.027625562 | BO22: =BA22/$BA$7 -> 0.019462351 | BP22: =BC22/$BC$7 -> 0.022274381 | BQ22: =BE22/$BE$7 -> 0.025285473 | BR22: =BF22/$BF$7 -> 0.024379378 | BS22: =BR22-BQ22 -> -0.00090609483
A23: 减：归属永续资本证券持有人损益 | B23: Interests of perpertual capital security holders | L23: 0 | M23: 0 | N23: =PL!P107 -> 17 | O23: =PL!Q107 -> 260.166 | P23: =PL!R107 -> 407.246 | Q23: =PL!S107 -> 465.132 | R23: =PL!T107 -> 295.824 | S23: =PL!U107 -> 304.788 | T23: =PL!V107 -> 339.297 | U23: =PL!W107 -> 228.808 | V23: =U23/T23-1 -> -0.32564096 | AS23: 0 | AT23: =N23-AS23 -> 17 | AU23: 124.095 | AV23: =O23-AU23 -> 136.071 | AW23: 202.4 | AX23: =P23-AW23 -> 204.846 | AY23: 210.752 | AZ23: =Q23-AY23 -> 254.38 | BA23: 146.954 | BB23: =R23-BA23 -> 148.87 | BC23: 147.094 | BD23: =S23-BC23 -> 157.694 | BE23: 169.88 | BF23: =T23-BE23 -> 169.417 | BG23: 114.321 | BH23: =U23-BG23 -> 114.487 | BI23: =BH23/BF23-1 -> -0.32422956 | BJ23: =BH23/BG23-1 -> 0.0014520517 | BL23: =AU23/AU$7 -> 0.0045055823 | BM23: =AW23/AW$7 -> 0.0072280291 | BN23: =AY23/AY$7 -> 0.0057945085 | BO23: =BA23/$BA$7 -> 0.002730951 | BP23: =BC23/$BC$7 -> 0.0026690637 | BQ23: =BE23/$BE$7 -> 0.0030031231 | BR23: =BF23/$BF$7 -> 0.0034748717 | BS23: =BR23-BQ23 -> 0.00047174853
A24: 减：少数股东损益 | B24: Minority interests | D24: ='PL（org）'!G28 -> 15.068 | E24: 54.415 | F24: 83.971 | G24: 2.774 | H24: =PL!J109 -> 5.042 | I24: =PL!K109 -> -78.864 | J24: =PL!L109 -> -69.532 | K24: =PL!M109 -> -51.443 | L24: =PL!N109 -> -122.85 | M24: =PL!O109 -> 44.213 | N24: =PL!P109 -> 39.485 | O24: =PL!Q109 -> 50.206 | ... U24: =PL!W109 -> 188.122 | V24: =U24/T24-1 -> -0.40402466 | Y24: 7.118 | Z24: =D24-Y24 -> 7.95 | AA24: 0 | AB24: =E24-AA24 -> 54.415 | AC24: 44.068 | AD24: =F24-AC24 -> 39.903 | AE24: -1.68 | AF24: =G24-AE24 -> 4.454 | AG24: 2.49 | AH24: =H24-AG24 -> 2.552 | AI24: -12.905 | AJ24: =(I24-AI24) -> -65.959 | AK24: -11.21 | AL24: =J24-AK24 -> -58.322 | AM24: 1.338 | AN24: =K24-AM24 -> -52.781 | AO24: -9.814 | AP24: =L24-AO24 -> -113.036 | AQ24: 41.134 | AR24: =M24-AQ24 -> 3.079 | AS24: 20.944 | AT24: =N24-AS24 -> 18.541 | AU24: 29.028 | AV24: =O24-AU24 -> 21.178 | AW24: 47.526 | AX24: =P24-AW24 -> 14.034 | AY24: 87.077 | AZ24: =Q24-AY24 -> 82.796 | BA24: 157.169 | BB24: =R24-BA24 -> 59.595 | BC24: 139.138 | BD24: =S24-BC24 -> 104.977 | BE24: 191.018 | BF24: =T24-BE24 -> 124.636 | BG24: 135.749 | BH24: =U24-BG24 -> 52.373 | BI24: =BH24/BF24-1 -> -0.57979236 | BJ24: =BH24/BG24-1 -> -0.61419237 | BL24: =AU24/AU$7 -> 0.0010539348 | BM24: =AW24/AW$7 -> 0.0016972298 | BN24: =AY24/AY$7 -> 0.0023941335 | BO24: =BA24/$BA$7 -> 0.0029207836 | BP24: =BC24/$BC$7 -> 0.0025246997 | BQ24: =BE24/$BE$7 -> 0.0033767988 | BR24: =BF24/$BF$7 -> 0.0025563793 | BS24: =BR24-BQ24 -> -0.00082041951
A25: 净利润 | B25: Company net profit | D25: =PL!F112 -> 489.321 | E25: =PL!G112 -> 612.531 | F25: =PL!H112 -> 1036.278 | G25: =PL!I112 -> 1507.405 | H25: =PL!J112 -> 2941.251 | I25: =PL!K112 -> 2749.551 | J25: =PL!L112 -> 3457.41 | K25: =PL!M112 -> 4524.126 | L25: =PL!N112 -> 5130.066 | M25: =M21-M22-M24 -> 5490.091 | N25: =N21-N22-N24-N23 -> 4500.148 | O25: =O21-O22-O24-O23 -> 5413.208 | P25: =P21-P22-P24-P23 -> 6015.368 | Q25: =Q21-Q22-Q24-Q23 -> 6800.879 | R25: =R21-R22-R24-R23 -> 7956.876 | S25: =S21-S22-S24-S23 -> 9164.045 | T25: =T21-T22-T24-T23 -> 8565.331 | U25: =U21-U22-U24-U23 -> 8588.444 | V25: =U25/T25-1 -> 0.0026984363 | X25: In line with our expectation | Y25: =Y21-Y22-Y24 -> 280.07 | Z25: =Z21-Z22-Z24 -> 253.769 | AA25: =AA21-AA22-AA24 -> 303.351 | AB25: =AB21-AB22-AB24 -> 370.715 | AC25: 463.835 | AD25: =F25-AC25 -> 572.443 | AE25: 652.953 | AF25: =G25-AE25 -> 854.452 | AG25: =AG21-AG22-AG24 -> 886.956 | AH25: =H25-AG25 -> 2054.295 | AI25: =AI21-AI22-AI24 -> 1172.796 | AJ25: =(I25-AI25) -> 1576.755 | AK25: =AK21-AK22-AK24 -> 1458.997 | AL25: =AL21-AL22-AL24 -> 1998.413 | AM25: =AM21-AM22-AM24 -> 1871.359 | AN25: =K25-AM25 -> 2652.767 | AO25: =AO21-AO22-AO24 -> 2253.309 | AP25: =L25-AO25 -> 2876.757 | AQ25: =AQ21-AQ22-AQ24 -> 2493.401 | AR25: =M25-AQ25 -> 2996.69 | AS25: =AS21-SUM(AS22:AS24) -> 2522.32 | AT25: =AT21-SUM(AT22:AT24) -> 1977.828 | AU25: =AU21-SUM(AU22:AU24) -> 2861.645 | AV25: =AV21-SUM(AV22:AV24) -> 2551.563 | AW25: =AW21-SUM(AW22:AW24) -> 2897.5 | AX25: =AX21-SUM(AX22:AX24) -> 3117.868 | AY25: =AY21-SUM(AY22:AY24) -> 3500.201 | AZ25: =AZ21-SUM(AZ22:AZ24) -> 3300.678 | BA25: =BA21-SUM(BA22:BA24) -> 4213.994 | BB25: =R25-BA25 -> 3742.882 | BC25: =BC21-SUM(BC22:BC24) -> 4848.622 | BD25: =S25-BC25 -> 4315.423 | BE25: =BE21-SUM(BE22:BE24) -> 5005.975 | BF25: =T25-BE25 -> 3559.356 | BG25: =BG21-SUM(BG22:BG24) -> 5258.822 | BH25: =U25-BG25 -> 3329.622 | BI25: =BH25/BF25-1 -> -0.064543698 | BJ25: =BH25/BG25-1 -> -0.36685022 | BL25: =AU25/AU$7 -> 0.10389925 | BM25: =AW25/AW$7 -> 0.10347438 | BN25: =AY25/AY$7 -> 0.096236071 | BO25: =BA25/$BA$7 -> 0.078311656 | BP25: =BC25/$BC$7 -> 0.087979665 | BQ25: =BE25/$BE$7 -> 0.088495169 | BR25: =BF25/$BF$7 -> 0.073005102 | BS25: =BR25-BQ25 -> -0.015490067
A26: 扣非盈利 | B26: Core earnings | D26: =PL!F118 -> 489.321 | E26: =PL!G118 -> 612.531 | F26: =PL!H118 -> 1036.278 | G26: =PL!I118 -> 1507.405 | H26: =PL!J118 -> 2131.459 | I26: =PL!K118 -> 2749.551 | J26: =PL!L118 -> 3457.41 | K26: =PL!M118 -> 4153 | ... U26: =PL!W118 -> 8587.444 | V26: =U26/T26-1 -> 0.0025816866 | Y26: =Y25 -> 280.07 | Z26: =Z25 -> 253.769 | AA26: =AA25 -> 303.351 | AB26: =AB25 -> 370.715 | AC26: =AC25 -> 463.835 | AD26: =AD25 -> 572.443 | AE26: =AE25 -> 652.953 | AF26: =AF25 -> 854.452 | ... AL26: =AL25 -> 1998.413 | AM26: 1783 | AN26: =K26-AM26 -> 2370 | AO26: 1301 | AP26: =L26-AO26 -> 2852.546 | AQ26: 2092.401 | AR26: =M26-AQ26 -> 2980.12 | AS26: 2522.32 | AT26: =N26-AS26 -> 2801.656 | AU26: =AU25 -> 2861.645 | AV26: =O26-AU26 -> 2551.563 | AW26: =AW25 -> 2897.5 | AX26: =P26-AW26 -> 2696.1783 | AY26: =AY25 -> 3500.201 | AZ26: =Q26-AY26 -> 3300.678 | BA26: =BA25 -> 4213.994 | BB26: =R26-BA26 -> 3742.882 | BC26: =BC25 -> 4848.622 | BD26: =S26-BC26 -> 4315.423 | BE26: =BE25 -> 5005.975 | BF26: =T26-BE26 -> 3559.356 | BG26: =BG25 -> 5258.822 | BH26: =U26-BG26 -> 3328.622 | BI26: =BH26/BF26-1 -> -0.064824648 | BJ26: =BH26/BG26-1 -> -0.36704038 | BL26: =AU26/AU$7 -> 0.10389925 | BM26: =AW26/AW$7 -> 0.10347438 | BN26: =AY26/AY$7 -> 0.096236071 | BO26: =BA26/$BA$7 -> 0.078311656 | BP26: =BC26/$BC$7 -> 0.087979665 | BQ26: =BE26/$BE$7 -> 0.088495169 | BR26: =BF26/$BF$7 -> 0.073005102 | BS26: =BR26-BQ26 -> -0.015490067
A27: 总股本（百万股） | B27: Total shares (mn) | D27: =BS!F88 -> 2444.7678 | E27: =BS!G88 -> 2954.5726 | F27: =BS!H88 -> 2979.4588 | G27: =BS!I88 -> 3586.7435 | H27: =BS!J88 -> 3887.4474 | I27: =BS!K88 -> 3888.294 | J27: =BS!L88 -> 3895.85 | K27: =BS!M88 -> 4056.3146 | ... U27: =BS!W88 -> 5282.2167 | V27: =U27/T27-1 -> 0.048554706 | Y27: =BS!$H$89 -> 5282.2167 | Z27: =BS!$H$89 -> 5282.2167 | AA27: =BS!$H$89 -> 5282.2167 | AB27: =BS!$H$89 -> 5282.2167 | AC27: =BS!$H$89 -> 5282.2167 | AD27: =AC27 -> 5282.2167 | AE27: =AD27 -> 5282.2167 | AF27: =AE27 -> 5282.2167 | AG27: =G27 -> 3586.7435 | AH27: =AG27 -> 3586.7435 | AI27: =$B$39 -> 5282.2167 | AJ27: =BS!K88 -> 3888.294 | AK27: 3890.299 | AL27: =BS!L88 -> 3895.85 | AM27: =4012.418 -> 4012.418 | AN27: =BS!M88 -> 4056.3146 | AO27: 4072.923 | AP27: =BS!N88 -> 4488.1393 | AQ27: 4488.139 | AR27: =BS!O88 -> 5049.1567 | AS27: 5049.1567 | BB27: =R27-BA27 -> 5037.6167 | BD27: =S27-BC27 -> 5037.6167 | BF27: =T27-BE27 -> 5037.6167 | BH27: =V27-BG27 -> 0.048554706 | BI27: =BH27/BF27-1 -> -0.99999036 | BJ27: =BH27/BG27-1 -> #DIV/0! | BQ27: =BE27/$BE$7 -> 0 | BR27: =BF27/$BE$7 -> 0.089054528 | BS27: =BQ27-BP27 -> 0
A28: 摊薄每股核心收益 | B28: Diluted core EPS | D28: =D26/$B$39 -> 0.092635541 | E28: =E26/$B$39 -> 0.11596098 | F28: =F26/$B$39 -> 0.19618241 | G28: =G26/$B$39 -> 0.28537356 | H28: =H26/$B$39 -> 0.40351601 | I28: =I26/$B$39 -> 0.52052976 | J28: =J26/$B$39 -> 0.65453771 | K28: =K26/$B$39 -> 0.78622295 | ... U28: =U26/$B$39 -> 1.6257273 | V28: =U28/T28-1 -> 0.0025816866 | Y28: =Y26/$B$39 -> 0.053021301 | Z28: =Z26/$B$39 -> 0.048042141 | AA28: =AA26/$B$39 -> 0.057428731 | AB28: =AB26/$B$39 -> 0.07018171 | AC28: =AC26/$B$39 -> 0.087810672 | AD28: =AD26/$B$39 -> 0.10837174 | AE28: =AE26/$B$39 -> 0.12361344 | AF28: =AF26/$B$39 -> 0.16176012 | ... AP28: =AP26/$B$39 -> 0.5400282 | AQ28: 0.5542 | AR28: =M28-AQ28 -> 0.40610157 | AS28: =AS26/$B$39 -> 0.47751165 | AT28: =N28-AS28 -> 0.53039399 | AU28: =AU26/$B$39 -> 0.54175078 | AV28: =AV26/$B$39 -> 0.48304777 | AW28: =AW26/$B$39 -> 0.54853865 | AX28: =AX26/$B$39 -> 0.51042554 | AY28: =AY26/$B$39 -> 0.66263866 | AZ28: =AZ26/$B$39 -> 0.62486607 | BA28: =BA26/$B$39 -> 0.79777 | BB28: =R28-BA28 -> 0.70858168 | BC28: =BC26/$B$39 -> 0.91791425 | BD28: =S28-BC28 -> 0.81697197 | BE28: =BE26/$B$39 -> 0.94770345 | BF28: =T28-BE28 -> 0.67383756 | BG28: =BG26/$B$39 -> 0.99557105 | BH28: =U28-BG28 -> 0.63015628 | BI28: =BH28/BF28-1 -> -0.064824648 | BJ28: =BH28/BG28-1 -> -0.36704038
A30: 毛利率 | B30: Gross margin | D30: =D9/D7 -> 0.082511531 | E30: =E9/E7 -> 0.077223641 | F30: =F9/F7 -> 0.10981125 | G30: =G9/G7 -> 0.10978386 | H30: =H9/H7 -> 0.12405911 | I30: =I9/I7 -> 0.13728642 | J30: =J9/J7 -> 0.13772214 | K30: =K9/K7 -> 0.13454902 | ... U30: =U9/U7 -> 0.15910342 | V30: =(ROUND(U30-T30,3)*100)&"ppt" -> 0.4ppt | X30: The gross margin from BT projects in PRC improved | Y30: =Y9/Y7 -> 0.078998915 | Z30: =Z9/Z7 -> 0.085934084 | AA30: =AA9/AA7 -> 0.084432958 | AB30: =AB9/AB7 -> 0.067788886 | AC30: =AC9/AC7 -> 0.10580709 | AD30: =AD9/AD7 -> 0.11267615 | AE30: =AE9/AE7 -> 0.096470737 | AF30: =AF9/AF7 -> 0.11762455 | ... BH30: =BH9/BH7 -> 0.17014584 | BI30: =(ROUND(BH30-BF30,3)*100)&"ppt" -> 1.5ppt | BJ30: =(ROUND(BH30-BG30,3)*100)&"ppt" -> 2ppt
A31: 销售和管理费用 | B31: Distribution, selling and adminstrative expenses | D31: =D13/D7 -> 0.037366198 | E31: =E13/E7 -> 0.03766345 | F31: =F13/F7 -> 0.039347999 | G31: =G13/G7 -> 0.03383555 | H31: =H13/H7 -> 0.03238807 | I31: =I13/I7 -> 0.038205399 | J31: =J13/J7 -> 0.029998628 | K31: =K13/K7 -> 0.026509112 | ... U31: =U13/U7 -> 0.02639903 | V31: =(ROUND(U31-T31,3)*100)&"ppt" -> 0.2ppt | AG31: =AG13/AG7 -> 0.034356668 | AH31: =AH13/AH7 -> 0.031026665 | AI31: =AI13/AI7 -> 0.041170789 | AJ31: =AJ13/AJ7 -> 0.036042168 | AK31: =AK13/AK7 -> 0.030302114 | AL31: =AL13/AL7 -> 0.029783566 | AM31: =AM13/AM7 -> 0.026491203 | AN31: =AN13/AN7 -> 0.026523636 | ... BH31: =BH13/BH7 -> 0.035702594 | BI31: =(ROUND(BH31-BF31,3)*100)&"ppt" -> 0.8ppt | BJ31: =(ROUND(BH31-BG31,3)*100)&"ppt" -> 1.6ppt
A32: 管理费用率 | B32: Administrative expense rate | D32: =D15/D7 -> 0.035751522 | E32: =E15/E7 -> 0.036649347 | F32: =F15/F7 -> 0.038952768 | G32: =G15/G7 -> 0.03288783 | H32: =H15/H7 -> 0.032136823 | I32: =I15/I7 -> 0.035165483 | J32: =J15/J7 -> 0.026111501 | V32: =(ROUND(U32-T32,3)*100)&"ppt" -> 0ppt | X32: Management efficiency improved | Y32: =Y15/Y7 -> 0.030596576 | Z32: =Z15/Z7 -> 0.040774295 | AA32: =AA15/AA7 -> 0.028923558 | AB32: =AB15/AB7 -> 0.046760003 | AC32: =AC15/AC7 -> 0.036204586 | AD32: =AD15/AD7 -> 0.040919043 | AE32: =AE15/AE7 -> 0.036700636 | AF32: =AF15/AF7 -> 0.030642301 | ... BH32: =BH15/BH7 -> #DIV/0! | BI32: =(ROUND(BH32-BF32,3)*100)&"ppt" -> #DIV/0! | BJ32: =(ROUND(BH32-BG32,3)*100)&"ppt" -> #DIV/0!
A33: 财务费用 | B33: Financial cost rate | D33: =D17/D7 -> 0.0018205483 | E33: =E17/E7 -> 0.0013348278 | F33: =F17/F7 -> 0.0012978526 | G33: =G17/G7 -> 0.011764231 | H33: =H17/H7 -> 0.010925047 | I33: =I17/I7 -> 0.01533555 | J33: =J17/J7 -> 0.013235616 | K33: =K17/K7 -> 0.016554577 | ... U33: =U17/U7 -> 0.02458641 | V33: =(ROUND(U33-T33,3)*100)&"ppt" -> -0.3ppt | AA33: =AA17/AA7 -> 0.0010249092 | AB33: =AB17/AB7 -> 0.0017404149 | AC33: =AC17/AC7 -> 0.00080456415 | AD33: =AD17/AD7 -> 0.0016507915 | AE33: =AE17/AE7 -> 0.016154308 | AF33: =AF17/AF7 -> 0.009178721 | AG33: =AG17/AG7 -> 0.012286362 | AH33: =AH17/AH7 -> 0.0099836153 | ... BH33: =BH17/BH7 -> 0.026704688 | BI33: =(ROUND(BH33-BF33,3)*100)&"ppt" -> -0.4ppt | BJ33: =(ROUND(BH33-BG33,3)*100)&"ppt" -> 0.4ppt
A34: 税前利润率 | B34: Profit before income tax margin | O34: =O21/O7 -> 0.11812079 | P34: =P21/P7 -> 0.1320003 | Q34: =Q21/Q7 -> 0.12139729 | R34: =R21/R7 -> 0.10569901 | S34: =S21/S7 -> 0.10641977 | T34: =T21/T7 -> 0.11240922 | U34: =U21/U7 -> 0.11914038 | V34: =(ROUND(U34-T34,3)*100)&"ppt" -> 0.7ppt | AW34: =AW21/AW7 -> 0.14101692 | AX34: =AX21/AX7 -> 0.12467255 | AY34: =AY21/AY7 -> 0.13205028 | AZ34: =AZ21/AZ7 -> 0.1119329 | BA34: =BA21/BA7 -> 0.10342574 | BB34: =BB21/BB7 -> 0.10823876 | BC34: =BC21/BC7 -> 0.11544781 | BD34: =BD21/BD7 -> 0.097932663 | ... BH34: =BH21/BH7 -> 0.10994181 | BI34: =(ROUND(BH34-BF34,3)*100)&"ppt" -> 0.7ppt | BJ34: =(ROUND(BH34-BG34,3)*100)&"ppt" -> -1.6ppt
A35: 净利率 | B35: Net profit margin | D35: =D25/D7 -> 0.044397334 | E35: =E25/E7 -> 0.063107703 | F35: =F25/F7 -> 0.086479943 | G35: =G25/G7 -> 0.092031038 | H35: =H25/H7 -> 0.13423836 | I35: =I25/I7 -> 0.10076923 | J35: =J25/J7 -> 0.10039061 | K35: =K25/K7 -> 0.11905007 | ... U35: =U25/U7 -> 0.085500968 | V35: =(ROUND(U35-T35,3)*100)&"ppt" -> 0.4ppt | X35: The effective tax rate increased in the period | Y35: =Y25/Y7 -> 0.051491615 | Z35: =Z25/Z7 -> 0.045459846 | AA35: =AA25/AA7 -> 0.055135169 | AB35: =AB25/AB7 -> 0.088177928 | AC35: =AC25/AC7 -> 0.092809005 | AD35: =AD25/AD7 -> 0.081951613 | AE35: =AE25/AE7 -> 0.10755258 | AF35: =AF25/AF7 -> 0.082889718 | ... BH35: =BH25/BH7 -> 0.076009951 | BI35: =(ROUND(BH35-BF35,3)*100)&"ppt" -> 0.3ppt | BJ35: =(ROUND(BH35-BG35,3)*100)&"ppt" -> -1.7ppt
A36: 有效税率 | B36: Effective tax rate | D36: =D22/D21 -> 0.1077338 | E36: =E22/E21 -> 0.090389089 | F36: =F22/F21 -> 0.15989747 | G36: =G22/G21 -> 0.18116457 | H36: =H22/H21 -> -0.14973699 | I36: =I22/I21 -> 0.15850957 | J36: =J22/J21 -> 0.16298967 | K36: =K22/K21 -> 0.12851335 | ... U36: =U22/U21 -> 0.24751242 | V36: =(ROUND(U36-T36,3)*100)&"ppt" -> 2.6ppt | AE36: =AE22/AE21 -> 0.087869549 | AF36: =AF22/AF21 -> 0.24009987 | AG36: =AG22/AG21 -> 0.17112797 | AH36: =AH22/AH21 -> -0.36084706 | AI36: =AI22/AI21 -> 0.17074411 | AJ36: =AJ22/AJ21 -> 0.1488689 | AK36: =AK22/AK21 -> 0.17904639 | AL36: =AL22/AL21 -> 0.15059208 | ... BH36: =BH22/BH21 -> 0.2739878 | BI36: =(ROUND(BH36-BF36,3)*100)&"ppt" -> 3.8ppt | BJ36: =(ROUND(BH36-BG36,3)*100)&"ppt" -> 4.4ppt
L37: =L33+L31 -> 0.038830118 | M37: =M33+M31 -> 0.049138544 | N37: =N33+N31 -> 0.057136836 | O37: =O33+O31 -> 0.06422581 | P37: =P33+P31 -> 0.073655406 | Q37: =Q33+Q31 -> 0.063987009 | R37: =R33+R31 -> 0.053210776 | S37: =S33+S31 -> 0.051235421 | ... U37: =U33+U31 -> 0.05098544 | V37: =(ROUND(U37-T37,3)*100)&"ppt" -> -0.2ppt | AO37: =AO33+AO31 -> 0.051455626 | AQ37: =AQ33+AQ31 -> 0.048182857 | AR37: =AR33+AR31 -> 0.049945875 | AS37: =AS33+AS31 -> 0.053935877 | AT37: =AT33+AT31 -> 0.060178977 | AU37: =AU33+AU31 -> 0.068071707 | AV37: =AV33+AV31 -> 0.06112196 | AW37: =AW33+AW31 -> 0.076182176 | AX37: =AX33+AX31 -> 0.071601915 | ... BH37: =BH33+BH31 -> 0.062407282 | BI37: =(ROUND(BH37-BF37,3)*100)&"ppt" -> 0.4ppt | BJ37: =(ROUND(BH37-BG37,3)*100)&"ppt" -> 2ppt
A38: 总股本 | B38: Total shars
B39: =BS!N89 -> 5282.2167
A40: 每股股息 | B40: DPS | Q40: 0.405 | R40: 0.48 | S40: 0.56 | T40: 0.615 | U40: 0.625 | V40: =U40-T40 -> 0.01 | AU40: 0.16 | AW40: 0.17 | AY40: 0.2 | AZ40: =Q40-AY40 -> 0.205 | BA40: 0.24 | BB40: =R40-BA40 -> 0.24 | BC40: 0.275 | BD40: 0.28 | BE40: 0.33 | BF40: 0.285 | BG40: 0.34 | BH40: =U40-BG40 -> 0.285 | BI40: =BH40/BF40-1 -> 0 | BJ40: =BH40/BG40-1 -> -0.16176471
A41: 股价 | B41: Price | Q41: 9.3 | R41: 9.5 | S41: 8.8 | T41: 9.5 | U41: 12.26 | AU41: 6.81 | AW41: 5.74 | AY41: 5.5 | AZ41: =Q41 -> 9.3 | BA41: 8.64 | BB41: =R41 -> 9.5 | BC41: 8.71 | BD41: 8.65 | BE41: 11.32 | BF41: 11.68 | BG41: 11.47 | BH41: 9.11
A42: 股息率 | B42: Yield | Q42: =Q40/Q41 -> 0.043548387 | R42: =R40/R41 -> 0.050526316 | S42: =S40/S41 -> 0.063636364 | T42: =T40/T41 -> 0.064736842 | U42: =U40/U41 -> 0.050978793 | V42: =U42-T42 -> -0.013758049 | AU42: =AU40/AU41 -> 0.02349486 | AW42: =AW40/AW41 -> 0.029616725 | AY42: =AY40/AY41 -> 0.036363636 | AZ42: =AZ40/AZ41 -> 0.022043011 | BA42: =BA40/BA41 -> 0.027777778 | BB42: =BB40/BB41 -> 0.025263158 | BC42: =BC40/BC41 -> 0.031572905 | BD42: =BD40/BD41 -> 0.032369942 | BE42: =BE40/BE41 -> 0.029151943 | BF42: =BF40/BF41 -> 0.024400685 | ... BH42: =BH40/BH41 -> 0.031284303 | BI42: =BH42/BF42-1 -> 0.28210757 | BJ42: =BH42/BG42-1 -> 0.055385162
A44: 净负债比率 | B44: Net gearing | Q44: 0.694 | R44: 0.694 | S44: 0.661 | T44: 0.736 | U44: 0.685 | V44: =U44-T44 -> -0.051 | AU44: 0.499 | AV44: 0.451 | AW44: 0.568 | AX44: 0.548 | AY44: 0.647 | AZ44: =Q44 -> 0.694 | BA44: 0.671 | BB44: =R44 -> 0.694 | BC44: 0.675 | BD44: 0.661 | BE44: 0.698 | BF44: 0.736 | BG44: 0.652 | BH44: 0.685 | BI44: =BH44/BF44-1 -> -0.069293478 | BJ44: =BH44/BG44-1 -> 0.050613497
A46: OCF | P46: -4530 | Q46: -550 | R46: 210 | S46: 501 | T46: 2007 | U46: 1050 | AS46: -39.94 | AU46: -14.06 | AW46: -5030 | AX46: 0 | AY46: -971 | AZ46: =Q46-AY46 -> 421 | BA46: 102 | BB46: =R46-BA46 -> 108 | BC46: 168 | BD46: =S46-BC46 -> 333 | BE46: 2 | BF46: =T46-BE46 -> 2005 | BG46: 123 | BH46: =U46-BG46 -> 927 | BI46: =BH46-BF46 -> -1078 | BJ46: =BH46-BG46 -> 804
A47: ICF | Q47: -4950 | R47: 500 | S47: 1174 | T47: 1137 | U47: 1139 | AS47: -39.18 | AU47: -9.55 | AW47: -1381 | AX47: 0 | AY47: -2224 | AZ47: =Q47-AY47 -> -2726 | BA47: 1899 | BB47: =R47-BA47 -> -1399 | BC47: 1097 | BD47: =S47-BC47 -> 77 | BE47: -1455 | BF47: =T47-BE47 -> 2592 | BG47: 304 | BH47: =U47-BG47 -> 835 | BI47: =BH47-BF47 -> -1757 | BJ47: =BH47-BG47 -> 531
A49: 中国内地业务现金净流入/流出 | O49: =O50-O51 -> -3568 | P49: =P50-P51 -> -5763 | Q49: =Q50-Q51 -> -1740 | R49: =R50-R51 -> -300 | S49: =S50-S51 -> 0 | T49: =T50-T51 -> 1000 | U49: 430 | AW49: =AW50-AW51 -> -3997 | AX49: =AX50-AX51 -> -1766 | AY49: =AY50-AY51 -> -1412 | AZ49: =Q49-AY49 -> -328 | BA49: =BA50-BA51 -> -990 | BB49: =R49-BA49 -> 690 | BC49: =BC50-BC51 -> -680 | BD49: =S49-BC49 -> 680 | BE49: =BE50-BE51 -> -222 | BF49: =T49-BE49 -> 1222 | BG49: =BG50-BG51 -> -336 | BH49: =U49-BG49 -> 766 | BI49: =BH49-BF49 -> -456 | BJ49: =BH49-BG49 -> 1102
A50: 中国内地业务现金流入 | O50: 21732 | P50: 33053 | Q50: 46750 | R50: 51170 | S50: 61000 | T50: 67200 | U50: 64330 | AW50: 14410 | AX50: 18643 | AY50: 19623 | AZ50: =Q50-AY50 -> 27127 | BA50: 22440 | BB50: =R50-BA50 -> 28730 | BC50: 24900 | BD50: =S50-BC50 -> 36100 | BE50: 27375 | BF50: =T50-BE50 -> 39825 | BG50: 28550 | BH50: =U50-BG50 -> 35780 | BI50: =BH50-BF50 -> -4045 | BJ50: =BH50-BG50 -> 7230
A51: 中国内地业务现金流出 | O51: 25300 | P51: 38816 | Q51: 48490 | R51: 51470 | S51: 61000 | T51: 66200 | U51: =U50-U49 -> 63900 | AW51: 18407 | AX51: 20409 | AY51: 21035 | AZ51: =Q51-AY51 -> 27455 | BA51: 23430 | BB51: =R51-BA51 -> 28040 | BC51: 25580 | BD51: =S51-BC51 -> 35420 | BE51: 27597 | BF51: =T51-BE51 -> 38603 | BG51: 28886 | BH51: =U51-BG51 -> 35014 | BI51: =BH51-BF51 -> -3589 | BJ51: =BH51-BG51 -> 6128
A52: 港澳业务现金净流入/流出 | O52: 864 | P52: 1231 | Q52: 1190 | R52: 500 | S52: 500 | T52: 1000 | U52: 630 | AW52: -1033 | AX52: 2264 | AY52: 441 | AZ52: =Q52-AY52 -> 749 | BA52: 1090 | BB52: =R52-BA52 -> -590 | BC52: 850 | BD52: =S52-BC52 -> -350 | BE52: 850 | BF52: =T52-BE52 -> 150 | BG52: 459 | BH52: =U52-BG52 -> 171 | BI52: =BH52-BF52 -> 21 | BJ52: =BH52-BG52 -> -288
A53: 经营性现金流合计 | O53: =O49+O52 -> -2704 | P53: =P49+P52 -> -4532 | Q53: =Q49+Q52 -> -550 | R53: =R49+R52 -> 200 | S53: =S49+S52 -> 500 | T53: =T49+T52 -> 2000 | U53: =U49+U52 -> 1060 | AW53: =AW49+AW52 -> -5030 | AX53: =AX49+AX52 -> 498 | AY53: =AY49+AY52 -> -971 | AZ53: =Q53-AY53 -> 421 | BA53: =BA49+BA52 -> 100 | BB53: =R53-BA53 -> 100 | BC53: =BC49+BC52 -> 170 | BD53: =S53-BC53 -> 330 | BE53: =BE49+BE52 -> 628 | BF53: =T53-BE53 -> 1372 | BG53: =BG49+BG52 -> 123 | BH53: =U53-BG53 -> 937 | BI53: =BH53-BF53 -> -435 | BJ53: =BH53-BG53 -> 814
M55: 9841 | N55: 7356 | O55: 7356
M56: 670 | N56: 475 | O56: 475
M57: =M56/M55 -> 0.068082512 | N57: =N56/N55 -> 0.064573138 | O57: =O56/O55 -> 0.064573138

Sheet BS
A1: Balance check | B1: 配平检查 | D1: =ROUND(D43-D84,1) -> 0 | E1: =ROUND(E43-E84,1) -> 0 | F1: =ROUND(F43-F84,1) -> 0 | G1: =ROUND(G43-G84,1) -> 0 | H1: =ROUND(H43-H84,1) -> 0 | I1: =ROUND(I43-I84,1) -> 0 | J1: =ROUND(J43-J84,1) -> 0 | K1: =ROUND(K43-K84,1) -> 0 | ... AG1: =ROUND(AG43-AG84,1) -> 0
A2: HKD mn | B2: 港币 百万元 | C2: 2005A | D2: 2006A | E2: 2007A | F2: 2008A | G2: 2009A | H2: 2010A | I2: 2011A | J2: 2012A | K2: 2013A | L2: 2014A | M2: 2015A | N2: 2016A | O2: 2017A | P2: 2018A | Q2: =PL!Q3 -> 2019A | R2: =PL!R3 -> 2020A | S2: =PL!S3 -> 2021A | T2: =PL!T3 -> 2022A | U2: =PL!U3 -> 2023A | V2: =PL!V3 -> 2024A | W2: =PL!W3 -> 2025A | X2: =PL!X3 -> 2026E | ... AG2: =PL!AG3 -> 2035E
A3: Non-current Assets: | B3: 非流动资产：
A4: Property, plant and equipment | B4: 物业、厂房及设备 | D4: ='BS（org）'!E5 -> 96.579 | E4: ='BS（org）'!F5 -> 971.953 | F4: ='BS（org）'!G5 -> 1107.275 | G4: ='BS（org）'!H5 -> 1121.324 | H4: ='BS（org）'!I5 -> 1454.445 | I4: ='BS（org）'!J5 -> 1870.033 | J4: ='BS（org）'!K5 -> 2190.951 | K4: ='BS（org）'!L5 -> 2672.357 | ... W4: ='BS（org）'!X5 -> 6505.429 | X4: =CAPEX!X78 -> 7340.0162 | Y4: =CAPEX!Y78 -> 8205.1342 | Z4: =CAPEX!Z78 -> 9074.7001 | AA4: =CAPEX!AA78 -> 9969.767 | AB4: =CAPEX!AB78 -> 10877.431 | AC4: =CAPEX!AC78 -> 11786.688 | AD4: =CAPEX!AD78 -> 12688.101 | AE4: =CAPEX!AE78 -> 13573.542 | ... AG4: =CAPEX!AG78 -> 15269.276
A5: Investment properties | B5: 投资物业 | D5: ='BS（org）'!E6 -> 10.065 | E5: ='BS（org）'!F6 -> 9.705 | F5: ='BS（org）'!G6 -> 44.692 | G5: ='BS（org）'!H6 -> 43.031 | H5: ='BS（org）'!I6 -> 42.038 | I5: ='BS（org）'!J6 -> 41.063 | J5: ='BS（org）'!K6 -> 40.044 | K5: ='BS（org）'!L6 -> 39.085 | ... W5: ='BS（org）'!X6 -> 6738.116 | X5: =CAPEX!X99 -> 6737.116 | Y5: =CAPEX!Y99 -> 6736.116 | Z5: =CAPEX!Z99 -> 6735.116 | AA5: =CAPEX!AA99 -> 6734.116 | AB5: =CAPEX!AB99 -> 6733.116 | AC5: =CAPEX!AC99 -> 6732.116 | AD5: =CAPEX!AD99 -> 6731.116 | AE5: =CAPEX!AE99 -> 6730.116 | ... AG5: =CAPEX!AG99 -> 6728.116
A6: Interests in infrastructure project investment | B6: 基建项目投资权益 | D6: ='BS（org）'!E7 -> 0 | E6: ='BS（org）'!F7 -> 0 | F6: ='BS（org）'!G7 -> 466.876 | G6: ='BS（org）'!H7 -> 1050.04 | H6: ='BS（org）'!I7 -> 673.575 | I6: ='BS（org）'!J7 -> 673.224 | J6: ='BS（org）'!K7 -> 915.049 | K6: ='BS（org）'!L7 -> 1186.012 | ... W6: ='BS（org）'!X7 -> 3247.527 | X6: =W6*1.05 -> 3409.9034 | Y6: =X6*1.05 -> 3580.3985 | Z6: =Y6*1.05 -> 3759.4184 | AA6: =Z6*1.05 -> 3947.3894 | AB6: =AA6*1.05 -> 4144.7588 | AC6: =AB6*1.05 -> 4351.9968 | AD6: =AC6*1.05 -> 4569.5966 | AE6: =AD6*1.05 -> 4798.0764 | ... AG6: =AF6*1.05 -> 5289.8793
A7: Investment in lands consolidation | B7: 土地综合整理之投资 | D7: ='BS（org）'!E13 -> 0 | E7: ='BS（org）'!F13 -> 0 | F7: ='BS（org）'!G13 -> 49.814 | G7: ='BS（org）'!H13 -> 0 | H7: ='BS（org）'!I13 -> 0 | I7: ='BS（org）'!J13 -> 0 | J7: ='BS（org）'!K13 -> 0 | K7: ='BS（org）'!L13 -> 0 | ... W7: ='BS（org）'!X13 -> 0 | X7: =W7 -> 0 | Y7: =X7 -> 0 | Z7: =Y7 -> 0 | AA7: =Z7 -> 0 | AB7: =AA7 -> 0 | AC7: =AB7 -> 0 | AD7: =AC7 -> 0 | AE7: =AD7 -> 0 | ... AG7: =AF7 -> 0
A8: Prepaid lease payments | B8: 预付租金 | D8: ='BS（org）'!E8 -> 12.448 | E8: ='BS（org）'!F8 -> 60.327 | F8: ='BS（org）'!G8 -> 78.536 | G8: ='BS（org）'!H8 -> 76.551 | H8: ='BS（org）'!I8 -> 172.258 | I8: ='BS（org）'!J8 -> 180.197 | J8: ='BS（org）'!K8 -> 182.291 | K8: ='BS（org）'!L8 -> 280.063 | ... W8: ='BS（org）'!X8 -> 0 | X8: =W8 -> 0 | Y8: =X8 -> 0 | Z8: =Y8 -> 0 | AA8: =Z8 -> 0 | AB8: =AA8 -> 0 | AC8: =AB8 -> 0 | AD8: =AC8 -> 0 | AE8: =AD8 -> 0 | ... AG8: =AF8 -> 0
A9: Trademark, project backlogs and licenses | B9: 商标、未完成工程合同、牌照和商誉 | D9: ='BS（org）'!E11 -> 0 | E9: ='BS（org）'!F11 -> 0 | F9: ='BS（org）'!G11 -> 0 | G9: ='BS（org）'!H11 -> 9.95 | H9: ='BS（org）'!I11 -> 9.95 | I9: ='BS（org）'!J11 -> 9.95 | J9: ='BS（org）'!K11 -> 252.551 | K9: ='BS（org）'!L11 -> 226.596 | ... W9: ='BS（org）'!X11 -> 164.258 | X9: =CAPEX!X136 -> 194.93297 | Y9: =CAPEX!Y136 -> 194.93297 | Z9: =CAPEX!Z136 -> 194.93297 | AA9: =CAPEX!AA136 -> 194.93297 | AB9: =CAPEX!AB136 -> 194.93297 | AC9: =CAPEX!AC136 -> 194.93297 | AD9: =CAPEX!AD136 -> 194.93297 | AE9: =CAPEX!AE136 -> 194.93297 | ... AG9: =CAPEX!AG136 -> 194.93297
A10: Interests in joint ventures | B10: 于合营企业之权益 | D10: ='BS（org）'!E10 -> 0 | E10: ='BS（org）'!F10 -> 0 | F10: ='BS（org）'!G10 -> 0 | G10: ='BS（org）'!H10 -> 0 | H10: ='BS（org）'!I10 -> 2350.893 | I10: ='BS（org）'!J10 -> 2589.828 | J10: ='BS（org）'!K10 -> 2735.493 | K10: ='BS（org）'!L10 -> 2149.893 | ... W10: ='BS（org）'!X10 -> 16344.908 | X10: =W10*1 -> 16344.908 | Y10: =X10*1 -> 16344.908 | Z10: =Y10*1 -> 16344.908 | AA10: =Z10*1 -> 16344.908 | AB10: =AA10*1 -> 16344.908 | AC10: =AB10*1 -> 16344.908 | AD10: =AC10*1 -> 16344.908 | AE10: =AD10*1 -> 16344.908 | ... AG10: =AF10*1 -> 16344.908
A11: Interests in associates | B11: 于联营公司之权益 | D11: ='BS（org）'!E9 -> 34.013 | E11: ='BS（org）'!F9 -> 35.071 | F11: ='BS（org）'!G9 -> 41.258 | G11: ='BS（org）'!H9 -> 35.175 | H11: ='BS（org）'!I9 -> 34.552 | I11: ='BS（org）'!J9 -> 29.237 | J11: ='BS（org）'!K9 -> 36.156 | K11: ='BS（org）'!L9 -> 48.757 | ... W11: ='BS（org）'!X9 -> 5585.917 | X11: =W11*1.03 -> 5753.4945 | Y11: =X11*1.03 -> 5926.0993 | Z11: =Y11*1.03 -> 6103.8823 | AA11: =Z11*1.03 -> 6286.9988 | AB11: =AA11*1.03 -> 6475.6088 | AC11: =AB11*1.03 -> 6669.877 | AD11: =AC11*1.03 -> 6869.9733 | AE11: =AD11*1.03 -> 7076.0725 | ... AG11: =AF11*1.03 -> 7507.0053
A12: Available-for-sale investments | B12: 可供出售之投资 | D12: ='BS（org）'!E14 -> 23.786 | E12: ='BS（org）'!F14 -> 111.295 | F12: ='BS（org）'!G14 -> 98.169 | G12: ='BS（org）'!H14 -> 116.179 | H12: ='BS（org）'!I14 -> 396.953 | I12: ='BS（org）'!J14 -> 490.842 | J12: ='BS（org）'!K14 -> 497.861 | K12: ='BS（org）'!L14 -> 543.642 | ... W12: ='BS（org）'!X14 -> 0 | X12: =W12 -> 0 | Y12: =X12 -> 0 | Z12: =Y12 -> 0 | AA12: =Z12 -> 0 | AB12: =AA12 -> 0 | AC12: =AB12 -> 0 | AD12: =AC12 -> 0 | AE12: =AD12 -> 0 | ... AG12: =AF12 -> 0
A13: Amounts due from investee companies | B13: 应收投资公司款 | D13: ='BS（org）'!E15 -> 10.909 | E13: ='BS（org）'!F15 -> 146.772 | F13: ='BS（org）'!G15 -> 181.94 | G13: ='BS（org）'!H15 -> 250.142 | H13: ='BS（org）'!I15 -> 362.247 | I13: ='BS（org）'!J15 -> 356.085 | J13: ='BS（org）'!K15 -> 361.471 | K13: ='BS（org）'!L15 -> 399.645 | ... W13: ='BS（org）'!X15 -> 13.193 | X13: =WC!X69 -> 13.601728 | Y13: =WC!Y69 -> 14.998457 | Z13: =WC!Z69 -> 16.14005 | AA13: =WC!AA69 -> 17.709901 | AB13: =WC!AB69 -> 19.189178 | AC13: =WC!AC69 -> 20.5951 | AD13: =WC!AD69 -> 21.941832 | AE13: =WC!AE69 -> 23.241035 | ... AG13: =WC!AG69 -> 25.733671
A14: Trade and other receivables | B14: 贸易及其他应收款-非流动部分 | D14: ='BS（org）'!E16 -> 0 | E14: ='BS（org）'!F16 -> 0 | F14: ='BS（org）'!G16 -> 0 | G14: ='BS（org）'!H16 -> 0 | H14: ='BS（org）'!I16 -> 0 | I14: ='BS（org）'!J16 -> 919.473 | J14: ='BS（org）'!K16 -> 3186.846 | K14: ='BS（org）'!L16 -> 8141.167 | ... W14: ='BS（org）'!X16 -> 53621.83 | X14: =WC!X60 -> 56417.978 | Y14: =WC!Y60 -> 60959.958 | Z14: =WC!Z60 -> 65263.188 | AA14: =WC!AA60 -> 71241.547 | AB14: =WC!AB60 -> 76791.95 | AC14: =WC!AC60 -> 82418.219 | AD14: =WC!AD60 -> 87349.919 | AE14: =WC!AE60 -> 92037.218 | ... AG14: =WC!AG60 -> 100834.76
A15: Deferred tax assets | B15: 递延税项资产 | D15: ='BS（org）'!E18 -> 0 | E15: ='BS（org）'!F18 -> 0 | F15: ='BS（org）'!G18 -> 0 | G15: ='BS（org）'!H18 -> 0 | H15: ='BS（org）'!I18 -> 0 | I15: ='BS（org）'!J18 -> 0 | J15: ='BS（org）'!K18 -> 0 | K15: ='BS（org）'!L18 -> 151.027 | ... W15: ='BS（org）'!X18 -> 114.67 | X15: =WC!X75 -> 118.22255 | Y15: =WC!Y75 -> 130.36255 | Z15: =WC!Z75 -> 140.28496 | AA15: =WC!AA75 -> 153.92969 | AB15: =WC!AB75 -> 166.78717 | AC15: =WC!AC75 -> 179.00706 | AD15: =WC!AD75 -> 190.71249 | AE15: =WC!AE75 -> 202.00481 | ... AG15: =WC!AG75 -> 223.67013
B16: 按公平值列入其他全面收益之金融资产 | P16: ='BS（org）'!Q19 -> 505.416 | Q16: ='BS（org）'!R19 -> 658.355 | R16: ='BS（org）'!S19 -> 689.958 | S16: ='BS（org）'!T19 -> 693.39 | T16: ='BS（org）'!U19 -> 545.886 | U16: ='BS（org）'!V19 -> 388.709 | V16: ='BS（org）'!W19 -> 227.928 | W16: ='BS（org）'!X19 -> 496.31 | X16: =W16 -> 496.31 | Y16: =X16 -> 496.31 | Z16: =Y16 -> 496.31 | AA16: =Z16 -> 496.31 | AB16: =AA16 -> 496.31 | AC16: =AB16 -> 496.31 | AD16: =AC16 -> 496.31 | AE16: =AD16 -> 496.31 | ... AG16: =AF16 -> 496.31
A17: Deposit paid for an investment | B17: 已付一投资项目按金 | D17: ='BS（org）'!E20 -> 0 | E17: ='BS（org）'!F20 -> 0 | F17: ='BS（org）'!G20 -> 0 | G17: ='BS（org）'!H20 -> 0 | H17: ='BS（org）'!I20 -> 0 | I17: ='BS（org）'!J20 -> 0 | J17: ='BS（org）'!K20 -> 0 | K17: ='BS（org）'!L20 -> 500 | ... W17: ='BS（org）'!X20 -> 0 | X17: =W17 -> 0 | Y17: =X17 -> 0 | Z17: =Y17 -> 0 | AA17: =Z17 -> 0 | AB17: =AA17 -> 0 | AC17: =AB17 -> 0 | AD17: =AC17 -> 0 | AE17: =AD17 -> 0 | ... AG17: =AF17 -> 0
A18: Loans receivable from a JV | B18: 应收一合营企业借款 | D18: ='BS（org）'!E21 -> 0 | E18: ='BS（org）'!F21 -> 0 | F18: ='BS（org）'!G21 -> 0 | G18: ='BS（org）'!H21 -> 0 | H18: ='BS（org）'!I21 -> 0 | I18: ='BS（org）'!J21 -> 0 | J18: ='BS（org）'!K21 -> 0 | K18: ='BS（org）'!L21 -> 127.55 | ... W18: ='BS（org）'!X21 -> 1021.85 | X18: =WC!X72 -> 1053.5076 | Y18: =WC!Y72 -> 1161.6898 | Z18: =WC!Z72 -> 1250.1106 | AA18: =WC!AA72 -> 1371.7018 | AB18: =WC!AB72 -> 1486.2777 | AC18: =WC!AC72 -> 1595.1719 | AD18: =WC!AD72 -> 1699.4816 | AE18: =WC!AE72 -> 1800.1101 | ... AG18: =WC!AG72 -> 1993.1746
A19: Convertible bonds | B19: 可换股债券之投资 | D19: ='BS（org）'!E23 -> 0 | E19: ='BS（org）'!F23 -> 0 | F19: ='BS（org）'!G23 -> 0 | G19: ='BS（org）'!H23 -> 0 | H19: ='BS（org）'!I23 -> 219.686 | I19: ='BS（org）'!J23 -> 240 | J19: ='BS（org）'!K23 -> 296.827 | K19: ='BS（org）'!L23 -> 0 | ... W19: ='BS（org）'!X23 -> 0 | X19: =W19 -> 0 | Y19: =X19 -> 0 | Z19: =Y19 -> 0 | AA19: =Z19 -> 0 | AB19: =AA19 -> 0 | AC19: =AB19 -> 0 | AD19: =AC19 -> 0 | AE19: =AD19 -> 0 | ... AG19: =AF19 -> 0
A20: Concession operating rights | B20: 特许经营权 | D20: ='BS（org）'!E12 -> 0 | E20: ='BS（org）'!F12 -> 0 | F20: ='BS（org）'!G12 -> 0 | G20: ='BS（org）'!H12 -> 0 | H20: ='BS（org）'!I12 -> 4046.058 | I20: ='BS（org）'!J12 -> 4926.465 | J20: ='BS（org）'!K12 -> 5501.701 | K20: ='BS（org）'!L12 -> 6353.833 | ... W20: ='BS（org）'!X12 -> 2411.087 | X20: =CAPEX!X118 -> 2378.2858 | Y20: =CAPEX!Y118 -> 2153.9938 | Z20: =CAPEX!Z118 -> 1934.7027 | AA20: =CAPEX!AA118 -> 1718.7874 | AB20: =CAPEX!AB118 -> 1507.0394 | AC20: =CAPEX!AC118 -> 1299.0735 | AD20: =CAPEX!AD118 -> 1095.0769 | AE20: =CAPEX!AE118 -> 894.95875 | ... AG20: =CAPEX!AG118 -> 506.46867
B21: 使用权资产 | N21: ='BS（org）'!O24 -> 0 | O21: ='BS（org）'!P24 -> 0 | P21: ='BS（org）'!Q24 -> 0 | Q21: ='BS（org）'!R24 -> 0 | R21: ='BS（org）'!S24 -> 0 | S21: ='BS（org）'!T24 -> 0 | T21: ='BS（org）'!U24 -> 0 | U21: ='BS（org）'!V24 -> 600.332 | ... W21: ='BS（org）'!X24 -> 799.497 | X21: =W21 -> 799.497 | Y21: =X21 -> 799.497 | Z21: =Y21 -> 799.497 | AA21: =Z21 -> 799.497 | AB21: =AA21 -> 799.497 | AC21: =AB21 -> 799.497 | AD21: =AC21 -> 799.497 | AE21: =AD21 -> 799.497 | ... AG21: =AF21 -> 799.497
A22: Goodwill | B22: 商誉 | D22: ='BS（org）'!E17 -> 0 | E22: ='BS（org）'!F17 -> 0 | F22: ='BS（org）'!G17 -> 0 | G22: ='BS（org）'!H17 -> 0 | H22: ='BS（org）'!I17 -> 0 | I22: ='BS（org）'!J17 -> 0 | J22: ='BS（org）'!K17 -> 577.664 | K22: ='BS（org）'!L17 -> 577.664 | ... W22: ='BS（org）'!X17 -> 519.9 | X22: =W22 -> 519.9 | Y22: =X22 -> 519.9 | Z22: =Y22 -> 519.9 | AA22: =Z22 -> 519.9 | AB22: =AA22 -> 519.9 | AC22: =AB22 -> 519.9 | AD22: =AC22 -> 519.9 | AE22: =AD22 -> 519.9 | ... AG22: =AF22 -> 519.9
B23: 应收借款 | N23: ='BS（org）'!O22 -> 0 | O23: ='BS（org）'!P22 -> 0 | P23: ='BS（org）'!Q22 -> 0 | Q23: ='BS（org）'!R22 -> 0 | R23: ='BS（org）'!S22 -> 0 | S23: ='BS（org）'!T22 -> 0 | T23: ='BS（org）'!U22 -> 0 | U23: ='BS（org）'!V22 -> 0 | ... W23: ='BS（org）'!X22 -> 37.53 | X23: =WC!X78 -> 38.692704 | Y23: =WC!Y78 -> 42.665967 | Z23: =WC!Z78 -> 45.913444 | AA23: =WC!AA78 -> 50.379185 | AB23: =WC!AB78 -> 54.587271 | AC23: =WC!AC78 -> 58.586683 | AD23: =WC!AD78 -> 62.417717 | AE23: =WC!AE78 -> 66.113549 | ... AG23: =WC!AG78 -> 73.204327
A24: Non-current Assets | B24: 非流动资产合计 | D24: =SUM(D4:D22) -> 187.8 | E24: =SUM(E4:E22) -> 1335.123 | F24: =SUM(F4:F22) -> 2068.56 | G24: =SUM(G4:G22) -> 2702.392 | H24: =SUM(H4:H22) -> 9762.655 | I24: =SUM(I4:I22) -> 12326.397 | J24: =SUM(J4:J22) -> 16774.905 | K24: =SUM(K4:K22) -> 23397.291 | ... V24: =SUM(V4:V22) -> 92779.24 | W24: =SUM(W4:W23) -> 97622.022 | X24: =SUM(X4:X23) -> 101616.37 | Y24: =SUM(Y4:Y23) -> 107266.96 | Z24: =SUM(Z4:Z23) -> 112679 | AA24: =SUM(AA4:AA23) -> 119847.87 | AB24: =SUM(AB4:AB23) -> 126612.29 | AC24: =SUM(AC4:AC23) -> 133466.88 | AD24: =SUM(AD4:AD23) -> 139633.88 | ... AG24: =SUM(AG4:AG23) -> 156806.83
A25: Current Assets: | B25: 流动资产：
A26: Properties held for sale | B26: 完成待售物业 | D26: =+'BS（org）'!E32 -> 20.408 | E26: =+'BS（org）'!F32 -> 20.408 | F26: =+'BS（org）'!G32 -> 9.309 | G26: =+'BS（org）'!H32 -> 7.859 | H26: =+'BS（org）'!I32 -> 8.13 | I26: =+'BS（org）'!J32 -> 158.608 | J26: =+'BS（org）'!K32 -> 158.608 | K26: =+'BS（org）'!L32 -> 152.905 | ... W26: =+'BS（org）'!X32 -> 4045.72 | X26: =WC!X32 -> 4045.72 | Y26: =WC!Y32 -> 4045.72 | Z26: =WC!Z32 -> 4045.72 | AA26: =WC!AA32 -> 4045.72 | AB26: =WC!AB32 -> 4045.72 | AC26: =WC!AC32 -> 4045.72 | AD26: =WC!AD32 -> 4045.72 | AE26: =WC!AE32 -> 4045.72 | ... AG26: =WC!AG32 -> 4045.72
A27: Inventories | B27: 存货 | D27: ='BS（org）'!E30 -> 8.715 | E27: ='BS（org）'!F30 -> 54.486 | F27: ='BS（org）'!G30 -> 55.509 | G27: ='BS（org）'!H30 -> 46.883 | H27: ='BS（org）'!I30 -> 117.711 | I27: ='BS（org）'!J30 -> 149.559 | J27: ='BS（org）'!K30 -> 185.374 | K27: ='BS（org）'!L30 -> 163.427 | ... W27: ='BS（org）'!X30 -> 460.09 | X27: =WC!X20 -> 542.18191 | Y27: =WC!Y20 -> 599.57459 | Z27: =WC!Z20 -> 647.88505 | AA27: =WC!AA20 -> 709.7253 | AB27: =WC!AB20 -> 768.15944 | AC27: =WC!AC20 -> 823.87424 | AD27: =WC!AD20 -> 877.43515 | AE27: =WC!AE20 -> 929.30856 | ... AG27: =WC!AG20 -> 1029.4701
A28: Properties under development | B28: 开发中之物业 | P28: ='BS（org）'!Q31 -> 2349.51 | Q28: ='BS（org）'!R31 -> 1810.383 | R28: ='BS（org）'!S31 -> 4311.691 | S28: ='BS（org）'!T31 -> 6312.434 | T28: ='BS（org）'!U31 -> 6827.851 | U28: ='BS（org）'!V31 -> 6289.737 | V28: ='BS（org）'!W31 -> 7029.266 | W28: ='BS（org）'!X31 -> 6690.65 | X28: =WC!X34 -> 6891.3695 | Y28: =WC!Y34 -> 7098.1106 | Z28: =WC!Z34 -> 7311.0539 | AA28: =WC!AA34 -> 7530.3855 | AB28: =WC!AB34 -> 7756.2971 | AC28: =WC!AC34 -> 7988.986 | AD28: =WC!AD34 -> 8228.6556 | AE28: =WC!AE34 -> 8475.5152 | ... AG28: =WC!AG34 -> 8991.6741
A29: Trade and other receivables | B29: 贸易及其他应收款－流动部分 | D29: ='BS（org）'!E34 -> 2682.688 | E29: ='BS（org）'!F34 -> 3339.204 | F29: ='BS（org）'!G34 -> 3703.163 | G29: ='BS（org）'!H34 -> 3398.325 | H29: ='BS（org）'!I34 -> 4163.43 | I29: ='BS（org）'!J34 -> 4736.191 | J29: ='BS（org）'!K34 -> 6559.777 | K29: ='BS（org）'!L34 -> 10023.98 | ... W29: ='BS（org）'!X34 -> 102867.31 | X29: =WC!X11 -> 106905.39 | Y29: =WC!Y11 -> 118821.84 | Z29: =WC!Z11 -> 128539.19 | AA29: =WC!AA11 -> 141780.32 | AB29: =WC!AB11 -> 154423.54 | AC29: =WC!AC11 -> 166596.81 | AD29: =WC!AD11 -> 178863.82 | AE29: =WC!AE11 -> 189454.57 | ... AG29: =WC!AG11 -> 209773.86
A30: Amounts due from customers for contract work | B30: 合约资产 | D30: ='BS（org）'!E33 -> 224.772 | E30: ='BS（org）'!F33 -> 595.037 | F30: ='BS（org）'!G33 -> 506.385 | G30: ='BS（org）'!H33 -> 539.294 | H30: ='BS（org）'!I33 -> 194.281 | I30: ='BS（org）'!J33 -> 2937.9 | J30: ='BS（org）'!K33 -> 5458.682 | K30: ='BS（org）'!L33 -> 1075.267 | ... W30: ='BS（org）'!X33 -> 30752.5 | X30: =WC!X14 -> 31988.96 | Y30: =WC!Y14 -> 35586.693 | Z30: =WC!Z14 -> 38632.015 | AA30: =WC!AA14 -> 42758.955 | AB30: =WC!AB14 -> 46730.815 | AC30: =WC!AC14 -> 50584.22 | AD30: =WC!AD14 -> 54349.665 | AE30: =WC!AE14 -> 58052.578 | ... AG30: =WC!AG14 -> 65352.395
A31: Other receivables | B31: 其他应收款 | D31: ='BS（org）'!E35+'BS（org）'!E36+'BS（org）'!E37+'BS（org）'!E38+'BS（org）'!E39+'BS（org）'!E40+'BS（org）'!E41 -> 519.746 | E31: ='BS（org）'!F35+'BS（org）'!F36+'BS（org）'!F37+'BS（org）'!F38+'BS（org）'!F39+'BS（org）'!F40+'BS（org）'!F41 -> 662.532 | F31: ='BS（org）'!G35+'BS（org）'!G36+'BS（org）'!G37+'BS（org）'!G38+'BS（org）'!G39+'BS（org）'!G40+'BS（org）'!G41 -> 703.268 | G31: ='BS（org）'!H35+'BS（org）'!H36+'BS（org）'!H37+'BS（org）'!H38+'BS（org）'!H39+'BS（org）'!H40+'BS（org）'!H41 -> 678.922 | H31: ='BS（org）'!I35+'BS（org）'!I36+'BS（org）'!I37+'BS（org）'!I38+'BS（org）'!I39+'BS（org）'!I40+'BS（org）'!I41 -> 669.473 | I31: ='BS（org）'!J35+'BS（org）'!J36+'BS（org）'!J37+'BS（org）'!J38+'BS（org）'!J39+'BS（org）'!J40+'BS（org）'!J41 -> 926.349 | J31: ='BS（org）'!K35+'BS（org）'!K36+'BS（org）'!K37+'BS（org）'!K38+'BS（org）'!K39+'BS（org）'!K40+'BS（org）'!K41 -> 1333.169 | K31: ='BS（org）'!L35+'BS（org）'!L36+'BS（org）'!L37+'BS（org）'!L38+'BS（org）'!L39+'BS（org）'!L40+'BS（org）'!L41 -> 312.576 | ... W31: ='BS（org）'!X35+'BS（org）'!X36+'BS（org）'!X37+'BS（org）'!X38+'BS（org）'!X39+'BS（org）'!X40+'BS（org）'!X41 -> 6759.84 | X31: =WC!X17 -> 6969.2642 | Y31: =WC!Y17 -> 7684.9216 | Z31: =WC!Z17 -> 8269.8517 | AA31: =WC!AA17 -> 9074.2134 | AB31: =WC!AB17 -> 9832.1667 | AC31: =WC!AC17 -> 10552.534 | AD31: =WC!AD17 -> 11242.573 | AE31: =WC!AE17 -> 11908.26 | ... AG31: =WC!AG17 -> 13185.439
A32: Held for sale assets | B32: 持作待售资产 | D32: ='BS（org）'!E49 -> 0 | E32: ='BS（org）'!F49 -> 0 | F32: ='BS（org）'!G49 -> 0 | G32: ='BS（org）'!H49 -> 0 | H32: ='BS（org）'!I49 -> 0 | I32: ='BS（org）'!J49 -> 0 | J32: ='BS（org）'!K49 -> 0 | K32: ='BS（org）'!L49 -> 9169.319 | ... W32: ='BS（org）'!X49 -> 7.792 | X32: =W32*1.02 -> 7.94784 | Y32: =X32*1.02 -> 8.1067968 | Z32: =Y32*1.02 -> 8.2689327 | AA32: =Z32*1.02 -> 8.4343114 | AB32: =AA32*1.02 -> 8.6029976 | AC32: =AB32*1.02 -> 8.7750576 | AD32: =AC32*1.02 -> 8.9505587 | AE32: =AD32*1.02 -> 9.1295699 | ... AG32: =AF32*1.02 -> 9.4984045
A33: Subtotal Receivables | B33: 应收款项合计 | D33: =SUM(D29:D32) -> 3427.206 | E33: =SUM(E29:E32) -> 4596.773 | F33: =SUM(F30:F32)+F29 -> 4912.816 | G33: =SUM(G30:G32)+G29 -> 4616.541 | H33: =SUM(H30:H32)+H29 -> 5027.184 | I33: =SUM(I30:I32)+I29 -> 8600.44 | J33: =SUM(J30:J32)+J29 -> 13351.628 | K33: =SUM(K30:K32)+K29 -> 20581.142 | L33: =SUM(L30:L32)+L29 -> 26621.591 | M33: =SUM(M30:M32)+M29 -> 22683.317 | ... W33: =SUM(W30:W32)+W29 -> 140387.44 | X33: =SUM(X29:X32) -> 145871.56 | Y33: =SUM(Y29:Y32) -> 162101.56 | Z33: =SUM(Z29:Z32) -> 175449.33 | AA33: =SUM(AA29:AA32) -> 193621.92 | AB33: =SUM(AB29:AB32) -> 210995.13 | AC33: =SUM(AC29:AC32) -> 227742.34 | AD33: =SUM(AD29:AD32) -> 244465.01 | AE33: =SUM(AE29:AE32) -> 259424.54 | ... AG33: =SUM(AG29:AG32) -> 288321.19
A34: Other Current Assets | B34: 其它流动资产 | D34: =+'BS（org）'!E28+'BS（org）'!E29 -> 0.427 | E34: =+'BS（org）'!F28+'BS（org）'!F29 -> 1.612 | F34: =+'BS（org）'!G28+'BS（org）'!G29 -> 18.02 | G34: =+'BS（org）'!H28+'BS（org）'!H29 -> 18.051 | H34: =+'BS（org）'!I28+'BS（org）'!I29 -> 23.48 | I34: =+'BS（org）'!J28+'BS（org）'!J29 -> 28.271 | J34: =+'BS（org）'!K28+'BS（org）'!K29 -> 8.506 | K34: =+'BS（org）'!L28+'BS（org）'!L29 -> 10.566 | ... T34: =+'BS（org）'!U28+'BS（org）'!U29 -> 471.693 | U34: =+'BS（org）'!V28+'BS（org）'!V29+'BS（org）'!V42+'BS（org）'!V43 -> 525.589 | V34: =+'BS（org）'!W28+'BS（org）'!W29+'BS（org）'!W42+'BS（org）'!W43 -> 612.492 | W34: =+'BS（org）'!X28+'BS（org）'!X29+'BS（org）'!X42+'BS（org）'!X43 -> 228.812 | X34: =WC!X29 -> 235.90074 | Y34: =WC!Y29 -> 594.43889 | Z34: =WC!Z29 -> 639.68401 | AA34: =WC!AA29 -> 664.96023 | AB34: =WC!AB29 -> 720.5032 | AC34: =WC!AC29 -> 773.29187 | AD34: =WC!AD29 -> 823.8581 | AE34: =WC!AE29 -> 872.63977 | ... AG34: =WC!AG29 -> 966.2317
A35: =+'BS（org）'!A44 -> Tax recoverable | B35: 预付税款 | D35: =+'BS（org）'!E44 -> 20.697 | E35: =+'BS（org）'!F44 -> 31.146 | F35: =+'BS（org）'!G44 -> 2.414 | G35: =+'BS（org）'!H44 -> 4.832 | H35: =+'BS（org）'!I44 -> 4.099 | I35: =+'BS（org）'!J44 -> 6.217 | J35: =+'BS（org）'!K44 -> 15.054 | K35: =+'BS（org）'!L44 -> 18.697 | ... W35: =+'BS（org）'!X44 -> 913.65 | X35: =WC!X26 -> 935.5065 | Y35: =WC!Y26 -> 1034.5346 | Z35: =WC!Z26 -> 1117.8917 | AA35: =WC!AA26 -> 1224.5938 | AB35: =WC!AB26 -> 1325.4189 | AC35: =WC!AC26 -> 1421.5518 | AD35: =WC!AD26 -> 1513.9684 | AE35: =WC!AE26 -> 1603.4733 | ... AG35: =WC!AG26 -> 1776.2968
A36: Pledged bank deposits | B36: 已抵押银行存款 | D36: ='BS（org）'!E45 -> 41.783 | E36: ='BS（org）'!F45 -> 17.654 | F36: ='BS（org）'!G45 -> 16.69 | G36: ='BS（org）'!H45 -> 14.905 | H36: ='BS（org）'!I45 -> 6.42 | I36: ='BS（org）'!J45 -> 4.992 | J36: ='BS（org）'!K45 -> 1.291 | K36: ='BS（org）'!L45 -> 0.291 | ... W36: ='BS（org）'!X45 -> 0 | X36: =Financing!X53 -> 0 | Y36: =Financing!Y53 -> 0 | Z36: =Financing!Z53 -> 0 | AA36: =Financing!AA53 -> 0 | AB36: =Financing!AB53 -> 0 | AC36: =Financing!AC53 -> 0 | AD36: =Financing!AD53 -> 0 | AE36: =Financing!AE53 -> 0 | ... AG36: =Financing!AG53 -> 0
B37: 按公平值列入其他全面收益之金融资产 | N37: ='BS（org）'!O46 -> 0 | O37: ='BS（org）'!P46 -> 0 | P37: ='BS（org）'!Q46 -> 0 | Q37: ='BS（org）'!R46 -> 0 | R37: ='BS（org）'!S46 -> 0 | S37: ='BS（org）'!T46 -> 0 | T37: ='BS（org）'!U46 -> 0 | U37: ='BS（org）'!V46 -> 0 | ... W37: ='BS（org）'!X46 -> 0 | X37: =W37 -> 0 | Y37: =X37 -> 0 | Z37: =Y37 -> 0 | AA37: =Z37 -> 0 | AB37: =AA37 -> 0 | AC37: =AB37 -> 0 | AD37: =AC37 -> 0 | AE37: =AD37 -> 0 | ... AG37: =AF37 -> 0
A38: Deposits with financial institutions | B38: 金融机构之存款 | D38: ='BS（org）'!E47 -> 0 | E38: ='BS（org）'!F47 -> 5.305 | F38: ='BS（org）'!G47 -> 0.177 | G38: ='BS（org）'!H47 -> 1.446 | H38: ='BS（org）'!I47 -> 1.639 | I38: ='BS（org）'!J47 -> 0.848 | J38: ='BS（org）'!K47 -> 0.516 | K38: ='BS（org）'!L47 -> 0.162 | ... W38: ='BS（org）'!X47 -> 0 | X38: =W38 -> 0 | Y38: =X38 -> 0 | Z38: =Y38 -> 0 | AA38: =Z38 -> 0 | AB38: =AA38 -> 0 | AC38: =AB38 -> 0 | AD38: =AC38 -> 0 | AE38: =AD38 -> 0 | ... AG38: =AF38 -> 0
A39: Bank balances and cash | B39: 银行结余及现金 | D39: ='BS（org）'!E48 -> 1701.104 | E39: ='BS（org）'!F48 -> 1545 | F39: ='BS（org）'!G48 -> 1900.169 | G39: ='BS（org）'!H48 -> 5746.573 | H39: ='BS（org）'!I48 -> 3728.104 | I39: ='BS（org）'!J48 -> 5457.812 | J39: ='BS（org）'!K48 -> 6716.913 | K39: ='BS（org）'!L48 -> 8126.183 | ... W39: ='BS（org）'!X48 -> 30328.6 | X39: =CF!X36 -> 31766.567 | Y39: =CF!Y36 -> 31330.235 | Z39: =CF!Z36 -> 32454.597 | AA39: =CF!AA36 -> 30543.195 | AB39: =CF!AB36 -> 29565.249 | AC39: =CF!AC36 -> 29016.878 | AD39: =CF!AD36 -> 29170.609 | AE39: =CF!AE36 -> 31407.594 | ... AG39: =CF!AG36 -> 37939.176
A40: Loan to a joint venture | B40: 应收—合营企业借款 | D40: ='BS（org）'!E50 -> 0 | E40: ='BS（org）'!F50 -> 0 | F40: ='BS（org）'!G50 -> 0 | G40: ='BS（org）'!H50 -> 0 | H40: ='BS（org）'!I50 -> 0 | I40: ='BS（org）'!J50 -> 0 | J40: ='BS（org）'!K50 -> 0 | K40: ='BS（org）'!L50 -> 0 | ... W40: ='BS（org）'!X50 -> 12.34 | X40: =WC!X23 -> 12.722301 | Y40: =WC!Y23 -> 14.028724 | Z40: =WC!Z23 -> 15.096507 | AA40: =WC!AA23 -> 16.564859 | AB40: =WC!AB23 -> 17.948492 | AC40: =WC!AC23 -> 19.263514 | AD40: =WC!AD23 -> 20.523172 | AE40: =WC!AE23 -> 21.738375 | ... AG40: =WC!AG23 -> 24.069848
A41: Current Assets | B41: 流动资产合计 | D41: =SUM(D26:D40)-D33 -> 5220.34 | E41: =SUM(E26:E40)-E33 -> 6272.384 | F41: =SUM(F26:F40)-F33 -> 6915.104 | G41: =SUM(G26:G40)-G33 -> 10457.09 | H41: =SUM(H26:H40)-H33 -> 8916.767 | I41: =SUM(I26:I40)-I33 -> 14406.747 | J41: =SUM(J26:J40)-J33 -> 20437.89 | K41: =SUM(K26:K40)-K33 -> 29053.373 | ... AG41: =SUM(AG26:AG40)-AG33 -> 343093.83
A43: Total Assets | B43: 总资产 | D43: =D24+D41 -> 5408.14 | E43: =E24+E41 -> 7607.507 | F43: =F24+F41 -> 8983.664 | G43: =G24+G41 -> 13159.482 | H43: =H24+H41 -> 18679.422 | I43: =I24+I41 -> 26733.144 | J43: =J24+J41 -> 37212.795 | K43: =K24+K41 -> 52450.664 | ... AG43: =AG24+AG41 -> 499900.67
A44: (+/-%) | B44: (+/-%) | E44: =E43/D43-1 -> 0.40667716 | F44: =F43/E43-1 -> 0.18089461 | G44: =G43/F43-1 -> 0.46482348 | H44: =H43/G43-1 -> 0.41946484 | I44: =I43/H43-1 -> 0.43115478 | J44: =J43/I43-1 -> 0.39200967 | K44: =K43/J43-1 -> 0.40947929 | L44: =L43/K43-1 -> 0.26936633 | ... AG44: =AG43/AF43-1 -> 0.050147426
A46: Non-current Liabilities: | B46: 非流动负债：
A47: Deferred income | B47: 递延收入 | D47: ='BS（org）'!E57 -> 0 | E47: ='BS（org）'!F57 -> 118.593 | F47: ='BS（org）'!G57 -> 165.32 | G47: ='BS（org）'!H57 -> 180.48 | H47: ='BS（org）'!I57 -> 244.047 | I47: ='BS（org）'!J57 -> 421.938 | J47: ='BS（org）'!K57 -> 520.791 | K47: ='BS（org）'!L57 -> 638.802 | ... W47: ='BS（org）'!X57 -> 0
B48: 合约负债 | P48: ='BS（org）'!Q60 -> 740.01 | Q48: ='BS（org）'!R60 -> 688.21 | R48: ='BS（org）'!S60 -> 656.125 | S48: ='BS（org）'!T60 -> 667.106 | T48: ='BS（org）'!U60 -> 663.898 | U48: ='BS（org）'!V60 -> 591.473 | V48: ='BS（org）'!W60 -> 486.414 | W48: ='BS（org）'!X60 -> 391.48 | X48: =WC!X47 -> 337.06923 | Y48: =WC!Y47 -> 372.74971 | Z48: =WC!Z47 -> 402.78385 | AA48: =WC!AA47 -> 441.22933 | AB48: =WC!AB47 -> 477.55727 | AC48: =WC!AC47 -> 512.19462 | AD48: =WC!AD47 -> 545.49292 | AE48: =WC!AE47 -> 577.74211 | ... AG48: =WC!AG47 -> 640.0116
A49: Deferred tax liability | B49: 递延税项 | D49: ='BS（org）'!E58 -> 0 | E49: ='BS（org）'!F58 -> 67.437 | F49: ='BS（org）'!G58 -> 71.133 | G49: ='BS（org）'!H58 -> 93.219 | H49: ='BS（org）'!I58 -> 228.813 | I49: ='BS（org）'!J58 -> 276.014 | J49: ='BS（org）'!K58 -> 362.265 | K49: ='BS（org）'!L58 -> 398.32 | ... W49: ='BS（org）'!X58 -> 592.59 | X49: =W49*1.02 -> 604.4418 | Y49: =X49*1.02 -> 616.53064 | Z49: =Y49*1.02 -> 628.86125 | AA49: =Z49*1.02 -> 641.43847 | AB49: =AA49 -> 641.43847 | AC49: =AB49 -> 641.43847 | AD49: =AC49 -> 641.43847 | AE49: =AD49 -> 641.43847 | AF49: =AE49 -> 641.43847 | AG49: =AF49 -> 641.43847
A50: Borrowings | B50: 借款 | D50: ='BS（org）'!E59 -> 0 | E50: ='BS（org）'!F59 -> 21.165 | F50: ='BS（org）'!G59 -> 1000 | G50: ='BS（org）'!H59 -> 1601.931 | H50: ='BS（org）'!I59 -> 2880.362 | I50: ='BS（org）'!J59 -> 4961.268 | J50: ='BS（org）'!K59 -> 9996.359 | K50: ='BS（org）'!L59 -> 8600.258 | ... W50: ='BS（org）'!X59 -> 57061.6 | X50: =Financing!X8 -> 59388.346 | Y50: =Financing!Y8 -> 61761.628 | Z50: =Financing!Z8 -> 64182.375 | AA50: =Financing!AA8 -> 66651.537 | AB50: =Financing!AB8 -> 69170.082 | AC50: =Financing!AC8 -> 71738.998 | AD50: =Financing!AD8 -> 74359.293 | AE50: =Financing!AE8 -> 77031.993 | ... AG50: =Financing!AG8 -> 82538.825
A51: Obligations under finance leases | B51: 融资租赁承担 | D51: ='BS（org）'!E61 -> 0.278 | E51: ='BS（org）'!F61 -> 0.103 | F51: ='BS（org）'!G61 -> 0.074 | G51: ='BS（org）'!H61 -> 0 | H51: ='BS（org）'!I61 -> 0 | I51: ='BS（org）'!J61 -> 0 | J51: ='BS（org）'!K61 -> 4.938 | K51: ='BS（org）'!L61 -> 4.28 | ... W51: ='BS（org）'!X61 -> 203.13 | X51: =W51*0.99 -> 201.0987 | Y51: =X51*0.99 -> 199.08771 | Z51: =Y51*0.99 -> 197.09684 | AA51: =Z51*0.99 -> 195.12587 | AB51: =AA51*0.99 -> 193.17461 | AC51: =AB51*0.99 -> 191.24286 | AD51: =AC51*0.99 -> 189.33043 | AE51: =AD51*0.99 -> 187.43713 | ... AG51: =AF51*0.99 -> 183.70713
A52: Loan from intermediate holding company | B52: 向间接控股公司借款 | D52: ='BS（org）'!E62 -> 0 | E52: ='BS（org）'!F62 -> 0 | F52: ='BS（org）'!G62 -> 0 | G52: ='BS（org）'!H62 -> 1703.578 | H52: ='BS（org）'!I62 -> 2470.537 | I52: ='BS（org）'!J62 -> 0 | J52: ='BS（org）'!K62 -> 0 | K52: ='BS（org）'!L62 -> 0 | ... W52: ='BS（org）'!X62 -> 0 | X52: =W52 -> 0 | Y52: =X52 -> 0 | Z52: =Y52 -> 0 | AA52: =Z52 -> 0 | AB52: =AA52 -> 0 | AC52: =AB52 -> 0 | AD52: =AC52 -> 0 | AE52: =AD52 -> 0 | ... AG52: =AF52 -> 0
A53: Guaranteed notes payables | B53: 应付担保票据 | D53: ='BS（org）'!E63 -> 0 | E53: ='BS（org）'!F63 -> 0 | F53: ='BS（org）'!G63 -> 0 | G53: ='BS（org）'!H63 -> 0 | H53: ='BS（org）'!I63 -> 0 | I53: ='BS（org）'!J63 -> 0 | J53: ='BS（org）'!K63 -> 0 | K53: ='BS（org）'!L63 -> 3860.286 | ... W53: ='BS（org）'!X63 -> 12144.64 | X53: =W53*1.05 -> 12751.872 | Y53: =X53*1.05 -> 13389.466 | Z53: =Y53*1.05 -> 14058.939 | AA53: =Z53*1.05 -> 14761.886 | AB53: =AA53*1.05 -> 15499.98 | AC53: =AB53*1.05 -> 16274.979 | AD53: =AC53*1.05 -> 17088.728 | AE53: =AD53*1.05 -> 17943.164 | ... AG53: =AF53*1.05 -> 19782.339
B54: 定额退休福利承担 | N54: ='BS（org）'!O64 -> 0 | O54: ='BS（org）'!P64 -> 0 | P54: ='BS（org）'!Q64 -> 0 | Q54: ='BS（org）'!R64 -> 0 | R54: ='BS（org）'!S64 -> 0 | S54: ='BS（org）'!T64 -> 0 | T54: ='BS（org）'!U64 -> 0 | U54: ='BS（org）'!V64 -> 23.555 | ... W54: ='BS（org）'!X64 -> 34.53 | X54: =W54 -> 34.53 | Y54: =X54 -> 34.53 | Z54: =Y54 -> 34.53 | AA54: =Z54 -> 34.53 | AB54: =AA54 -> 34.53 | AC54: =AB54 -> 34.53 | AD54: =AC54 -> 34.53 | AE54: =AD54 -> 34.53 | ... AG54: =AF54 -> 34.53
A56: Non-current Liabilities | B56: 非流动负债合计 | D56: =SUM(D47:D53) -> 0.278 | E56: =SUM(E47:E53) -> 207.298 | F56: =SUM(F47:F53) -> 1236.527 | G56: =SUM(G47:G53) -> 3579.208 | H56: =SUM(H47:H53) -> 5823.759 | I56: =SUM(I47:I53) -> 5659.22 | J56: =SUM(J47:J53) -> 10884.353 | K56: =SUM(K47:K53) -> 13501.946 | ... M56: =SUM(M47:M53) -> 18112.61 | N56: =SUM(N47:N54) -> 20788.013 | O56: =SUM(O47:O54) -> 27247.65 | P56: =SUM(P47:P54) -> 39413.852 | Q56: =SUM(Q47:Q54) -> 39410.568 | R56: =SUM(R47:R54) -> 48592.268 | S56: =SUM(S47:S54) -> 60145.706 | T56: =SUM(T47:T54) -> 58229.033 | U56: =SUM(U47:U54) -> 59641.571 | ... AG56: =SUM(AG47:AG54) -> 103820.85
A57: Current Liabilities: | B57: 流动负债：
A58: Trade payables, other payables and accruals | B58: 贸易及其他应付款 | D58: =+'BS（org）'!E70 -> 3440.233 | E58: =+'BS（org）'!F70 -> 3759.933 | F58: =+'BS（org）'!G70 -> 3690.426 | G58: =+'BS（org）'!H70 -> 3552.277 | H58: =+'BS（org）'!I70 -> 4116.911 | I58: =+'BS（org）'!J70 -> 5175.888 | J58: =+'BS（org）'!K70 -> 6498.27 | K58: =+'BS（org）'!L70 -> 13019.734 | ... W58: =+'BS（org）'!X70 -> 96447.27 | X58: =WC!X38 -> 97569.739 | Y58: =WC!Y38 -> 106587.81 | Z58: =WC!Z38 -> 113760.34 | AA58: =WC!AA38 -> 123067.83 | AB58: =WC!AB38 -> 131521.87 | AC58: =WC!AC38 -> 139260.88 | AD58: =WC!AD38 -> 146397.03 | AE58: =WC!AE38 -> 153021.23 | ... AG58: =WC!AG38 -> 165014.85
A59: Amounts due to joint ventures and others | B59: 其他应付款 | D59: ='BS（org）'!E72+'BS（org）'!E73+'BS（org）'!E74+'BS（org）'!E75+'BS（org）'!E76+'BS（org）'!E77 -> 235.769 | E59: ='BS（org）'!F72+'BS（org）'!F73+'BS（org）'!F74+'BS（org）'!F75+'BS（org）'!F76+'BS（org）'!F77 -> 325.345 | F59: ='BS（org）'!G72+'BS（org）'!G73+'BS（org）'!G74+'BS（org）'!G75+'BS（org）'!G76+'BS（org）'!G77 -> 456.691 | G59: ='BS（org）'!H72+'BS（org）'!H73+'BS（org）'!H74+'BS（org）'!H75+'BS（org）'!H76+'BS（org）'!H77 -> 379.888 | H59: ='BS（org）'!I72+'BS（org）'!I73+'BS（org）'!I74+'BS（org）'!I75+'BS（org）'!I76+'BS（org）'!I77 -> 2621.18 | I59: ='BS（org）'!J72+'BS（org）'!J73+'BS（org）'!J74+'BS（org）'!J75+'BS（org）'!J76+'BS（org）'!J77 -> 2807.397 | J59: ='BS（org）'!K72+'BS（org）'!K73+'BS（org）'!K74+'BS（org）'!K75+'BS（org）'!K76+'BS（org）'!K77 -> 2974.048 | K59: ='BS（org）'!L72+'BS（org）'!L73+'BS（org）'!L74+'BS（org）'!L75+'BS（org）'!L76+'BS（org）'!L77 -> 477.505 | ... W59: ='BS（org）'!X72+'BS（org）'!X73+'BS（org）'!X74+'BS（org）'!X75+'BS（org）'!X76+'BS（org）'!X77 -> 1706.99 | X59: =WC!X56 -> 1747.8249 | Y59: =WC!Y56 -> 1932.841 | Z59: =WC!Z56 -> 2088.5788 | AA59: =WC!AA56 -> 2287.9324 | AB59: =WC!AB56 -> 2476.3058 | AC59: =WC!AC56 -> 2655.9129 | AD59: =WC!AD56 -> 2828.5765 | AE59: =WC!AE56 -> 2995.8001 | ... AG59: =WC!AG56 -> 3318.6898
A60: Amounts due to customers for contract work | B60: 应付客户合同工程款项 | D60: =+'BS（org）'!E68 -> 329.983 | E60: =+'BS（org）'!F68 -> 425.864 | F60: =+'BS（org）'!G68 -> 301.089 | G60: =+'BS（org）'!H68 -> 505.449 | H60: =+'BS（org）'!I68 -> 692.965 | I60: =+'BS（org）'!J68 -> 1282.035 | J60: =+'BS（org）'!K68 -> 1219.729 | K60: =+'BS（org）'!L68 -> 1903.378 | ... W60: =+'BS（org）'!X68 -> 0
B61: 合约负债 | O61: ='BS（org）'!P69 -> 7604.596 | P61: ='BS（org）'!Q69 -> 9027.486 | Q61: ='BS（org）'!R69 -> 7830.567 | R61: ='BS（org）'!S69 -> 8547.294 | S61: ='BS（org）'!T69 -> 9662.819 | T61: ='BS（org）'!U69 -> 8503.09 | U61: ='BS（org）'!V69 -> 9926.742 | V61: ='BS（org）'!W69 -> 8324.669 | W61: ='BS（org）'!X69 -> 9001.13 | X61: =WC!X44 -> 7750.0868 | Y61: =WC!Y44 -> 8308.4381 | Z61: =WC!Z44 -> 8694.739 | AA61: =WC!AA44 -> 9214.4728 | AB61: =WC!AB44 -> 9637.4206 | AC61: =WC!AC44 -> 9976.3642 | AD61: =WC!AD44 -> 10241.469 | AE61: =WC!AE44 -> 10440.799 | ... AG61: =WC!AG44 -> 10666.289
A62: Current tax payables | B62: 流动所得税负债 | D62: ='BS（org）'!E78 -> 49.443 | E62: ='BS（org）'!F78 -> 101.52 | F62: ='BS（org）'!G78 -> 114.622 | G62: ='BS（org）'!H78 -> 134.047 | H62: ='BS（org）'!I78 -> 112.362 | I62: ='BS（org）'!J78 -> 313.787 | J62: ='BS（org）'!K78 -> 594.57 | K62: ='BS（org）'!L78 -> 608.633 | ... W62: ='BS（org）'!X78 -> 6230.03 | X62: =WC!X50 -> 5905.1622 | Y62: =WC!Y50 -> 6006.1844 | Z62: =WC!Z50 -> 5923.8346 | AA62: =WC!AA50 -> 5868.9132 | AB62: =WC!AB50 -> 5680.6977 | AC62: =WC!AC50 -> 5372.5983 | AD62: =WC!AD50 -> 4954.9387 | AE62: =WC!AE50 -> 4435.5929 | ... AG62: =WC!AG50 -> 3114.0111
A63: Deposits received, advances from customers and others | B63: 其他负债 | D63: ='BS（org）'!E71+'BS（org）'!E81+'BS（org）'!E82 -> 378.233 | E63: ='BS（org）'!F71+'BS（org）'!F81+'BS（org）'!F82 -> 602.135 | F63: ='BS（org）'!G71+'BS（org）'!G81+'BS（org）'!G82 -> 623.924 | G63: ='BS（org）'!H71+'BS（org）'!H81+'BS（org）'!H82 -> 681.875 | H63: ='BS（org）'!I71+'BS（org）'!I81+'BS（org）'!I82 -> 688.845 | I63: ='BS（org）'!J71+'BS（org）'!J81+'BS（org）'!J82 -> 699.874 | J63: ='BS（org）'!K71+'BS（org）'!K81+'BS（org）'!K82 -> 1140.077 | K63: ='BS（org）'!L71+'BS（org）'!L81+'BS（org）'!L82 -> 1767.132 | ... W63: ='BS（org）'!X71+'BS（org）'!X81+'BS（org）'!X82 -> 302.73 | X63: =WC!X53 -> 309.97196 | Y63: =WC!Y53 -> 342.78405 | Z63: =WC!Z53 -> 370.40372 | AA63: =WC!AA53 -> 405.75854 | AB63: =WC!AB53 -> 439.16605 | AC63: =WC!AC53 -> 471.01887 | AD63: =WC!AD53 -> 501.64029 | AE63: =WC!AE53 -> 531.29695 | ... AG63: =WC!AG53 -> 588.56054
A64: Held for sale liability | B64: 与持作待售资产有关的负债 | D64: ='BS（org）'!E83 -> 0 | E64: ='BS（org）'!F83 -> 0 | F64: ='BS（org）'!G83 -> 0 | G64: ='BS（org）'!H83 -> 0 | H64: ='BS（org）'!I83 -> 0 | I64: ='BS（org）'!J83 -> 0 | J64: ='BS（org）'!K83 -> 0 | K64: ='BS（org）'!L83 -> 4723.121 | ... W64: ='BS（org）'!X83 -> 0 | X64: =W64 -> 0 | Y64: =X64 -> 0 | Z64: =Y64 -> 0 | AA64: =Z64 -> 0 | AB64: =AA64 -> 0 | AC64: =AB64 -> 0 | AD64: =AC64 -> 0 | AE64: =AD64 -> 0 | ... AG64: =AF64 -> 0
A65: Subtotal Payables | B65: 应付款项合计 | D65: =SUM(D58:D64) -> 4433.661 | E65: =SUM(E58:E64) -> 5214.797 | F65: =SUM(F58:F64) -> 5186.752 | G65: =SUM(G58:G64) -> 5253.536 | H65: =SUM(H58:H64) -> 8232.263 | I65: =SUM(I58:I64) -> 10278.981 | J65: =SUM(J58:J64) -> 12426.694 | K65: =SUM(K58:K64) -> 22499.503 | ... AG65: =SUM(AG58:AG64) -> 182702.4
A66: Borrowings | B66: 借款 | D66: ='BS（org）'!E79 -> 0 | E66: ='BS（org）'!F79 -> 29.729 | F66: ='BS（org）'!G79 -> 37.128 | G66: ='BS（org）'!H79 -> 21.956 | H66: ='BS（org）'!I79 -> 0 | I66: ='BS（org）'!J79 -> 357.716 | J66: ='BS（org）'!K79 -> 48.78 | K66: ='BS（org）'!L79 -> 261.889 | ... W66: ='BS（org）'!X79 -> 15096.37 | X66: =Financing!X14 -> 16932.996 | Y66: =Financing!Y14 -> 18806.355 | Z66: =Financing!Z14 -> 20717.181 | AA66: =Financing!AA14 -> 22666.224 | AB66: =Financing!AB14 -> 24654.247 | AC66: =Financing!AC14 -> 26682.031 | AD66: =Financing!AD14 -> 28750.37 | AE66: =Financing!AE14 -> 30860.077 | ... AG66: =Financing!AG14 -> 35206.915
B67: 应付担保票据及公司债券 | S67: ='BS（org）'!T84 -> 4286.155 | T67: ='BS（org）'!U84 -> 2980.184 | U67: ='BS（org）'!V84 -> 2753.304 | V67: ='BS（org）'!W84 -> 2460 | W67: ='BS（org）'!X84 -> 1099.76 | X67: =W67 -> 1099.76 | Y67: =X67 -> 1099.76 | Z67: =Y67 -> 1099.76 | AA67: =Z67 -> 1099.76 | AB67: =AA67 -> 1099.76 | AC67: =AB67 -> 1099.76 | AD67: =AC67 -> 1099.76 | AE67: =AD67 -> 1099.76 | ... AG67: =AF67 -> 1099.76
A68: Loan from intermediate holding company | B68: 向间接控股公司借款 | D68: =+'BS（org）'!E80 -> 0 | E68: =+'BS（org）'!F80 -> 0 | F68: =+'BS（org）'!G80 -> 0 | G68: =+'BS（org）'!H80 -> 0 | H68: =+'BS（org）'!I80 -> 0 | I68: =+'BS（org）'!J80 -> 940.151 | J68: =+'BS（org）'!K80 -> 0 | K68: =+'BS（org）'!L80 -> 0 | ... W68: =+'BS（org）'!X80 -> 0 | X68: =W68 -> 0 | Y68: =X68 -> 0 | Z68: =Y68 -> 0 | AA68: =Z68 -> 0 | AB68: =AA68 -> 0 | AC68: =AB68 -> 0 | AD68: =AC68 -> 0 | AE68: =AD68 -> 0 | ... AG68: =AF68 -> 0
A69: Current Liabilities | B69: 流动负债合计 | D69: =SUM(D58:D66)-D65 -> 4433.661 | E69: =SUM(E58:E66)-E65 -> 5244.526 | F69: =SUM(F58:F66)-F65 -> 5223.88 | G69: =SUM(G58:G68)-G65 -> 5275.492 | H69: =SUM(H58:H68)-H65 -> 8232.263 | I69: =SUM(I58:I68)-I65 -> 11576.848 | J69: =SUM(J58:J68)-J65 -> 12475.474 | K69: =SUM(K58:K68)-K65 -> 22761.392 | L69: =SUM(L58:L68)-L65 -> 31221.072 | M69: =SUM(M58:M68)-M65 -> 31706.669 | N69: =SUM(N58:N68)-N65 -> 39716.114 | ... AG69: =SUM(AG58:AG68)-AG65 -> 219009.07
A71: Total Liabilities | B71: 负债合计 | D71: =D56+D69 -> 4433.939 | E71: =E56+E69 -> 5451.824 | F71: =F56+F69 -> 6460.407 | G71: =G56+G69 -> 8854.7 | H71: =H56+H69 -> 14056.022 | I71: =I56+I69 -> 17236.068 | J71: =J56+J69 -> 23359.827 | K71: =K56+K69 -> 36263.338 | ... AG71: =AG56+AG69 -> 322829.92
A72: (+/-%) | B72: (+/-%) | E72: =E71/D71-1 -> 0.22956676 | F72: =F71/E71-1 -> 0.18499919 | G72: =G71/F71-1 -> 0.37061024 | H72: =H71/G71-1 -> 0.58740804 | I72: =I71/H71-1 -> 0.22624082 | J72: =J71/I71-1 -> 0.35528747 | K72: =K71/J71-1 -> 0.55238042 | L72: =L71/K71-1 -> 0.28453274 | ... AG72: =AG71/AF71-1 -> 0.036344223
A74: Equity | B74: 本公司权益：
A75: Share Capital | B75: 股本 | D75: ='BS（org）'!E91 -> 49.896 | E75: ='BS（org）'!F91 -> 60.821 | F75: ='BS（org）'!G91 -> 61.119 | G75: ='BS（org）'!H91 -> 73.864 | H75: ='BS（org）'!I91 -> 74.486 | I75: ='BS（org）'!J91 -> 89.668 | J75: ='BS（org）'!K91 -> 97.186 | K75: ='BS（org）'!L91 -> 97.219 | ... W75: ='BS（org）'!X91 -> 123.8 | X75: =W75 -> 123.8 | Y75: =X75 -> 123.8 | Z75: =Y75 -> 123.8 | AA75: =Z75 -> 123.8 | AB75: =AA75 -> 123.8 | AC75: =AB75 -> 123.8 | AD75: =AC75 -> 123.8 | AE75: =AD75 -> 123.8 | ... AG75: =AF75 -> 123.8
A76: Share Premium and reserves | B76: 股本溢价和储备 | D76: ='BS（org）'!E92 -> 924.305 | E76: ='BS（org）'!F92 -> 2094.862 | F76: ='BS（org）'!G92 -> 2462.138 | G76: ='BS（org）'!H92 -> 4230.918 | H76: ='BS（org）'!I92 -> 4544.964 | I76: ='BS（org）'!J92 -> 9400.684 | J76: ='BS（org）'!K92 -> 13412.638 | K76: ='BS（org）'!L92 -> 15836.417 | ... W76: ='BS（org）'!X92 -> 70278.73 | X76: =-(X75-W75)+W76+PL!X112-PL!W129+CF!X23 -> 76975.632 | Y76: =-(Y75-X75)+X76+PL!Y112-PL!X129+CF!Y23 -> 84088.841 | Z76: =-(Z75-Y75)+Y76+PL!Z112-PL!Y129+CF!Z23 -> 91422.952 | AA76: =-(AA75-Z75)+Z76+PL!AA112-PL!Z129+CF!AA23 -> 99824.096 | AB76: =-(AB75-AA75)+AA76+PL!AB112-PL!AA129+CF!AB23 -> 108945.29 | AC76: =-(AC75-AB75)+AB76+PL!AC112-PL!AB129+CF!AC23 -> 118737.69 | AD76: =-(AD75-AC75)+AC76+PL!AD112-PL!AC129+CF!AD23 -> 129162.44 | AE76: =-(AE75-AD75)+AD76+PL!AE112-PL!AD129+CF!AE23 -> 140196.04 | ... AG76: =-(AG75-AF75)+AF76+PL!AG112-PL!AF129+CF!AG23 -> 163960.73
A77: Attributable to Equity Holders of Company | B77: 本公司股东权益 | C77: ='BS（org）'!D95 -> 827.806 | D77: ='BS（org）'!E95 -> 974.201 | E77: ='BS（org）'!F95 -> 2155.683 | F77: =SUM(F75:F76) -> 2523.257 | G77: =SUM(G75:G76) -> 4304.782 | H77: =SUM(H75:H76) -> 4619.45 | I77: =SUM(I75:I76) -> 9490.352 | J77: =SUM(J75:J76) -> 13509.824 | K77: =SUM(K75:K76) -> 15933.636 | L77: =SUM(L75:L76) -> 19830.096 | M77: =SUM(M75:M76) -> 23184.554 | ... AG77: =SUM(AG75:AG76) -> 164084.53
A78: (+/-%) | B78: (+/-%) | E78: =E77/D77-1 -> 1.2127703 | F78: =F77/E77-1 -> 0.17051394 | G78: =G77/F77-1 -> 0.70604183 | H78: =H77/G77-1 -> 0.073097314 | I78: =I77/H77-1 -> 1.0544333 | J78: =J77/I77-1 -> 0.42353245 | K78: =K77/J77-1 -> 0.17941107 | L78: =L77/K77-1 -> 0.24454305 | ... AG78: =AG77/AF77-1 -> 0.080012445
A79: Attributable to perpetual securities | B79: 归属永续资本证券持有者 | P79: ='BS（org）'!Q96 -> 3878.468 | Q79: ='BS（org）'!R96 -> 7781.962 | R79: ='BS（org）'!S96 -> 7799.208 | S79: ='BS（org）'!T96 -> 7793.93 | T79: ='BS（org）'!U96 -> 7801.154 | U79: ='BS（org）'!V96 -> 10017.782 | V79: ='BS（org）'!W96 -> 6738.982 | W79: ='BS（org）'!X96 -> 6741.71 | X79: =W79 -> 6741.71 | Y79: =X79 -> 6741.71 | Z79: =Y79 -> 6741.71 | AA79: =Z79 -> 6741.71 | AB79: =AA79 -> 6741.71 | AC79: =AB79 -> 6741.71 | AD79: =AC79 -> 6741.71 | AE79: =AD79 -> 6741.71 | ... AG79: =AF79 -> 6741.71
